Workbook

Sheet Read me
A1: Panoptic SDG database: department mapping
A2: Consolidated 1 October 2026 as the clean source for the gigamap 3D dashboard.
A4: Basis | B4: The department workbook's 'Panoptic to SDG alignment' sheet, columns B (primary) and C (secondary): 66 target links to 35 targets across 12 SDGs.
A5: Removed | B5: The ten suggested targets, the system map v4 SDG comparison and the AU Agenda 2063 links. They stay in the comparison workbook if needed later.
A6: Prescripts | B6: The Sep 26 and 2024 prescript columns are merged into one de-duplicated list per sub-principle; acronyms MSDG, SDIP and UID confirmed by the department.
A7: Text | B7: Criterion and question wording follow the department workbook; spelling differences with the system map are resolved in its favour. Target and indicator text comes from the UNSD framework (after the 2026 refinement).
A8: Keys | B8: Sub-principle ID (PP1.1); Link ID = sub-principle|target (PP1.1|9.1); SDG number; target code; indicator code.
A9: Sheets | B9: Principles, Sub-principles, Target links (the core table), Indicator links, Projects, Project scores, SDG matrix, SDG goals, Coverage summary, SDG target coverage, Cleanup log.
A10: Formulas | B10: Counts, SDG lists and the matrix are formulas over 'Target links', so edits there flow through.
A11: Maintenance | B11: Edit this workbook only, mainly 'Target links' and 'Sub-principles'. Then run build.py, which checks the data, writes panoptic_dashboard_data.json and rebuilds the dashboard page.
A12: For the dashboard | B12: Principles → sub-principles (weights) → target links (primary/secondary) → indicators; SDG colours in 'SDG goals'.
A13: Scoring | B13: Add a project on 'Projects' (new ID), then one row per evaluator and sub-principle on 'Project scores' (score 1–5 in steps of 0.5). Score = Σ(score ÷ 5 × weight) ÷ Σ weight. 80–100% bankable portfolio; 50–79% return to step 2; below 50% rework.
A14: Coverage and gaps | B14: 'SDG target coverage' lists all 169 SDG targets with the sub-principles and principles that link to each, and flags gaps. 'Coverage summary' rolls this up per SDG. Both are formulas over 'Target links'; the amber columns are for the team's gap discussion and do not change the mapping until a link is added on 'Target links'.

Sheet Principles
A1: Principle | B1: Name | C1: Short name | D1: Sub-principles | E1: Weight | F1: SDGs | G1: Primary SDGs | H1: Target links | I1: Indicator links
A2: PP1 | B2: Innovation supporting equitable development | C2: Innovation | D2: =COUNTIF('Sub-principles'!$B$2:$B$11,A2) -> 2 | E2: =SUMIF('Sub-principles'!$B$2:$B$11,A2,'Sub-principles'!$E$2:$E$11) -> 16 | F2: =_xlfn.TEXTJOIN(", ",TRUE(),IF(COUNTIFS(tl_principle,$A2,tl_sdg,1)>0,"1",""),IF(COUNTIFS(tl_principle,$A2,tl_sdg,2)>0,"2",""),IF(COUNTIFS(tl_principle,$A2,tl_sdg,3)>0,"3",""),IF(COUNTIFS(tl_principle,$A2,tl_sdg,4)>0,"4",""),IF(COUNTIFS(tl_principle,$A2,tl_sdg,5)>0,"5",""),IF(COUNTIFS(tl_principle,$A2,tl_sdg,6)>0,"6",""),IF(COUNTIFS(tl_principle,$A2,tl_sdg,7)>0,"7",""),IF(COUNTIFS(tl_principle,$A2,tl_sdg,8)>0,"8",""),IF(COUNTIFS(tl_principle,$A2,tl_sdg,9)>0,"9",""),IF(COUNTIFS(tl_principle,$A2,tl_sdg,10)>0,"10",""),IF(COUNTIFS(tl_principle,$A2,tl_sdg,11)>0,"11",""),IF(COUNTIFS(tl_principle,$A2,tl_sdg,12)>0,"12",""),IF(COUNTIFS(tl_principle,$A2,tl_sdg,13)>0,"13",""),IF(COUNTIFS(tl_principle,$A2,tl_sdg,14)>0,"14",""),IF(COUNTIFS(tl_principle,$A2,tl_sdg,15)>0,"15",""),IF(COUNTIFS(tl_principle,$A2,tl_sdg,16)>0,"16",""),IF(COUNTIFS(tl_principle,$A2,tl_sdg,17)>0,"17","")) -> 8, 9, 11, 12, 16, 17 | G2: =_xlfn.TEXTJOIN(", ",TRUE(),IF(COUNTIFS(tl_principle,$A2,tl_sdg,1,tl_align,"Primary")>0,"1",""),IF(COUNTIFS(tl_principle,$A2,tl_sdg,2,tl_align,"Primary")>0,"2",""),IF(COUNTIFS(tl_principle,$A2,tl_sdg,3,tl_align,"Primary")>0,"3",""),IF(COUNTIFS(tl_principle,$A2,tl_sdg,4,tl_align,"Primary")>0,"4",""),IF(COUNTIFS(tl_principle,$A2,tl_sdg,5,tl_align,"Primary")>0,"5",""),IF(COUNTIFS(tl_principle,$A2,tl_sdg,6,tl_align,"Primary")>0,"6",""),IF(COUNTIFS(tl_principle,$A2,tl_sdg,7,tl_align,"Primary")>0,"7",""),IF(COUNTIFS(tl_principle,$A2,tl_sdg,8,tl_align,"Primary")>0,"8",""),IF(COUNTIFS(tl_principle,$A2,tl_sdg,9,tl_align,"Primary")>0,"9",""),IF(COUNTIFS(tl_principle,$A2,tl_sdg,10,tl_align,"Primary")>0,"10",""),IF(COUNTIFS(tl_principle,$A2,tl_sdg,11,tl_align,"Primary")>0,"11",""),IF(COUNTIFS(tl_principle,$A2,tl_sdg,12,tl_align,"Primary")>0,"12",""),IF(COUNTIFS(tl_principle,$A2,tl_sdg,13,tl_align,"Primary")>0,"13",""),IF(COUNTIFS(tl_principle,$A2,tl_sdg,14,tl_align,"Primary")>0,"14",""),IF(COUNTIFS(tl_principle,$A2,tl_sdg,15,tl_align,"Primary")>0,"15",""),IF(COUNTIFS(tl_principle,$A2,tl_sdg,16,tl_align,"Primary")>0,"16",""),IF(COUNTIFS(tl_principle,$A2,tl_sdg,17,tl_align,"Primary")>0,"17","")) -> 9 | H2: =COUNTIF(tl_principle,A2) -> 12 | I2: =SUMIF('Sub-principles'!$B$2:$B$11,A2,'Sub-principles'!$M$2:$M$11) -> 19
A3: PP2 | B3: Resilient, sustainable and regenerative systems | C3: Resilience | D3: =COUNTIF('Sub-principles'!$B$2:$B$11,A3) -> 3 | E3: =SUMIF('Sub-principles'!$B$2:$B$11,A3,'Sub-principles'!$E$2:$E$11) -> 24 | F3: =_xlfn.TEXTJOIN(", ",TRUE(),IF(COUNTIFS(tl_principle,$A3,tl_sdg,1)>0,"1",""),IF(COUNTIFS(tl_principle,$A3,tl_sdg,2)>0,"2",""),IF(COUNTIFS(tl_principle,$A3,tl_sdg,3)>0,"3",""),IF(COUNTIFS(tl_principle,$A3,tl_sdg,4)>0,"4",""),IF(COUNTIFS(tl_principle,$A3,tl_sdg,5)>0,"5",""),IF(COUNTIFS(tl_principle,$A3,tl_sdg,6)>0,"6",""),IF(COUNTIFS(tl_principle,$A3,tl_sdg,7)>0,"7",""),IF(COUNTIFS(tl_principle,$A3,tl_sdg,8)>0,"8",""),IF(COUNTIFS(tl_principle,$A3,tl_sdg,9)>0,"9",""),IF(COUNTIFS(tl_principle,$A3,tl_sdg,10)>0,"10",""),IF(COUNTIFS(tl_principle,$A3,tl_sdg,11)>0,"11",""),IF(COUNTIFS(tl_principle,$A3,tl_sdg,12)>0,"12",""),IF(COUNTIFS(tl_principle,$A3,tl_sdg,13)>0,"13",""),IF(COUNTIFS(tl_principle,$A3,tl_sdg,14)>0,"14",""),IF(COUNTIFS(tl_principle,$A3,tl_sdg,15)>0,"15",""),IF(COUNTIFS(tl_principle,$A3,tl_sdg,16)>0,"16",""),IF(COUNTIFS(tl_principle,$A3,tl_sdg,17)>0,"17","")) -> 6, 7, 8, 9, 11, 12, 13, 17 | G3: =_xlfn.TEXTJOIN(", ",TRUE(),IF(COUNTIFS(tl_principle,$A3,tl_sdg,1,tl_align,"Primary")>0,"1",""),IF(COUNTIFS(tl_principle,$A3,tl_sdg,2,tl_align,"Primary")>0,"2",""),IF(COUNTIFS(tl_principle,$A3,tl_sdg,3,tl_align,"Primary")>0,"3",""),IF(COUNTIFS(tl_principle,$A3,tl_sdg,4,tl_align,"Primary")>0,"4",""),IF(COUNTIFS(tl_principle,$A3,tl_sdg,5,tl_align,"Primary")>0,"5",""),IF(COUNTIFS(tl_principle,$A3,tl_sdg,6,tl_align,"Primary")>0,"6",""),IF(COUNTIFS(tl_principle,$A3,tl_sdg,7,tl_align,"Primary")>0,"7",""),IF(COUNTIFS(tl_principle,$A3,tl_sdg,8,tl_align,"Primary")>0,"8",""),IF(COUNTIFS(tl_principle,$A3,tl_sdg,9,tl_align,"Primary")>0,"9",""),IF(COUNTIFS(tl_principle,$A3,tl_sdg,10,tl_align,"Primary")>0,"10",""),IF(COUNTIFS(tl_principle,$A3,tl_sdg,11,tl_align,"Primary")>0,"11",""),IF(COUNTIFS(tl_principle,$A3,tl_sdg,12,tl_align,"Primary")>0,"12",""),IF(COUNTIFS(tl_principle,$A3,tl_sdg,13,tl_align,"Primary")>0,"13",""),IF(COUNTIFS(tl_principle,$A3,tl_sdg,14,tl_align,"Primary")>0,"14",""),IF(COUNTIFS(tl_principle,$A3,tl_sdg,15,tl_align,"Primary")>0,"15",""),IF(COUNTIFS(tl_principle,$A3,tl_sdg,16,tl_align,"Primary")>0,"16",""),IF(COUNTIFS(tl_principle,$A3,tl_sdg,17,tl_align,"Primary")>0,"17","")) -> 9, 11, 12, 13 | H3: =COUNTIF(tl_principle,A3) -> 23 | I3: =SUMIF('Sub-principles'!$B$2:$B$11,A3,'Sub-principles'!$M$2:$M$11) -> 39
A4: PP3 | B4: Stakeholder value, trust and spatial justice | C4: Stakeholder value | D4: =COUNTIF('Sub-principles'!$B$2:$B$11,A4) -> 3 | E4: =SUMIF('Sub-principles'!$B$2:$B$11,A4,'Sub-principles'!$E$2:$E$11) -> 32 | F4: =_xlfn.TEXTJOIN(", ",TRUE(),IF(COUNTIFS(tl_principle,$A4,tl_sdg,1)>0,"1",""),IF(COUNTIFS(tl_principle,$A4,tl_sdg,2)>0,"2",""),IF(COUNTIFS(tl_principle,$A4,tl_sdg,3)>0,"3",""),IF(COUNTIFS(tl_principle,$A4,tl_sdg,4)>0,"4",""),IF(COUNTIFS(tl_principle,$A4,tl_sdg,5)>0,"5",""),IF(COUNTIFS(tl_principle,$A4,tl_sdg,6)>0,"6",""),IF(COUNTIFS(tl_principle,$A4,tl_sdg,7)>0,"7",""),IF(COUNTIFS(tl_principle,$A4,tl_sdg,8)>0,"8",""),IF(COUNTIFS(tl_principle,$A4,tl_sdg,9)>0,"9",""),IF(COUNTIFS(tl_principle,$A4,tl_sdg,10)>0,"10",""),IF(COUNTIFS(tl_principle,$A4,tl_sdg,11)>0,"11",""),IF(COUNTIFS(tl_principle,$A4,tl_sdg,12)>0,"12",""),IF(COUNTIFS(tl_principle,$A4,tl_sdg,13)>0,"13",""),IF(COUNTIFS(tl_principle,$A4,tl_sdg,14)>0,"14",""),IF(COUNTIFS(tl_principle,$A4,tl_sdg,15)>0,"15",""),IF(COUNTIFS(tl_principle,$A4,tl_sdg,16)>0,"16",""),IF(COUNTIFS(tl_principle,$A4,tl_sdg,17)>0,"17","")) -> 1, 4, 8, 9, 10, 11, 12, 16, 17 | G4: =_xlfn.TEXTJOIN(", ",TRUE(),IF(COUNTIFS(tl_principle,$A4,tl_sdg,1,tl_align,"Primary")>0,"1",""),IF(COUNTIFS(tl_principle,$A4,tl_sdg,2,tl_align,"Primary")>0,"2",""),IF(COUNTIFS(tl_principle,$A4,tl_sdg,3,tl_align,"Primary")>0,"3",""),IF(COUNTIFS(tl_principle,$A4,tl_sdg,4,tl_align,"Primary")>0,"4",""),IF(COUNTIFS(tl_principle,$A4,tl_sdg,5,tl_align,"Primary")>0,"5",""),IF(COUNTIFS(tl_principle,$A4,tl_sdg,6,tl_align,"Primary")>0,"6",""),IF(COUNTIFS(tl_principle,$A4,tl_sdg,7,tl_align,"Primary")>0,"7",""),IF(COUNTIFS(tl_principle,$A4,tl_sdg,8,tl_align,"Primary")>0,"8",""),IF(COUNTIFS(tl_principle,$A4,tl_sdg,9,tl_align,"Primary")>0,"9",""),IF(COUNTIFS(tl_principle,$A4,tl_sdg,10,tl_align,"Primary")>0,"10",""),IF(COUNTIFS(tl_principle,$A4,tl_sdg,11,tl_align,"Primary")>0,"11",""),IF(COUNTIFS(tl_principle,$A4,tl_sdg,12,tl_align,"Primary")>0,"12",""),IF(COUNTIFS(tl_principle,$A4,tl_sdg,13,tl_align,"Primary")>0,"13",""),IF(COUNTIFS(tl_principle,$A4,tl_sdg,14,tl_align,"Primary")>0,"14",""),IF(COUNTIFS(tl_principle,$A4,tl_sdg,15,tl_align,"Primary")>0,"15",""),IF(COUNTIFS(tl_principle,$A4,tl_sdg,16,tl_align,"Primary")>0,"16",""),IF(COUNTIFS(tl_principle,$A4,tl_sdg,17,tl_align,"Primary")>0,"17","")) -> 10, 11, 17 | H4: =COUNTIF(tl_principle,A4) -> 20 | I4: =SUMIF('Sub-principles'!$B$2:$B$11,A4,'Sub-principles'!$M$2:$M$11) -> 29
A5: PP4 | B5: Transversal planning and governance | C5: Governance | D5: =COUNTIF('Sub-principles'!$B$2:$B$11,A5) -> 2 | E5: =SUMIF('Sub-principles'!$B$2:$B$11,A5,'Sub-principles'!$E$2:$E$11) -> 28 | F5: =_xlfn.TEXTJOIN(", ",TRUE(),IF(COUNTIFS(tl_principle,$A5,tl_sdg,1)>0,"1",""),IF(COUNTIFS(tl_principle,$A5,tl_sdg,2)>0,"2",""),IF(COUNTIFS(tl_principle,$A5,tl_sdg,3)>0,"3",""),IF(COUNTIFS(tl_principle,$A5,tl_sdg,4)>0,"4",""),IF(COUNTIFS(tl_principle,$A5,tl_sdg,5)>0,"5",""),IF(COUNTIFS(tl_principle,$A5,tl_sdg,6)>0,"6",""),IF(COUNTIFS(tl_principle,$A5,tl_sdg,7)>0,"7",""),IF(COUNTIFS(tl_principle,$A5,tl_sdg,8)>0,"8",""),IF(COUNTIFS(tl_principle,$A5,tl_sdg,9)>0,"9",""),IF(COUNTIFS(tl_principle,$A5,tl_sdg,10)>0,"10",""),IF(COUNTIFS(tl_principle,$A5,tl_sdg,11)>0,"11",""),IF(COUNTIFS(tl_principle,$A5,tl_sdg,12)>0,"12",""),IF(COUNTIFS(tl_principle,$A5,tl_sdg,13)>0,"13",""),IF(COUNTIFS(tl_principle,$A5,tl_sdg,14)>0,"14",""),IF(COUNTIFS(tl_principle,$A5,tl_sdg,15)>0,"15",""),IF(COUNTIFS(tl_principle,$A5,tl_sdg,16)>0,"16",""),IF(COUNTIFS(tl_principle,$A5,tl_sdg,17)>0,"17","")) -> 8, 10, 11, 16, 17 | G5: =_xlfn.TEXTJOIN(", ",TRUE(),IF(COUNTIFS(tl_principle,$A5,tl_sdg,1,tl_align,"Primary")>0,"1",""),IF(COUNTIFS(tl_principle,$A5,tl_sdg,2,tl_align,"Primary")>0,"2",""),IF(COUNTIFS(tl_principle,$A5,tl_sdg,3,tl_align,"Primary")>0,"3",""),IF(COUNTIFS(tl_principle,$A5,tl_sdg,4,tl_align,"Primary")>0,"4",""),IF(COUNTIFS(tl_principle,$A5,tl_sdg,5,tl_align,"Primary")>0,"5",""),IF(COUNTIFS(tl_principle,$A5,tl_sdg,6,tl_align,"Primary")>0,"6",""),IF(COUNTIFS(tl_principle,$A5,tl_sdg,7,tl_align,"Primary")>0,"7",""),IF(COUNTIFS(tl_principle,$A5,tl_sdg,8,tl_align,"Primary")>0,"8",""),IF(COUNTIFS(tl_principle,$A5,tl_sdg,9,tl_align,"Primary")>0,"9",""),IF(COUNTIFS(tl_principle,$A5,tl_sdg,10,tl_align,"Primary")>0,"10",""),IF(COUNTIFS(tl_principle,$A5,tl_sdg,11,tl_align,"Primary")>0,"11",""),IF(COUNTIFS(tl_principle,$A5,tl_sdg,12,tl_align,"Primary")>0,"12",""),IF(COUNTIFS(tl_principle,$A5,tl_sdg,13,tl_align,"Primary")>0,"13",""),IF(COUNTIFS(tl_principle,$A5,tl_sdg,14,tl_align,"Primary")>0,"14",""),IF(COUNTIFS(tl_principle,$A5,tl_sdg,15,tl_align,"Primary")>0,"15",""),IF(COUNTIFS(tl_principle,$A5,tl_sdg,16,tl_align,"Primary")>0,"16",""),IF(COUNTIFS(tl_principle,$A5,tl_sdg,17,tl_align,"Primary")>0,"17","")) -> 16 | H5: =COUNTIF(tl_principle,A5) -> 11 | I5: =SUMIF('Sub-principles'!$B$2:$B$11,A5,'Sub-principles'!$M$2:$M$11) -> 16
B6: Total | D6: =SUM(D2:D5) -> 10 | E6: =SUM(E2:E5) -> 100 | H6: =SUM(H2:H5) -> 66 | I6: =SUM(I2:I5) -> 103

Sheet Sub-principles
A1: Sub-principle | B1: Principle | C1: Name | D1: Short name | E1: Weight | F1: Key policy criterion | G1: Assessment question | H1: Primary SDGs | I1: Secondary SDGs | J1: Primary targets | K1: Secondary targets | L1: Target links | M1: Indicator links | N1: Alignment rationale | O1: Prescripts
A2: PP1.1 | B2: PP1 | C2: Infrastructure Design and Material Innovation | D2: Design & material innovation | E2: 8 | F2: Integrate prescribed planning frameworks to promote innovation in infrastructure design, and infrastructure material use aligned to national and local development goals. | G2: Does the project offer clear evidence of compliance to design innovations pertaining to key planning prescripts and construction material use across the 3 spheres of government? | H2: =_xlfn.TEXTJOIN(", ",TRUE(),IF(COUNTIFS(tl_sub,$A2,tl_sdg,1,tl_align,"Primary")>0,"1",""),IF(COUNTIFS(tl_sub,$A2,tl_sdg,2,tl_align,"Primary")>0,"2",""),IF(COUNTIFS(tl_sub,$A2,tl_sdg,3,tl_align,"Primary")>0,"3",""),IF(COUNTIFS(tl_sub,$A2,tl_sdg,4,tl_align,"Primary")>0,"4",""),IF(COUNTIFS(tl_sub,$A2,tl_sdg,5,tl_align,"Primary")>0,"5",""),IF(COUNTIFS(tl_sub,$A2,tl_sdg,6,tl_align,"Primary")>0,"6",""),IF(COUNTIFS(tl_sub,$A2,tl_sdg,7,tl_align,"Primary")>0,"7",""),IF(COUNTIFS(tl_sub,$A2,tl_sdg,8,tl_align,"Primary")>0,"8",""),IF(COUNTIFS(tl_sub,$A2,tl_sdg,9,tl_align,"Primary")>0,"9",""),IF(COUNTIFS(tl_sub,$A2,tl_sdg,10,tl_align,"Primary")>0,"10",""),IF(COUNTIFS(tl_sub,$A2,tl_sdg,11,tl_align,"Primary")>0,"11",""),IF(COUNTIFS(tl_sub,$A2,tl_sdg,12,tl_align,"Primary")>0,"12",""),IF(COUNTIFS(tl_sub,$A2,tl_sdg,13,tl_align,"Primary")>0,"13",""),IF(COUNTIFS(tl_sub,$A2,tl_sdg,14,tl_align,"Primary")>0,"14",""),IF(COUNTIFS(tl_sub,$A2,tl_sdg,15,tl_align,"Primary")>0,"15",""),IF(COUNTIFS(tl_sub,$A2,tl_sdg,16,tl_align,"Primary")>0,"16",""),IF(COUNTIFS(tl_sub,$A2,tl_sdg,17,tl_align,"Primary")>0,"17","")) -> 9 | I2: =_xlfn.TEXTJOIN(", ",TRUE(),IF(COUNTIFS(tl_sub,$A2,tl_sdg,1,tl_align,"Secondary")>0,"1",""),IF(COUNTIFS(tl_sub,$A2,tl_sdg,2,tl_align,"Secondary")>0,"2",""),IF(COUNTIFS(tl_sub,$A2,tl_sdg,3,tl_align,"Secondary")>0,"3",""),IF(COUNTIFS(tl_sub,$A2,tl_sdg,4,tl_align,"Secondary")>0,"4",""),IF(COUNTIFS(tl_sub,$A2,tl_sdg,5,tl_align,"Secondary")>0,"5",""),IF(COUNTIFS(tl_sub,$A2,tl_sdg,6,tl_align,"Secondary")>0,"6",""),IF(COUNTIFS(tl_sub,$A2,tl_sdg,7,tl_align,"Secondary")>0,"7",""),IF(COUNTIFS(tl_sub,$A2,tl_sdg,8,tl_align,"Secondary")>0,"8",""),IF(COUNTIFS(tl_sub,$A2,tl_sdg,9,tl_align,"Secondary")>0,"9",""),IF(COUNTIFS(tl_sub,$A2,tl_sdg,10,tl_align,"Secondary")>0,"10",""),IF(COUNTIFS(tl_sub,$A2,tl_sdg,11,tl_align,"Secondary")>0,"11",""),IF(COUNTIFS(tl_sub,$A2,tl_sdg,12,tl_align,"Secondary")>0,"12",""),IF(COUNTIFS(tl_sub,$A2,tl_sdg,13,tl_align,"Secondary")>0,"13",""),IF(COUNTIFS(tl_sub,$A2,tl_sdg,14,tl_align,"Secondary")>0,"14",""),IF(COUNTIFS(tl_sub,$A2,tl_sdg,15,tl_align,"Secondary")>0,"15",""),IF(COUNTIFS(tl_sub,$A2,tl_sdg,16,tl_align,"Secondary")>0,"16",""),IF(COUNTIFS(tl_sub,$A2,tl_sdg,17,tl_align,"Secondary")>0,"17","")) -> 8, 11, 12 | J2: 9.1, 9.4, 9.5 | K2: 8.2, 11.3, 12.2 | L2: =COUNTIF(tl_sub,A2) -> 6 | M2: =COUNTIF(il_sub,A2) -> 10 | N2: Innovative, sustainable infrastructure design and material use improve resource efficiency while aligning projects with national and local development plans. | O2: NT/PFMA; MTEF; NDP; NIP 2050; NSDF; NLTF; WCSDF 2035; MSDF; PLTF; PSP 2025-2030; G4J; WCIF; WCEIIF; CC response strategy; Green BCSA; SABS; BSA; NDC; CCA 2024; JTF; WCCCRS; MTSF; CIDB; CIF; CEF; C-AMP (GIAMA); U-AMP (GIAMA).
A3: PP1.2 | B3: PP1 | C3: ICT Innovation | D3: ICT innovation | E3: 8 | F3: Promote innovation in ICT to enhance ease of doing business and government processes, driving economic and governance efficiencies. | G3: Does the project offer clear evidence of compliance to ICT innovations and/or efficiencies like ease-of-doing-business and/or ease-of-doing-government? | H3: =_xlfn.TEXTJOIN(", ",TRUE(),IF(COUNTIFS(tl_sub,$A3,tl_sdg,1,tl_align,"Primary")>0,"1",""),IF(COUNTIFS(tl_sub,$A3,tl_sdg,2,tl_align,"Primary")>0,"2",""),IF(COUNTIFS(tl_sub,$A3,tl_sdg,3,tl_align,"Primary")>0,"3",""),IF(COUNTIFS(tl_sub,$A3,tl_sdg,4,tl_align,"Primary")>0,"4",""),IF(COUNTIFS(tl_sub,$A3,tl_sdg,5,tl_align,"Primary")>0,"5",""),IF(COUNTIFS(tl_sub,$A3,tl_sdg,6,tl_align,"Primary")>0,"6",""),IF(COUNTIFS(tl_sub,$A3,tl_sdg,7,tl_align,"Primary")>0,"7",""),IF(COUNTIFS(tl_sub,$A3,tl_sdg,8,tl_align,"Primary")>0,"8",""),IF(COUNTIFS(tl_sub,$A3,tl_sdg,9,tl_align,"Primary")>0,"9",""),IF(COUNTIFS(tl_sub,$A3,tl_sdg,10,tl_align,"Primary")>0,"10",""),IF(COUNTIFS(tl_sub,$A3,tl_sdg,11,tl_align,"Primary")>0,"11",""),IF(COUNTIFS(tl_sub,$A3,tl_sdg,12,tl_align,"Primary")>0,"12",""),IF(COUNTIFS(tl_sub,$A3,tl_sdg,13,tl_align,"Primary")>0,"13",""),IF(COUNTIFS(tl_sub,$A3,tl_sdg,14,tl_align,"Primary")>0,"14",""),IF(COUNTIFS(tl_sub,$A3,tl_sdg,15,tl_align,"Primary")>0,"15",""),IF(COUNTIFS(tl_sub,$A3,tl_sdg,16,tl_align,"Primary")>0,"16",""),IF(COUNTIFS(tl_sub,$A3,tl_sdg,17,tl_align,"Primary")>0,"17","")) -> 9 | I3: =_xlfn.TEXTJOIN(", ",TRUE(),IF(COUNTIFS(tl_sub,$A3,tl_sdg,1,tl_align,"Secondary")>0,"1",""),IF(COUNTIFS(tl_sub,$A3,tl_sdg,2,tl_align,"Secondary")>0,"2",""),IF(COUNTIFS(tl_sub,$A3,tl_sdg,3,tl_align,"Secondary")>0,"3",""),IF(COUNTIFS(tl_sub,$A3,tl_sdg,4,tl_align,"Secondary")>0,"4",""),IF(COUNTIFS(tl_sub,$A3,tl_sdg,5,tl_align,"Secondary")>0,"5",""),IF(COUNTIFS(tl_sub,$A3,tl_sdg,6,tl_align,"Secondary")>0,"6",""),IF(COUNTIFS(tl_sub,$A3,tl_sdg,7,tl_align,"Secondary")>0,"7",""),IF(COUNTIFS(tl_sub,$A3,tl_sdg,8,tl_align,"Secondary")>0,"8",""),IF(COUNTIFS(tl_sub,$A3,tl_sdg,9,tl_align,"Secondary")>0,"9",""),IF(COUNTIFS(tl_sub,$A3,tl_sdg,10,tl_align,"Secondary")>0,"10",""),IF(COUNTIFS(tl_sub,$A3,tl_sdg,11,tl_align,"Secondary")>0,"11",""),IF(COUNTIFS(tl_sub,$A3,tl_sdg,12,tl_align,"Secondary")>0,"12",""),IF(COUNTIFS(tl_sub,$A3,tl_sdg,13,tl_align,"Secondary")>0,"13",""),IF(COUNTIFS(tl_sub,$A3,tl_sdg,14,tl_align,"Secondary")>0,"14",""),IF(COUNTIFS(tl_sub,$A3,tl_sdg,15,tl_align,"Secondary")>0,"15",""),IF(COUNTIFS(tl_sub,$A3,tl_sdg,16,tl_align,"Secondary")>0,"16",""),IF(COUNTIFS(tl_sub,$A3,tl_sdg,17,tl_align,"Secondary")>0,"17","")) -> 8, 16, 17 | J3: 9.5, 9.c | K3: 8.2, 16.6, 16.10, 17.8 | L3: =COUNTIF(tl_sub,A3) -> 6 | M3: =COUNTIF(il_sub,A3) -> 9 | N3: Digital infrastructure and ICT innovation improve business processes, public-service delivery, information access and institutional efficiency. | O3: NDP; SITA; G4J; WCIF; PSP 2025-2030; PLTF; MTSF.
A4: PP2.1 | B4: PP2 | C4: Resilient Infrastructure Design and Risk Mitigation | D4: Resilient design & risk | E4: 8 | F4: Align infrastructure design with resilience principles to address climate change, sustainability, and regenerative practices. It must also address water, energy, and disaster management through proactive risk mitigation strategies and policies. | G4: Does the project offer clear evidence of innovations that foster resilience and regenerative aspects of the infrastructure value chain; and are there risk mitigation strategies in place? | H4: =_xlfn.TEXTJOIN(", ",TRUE(),IF(COUNTIFS(tl_sub,$A4,tl_sdg,1,tl_align,"Primary")>0,"1",""),IF(COUNTIFS(tl_sub,$A4,tl_sdg,2,tl_align,"Primary")>0,"2",""),IF(COUNTIFS(tl_sub,$A4,tl_sdg,3,tl_align,"Primary")>0,"3",""),IF(COUNTIFS(tl_sub,$A4,tl_sdg,4,tl_align,"Primary")>0,"4",""),IF(COUNTIFS(tl_sub,$A4,tl_sdg,5,tl_align,"Primary")>0,"5",""),IF(COUNTIFS(tl_sub,$A4,tl_sdg,6,tl_align,"Primary")>0,"6",""),IF(COUNTIFS(tl_sub,$A4,tl_sdg,7,tl_align,"Primary")>0,"7",""),IF(COUNTIFS(tl_sub,$A4,tl_sdg,8,tl_align,"Primary")>0,"8",""),IF(COUNTIFS(tl_sub,$A4,tl_sdg,9,tl_align,"Primary")>0,"9",""),IF(COUNTIFS(tl_sub,$A4,tl_sdg,10,tl_align,"Primary")>0,"10",""),IF(COUNTIFS(tl_sub,$A4,tl_sdg,11,tl_align,"Primary")>0,"11",""),IF(COUNTIFS(tl_sub,$A4,tl_sdg,12,tl_align,"Primary")>0,"12",""),IF(COUNTIFS(tl_sub,$A4,tl_sdg,13,tl_align,"Primary")>0,"13",""),IF(COUNTIFS(tl_sub,$A4,tl_sdg,14,tl_align,"Primary")>0,"14",""),IF(COUNTIFS(tl_sub,$A4,tl_sdg,15,tl_align,"Primary")>0,"15",""),IF(COUNTIFS(tl_sub,$A4,tl_sdg,16,tl_align,"Primary")>0,"16",""),IF(COUNTIFS(tl_sub,$A4,tl_sdg,17,tl_align,"Primary")>0,"17","")) -> 9, 13 | I4: =_xlfn.TEXTJOIN(", ",TRUE(),IF(COUNTIFS(tl_sub,$A4,tl_sdg,1,tl_align,"Secondary")>0,"1",""),IF(COUNTIFS(tl_sub,$A4,tl_sdg,2,tl_align,"Secondary")>0,"2",""),IF(COUNTIFS(tl_sub,$A4,tl_sdg,3,tl_align,"Secondary")>0,"3",""),IF(COUNTIFS(tl_sub,$A4,tl_sdg,4,tl_align,"Secondary")>0,"4",""),IF(COUNTIFS(tl_sub,$A4,tl_sdg,5,tl_align,"Secondary")>0,"5",""),IF(COUNTIFS(tl_sub,$A4,tl_sdg,6,tl_align,"Secondary")>0,"6",""),IF(COUNTIFS(tl_sub,$A4,tl_sdg,7,tl_align,"Secondary")>0,"7",""),IF(COUNTIFS(tl_sub,$A4,tl_sdg,8,tl_align,"Secondary")>0,"8",""),IF(COUNTIFS(tl_sub,$A4,tl_sdg,9,tl_align,"Secondary")>0,"9",""),IF(COUNTIFS(tl_sub,$A4,tl_sdg,10,tl_align,"Secondary")>0,"10",""),IF(COUNTIFS(tl_sub,$A4,tl_sdg,11,tl_align,"Secondary")>0,"11",""),IF(COUNTIFS(tl_sub,$A4,tl_sdg,12,tl_align,"Secondary")>0,"12",""),IF(COUNTIFS(tl_sub,$A4,tl_sdg,13,tl_align,"Secondary")>0,"13",""),IF(COUNTIFS(tl_sub,$A4,tl_sdg,14,tl_align,"Secondary")>0,"14",""),IF(COUNTIFS(tl_sub,$A4,tl_sdg,15,tl_align,"Secondary")>0,"15",""),IF(COUNTIFS(tl_sub,$A4,tl_sdg,16,tl_align,"Secondary")>0,"16",""),IF(COUNTIFS(tl_sub,$A4,tl_sdg,17,tl_align,"Secondary")>0,"17","")) -> 6, 7, 11, 12 | J4: 9.1, 13.1, 13.2 | K4: 6.4, 6.5, 7.2, 7.3, 11.5, 11.b, 12.2 | L4: =COUNTIF(tl_sub,A4) -> 10 | M4: =COUNTIF(il_sub,A4) -> 20 | N4: Directly addresses climate resilience, disaster-risk reduction, water and energy management, sustainability and regenerative design. | O4: WCIF; PLTF; NDC; CCA 2024; JTF; WCCCRS; WCEIIF; Green BCSA; UIDG; CIDB; CIF; CEF; IGM; C-AMP (GIAMA); U-AMP (GIAMA).
A5: PP2.2 | B5: PP2 | C5: Infrastructure Planning for Systemic Alignment | D5: Systemic planning alignment | E5: 8 | F5: Integrated and collaborative planning ensures alignment across spatial, economic, and environmental systems, serving as the foundation for sustainable infrastructure value chains and ecosystems. | G5: Does the project offer clear evidence of alignment, integration and collaboration across the WC infrastructure ecosystem? | H5: =_xlfn.TEXTJOIN(", ",TRUE(),IF(COUNTIFS(tl_sub,$A5,tl_sdg,1,tl_align,"Primary")>0,"1",""),IF(COUNTIFS(tl_sub,$A5,tl_sdg,2,tl_align,"Primary")>0,"2",""),IF(COUNTIFS(tl_sub,$A5,tl_sdg,3,tl_align,"Primary")>0,"3",""),IF(COUNTIFS(tl_sub,$A5,tl_sdg,4,tl_align,"Primary")>0,"4",""),IF(COUNTIFS(tl_sub,$A5,tl_sdg,5,tl_align,"Primary")>0,"5",""),IF(COUNTIFS(tl_sub,$A5,tl_sdg,6,tl_align,"Primary")>0,"6",""),IF(COUNTIFS(tl_sub,$A5,tl_sdg,7,tl_align,"Primary")>0,"7",""),IF(COUNTIFS(tl_sub,$A5,tl_sdg,8,tl_align,"Primary")>0,"8",""),IF(COUNTIFS(tl_sub,$A5,tl_sdg,9,tl_align,"Primary")>0,"9",""),IF(COUNTIFS(tl_sub,$A5,tl_sdg,10,tl_align,"Primary")>0,"10",""),IF(COUNTIFS(tl_sub,$A5,tl_sdg,11,tl_align,"Primary")>0,"11",""),IF(COUNTIFS(tl_sub,$A5,tl_sdg,12,tl_align,"Primary")>0,"12",""),IF(COUNTIFS(tl_sub,$A5,tl_sdg,13,tl_align,"Primary")>0,"13",""),IF(COUNTIFS(tl_sub,$A5,tl_sdg,14,tl_align,"Primary")>0,"14",""),IF(COUNTIFS(tl_sub,$A5,tl_sdg,15,tl_align,"Primary")>0,"15",""),IF(COUNTIFS(tl_sub,$A5,tl_sdg,16,tl_align,"Primary")>0,"16",""),IF(COUNTIFS(tl_sub,$A5,tl_sdg,17,tl_align,"Primary")>0,"17","")) -> 11 | I5: =_xlfn.TEXTJOIN(", ",TRUE(),IF(COUNTIFS(tl_sub,$A5,tl_sdg,1,tl_align,"Secondary")>0,"1",""),IF(COUNTIFS(tl_sub,$A5,tl_sdg,2,tl_align,"Secondary")>0,"2",""),IF(COUNTIFS(tl_sub,$A5,tl_sdg,3,tl_align,"Secondary")>0,"3",""),IF(COUNTIFS(tl_sub,$A5,tl_sdg,4,tl_align,"Secondary")>0,"4",""),IF(COUNTIFS(tl_sub,$A5,tl_sdg,5,tl_align,"Secondary")>0,"5",""),IF(COUNTIFS(tl_sub,$A5,tl_sdg,6,tl_align,"Secondary")>0,"6",""),IF(COUNTIFS(tl_sub,$A5,tl_sdg,7,tl_align,"Secondary")>0,"7",""),IF(COUNTIFS(tl_sub,$A5,tl_sdg,8,tl_align,"Secondary")>0,"8",""),IF(COUNTIFS(tl_sub,$A5,tl_sdg,9,tl_align,"Secondary")>0,"9",""),IF(COUNTIFS(tl_sub,$A5,tl_sdg,10,tl_align,"Secondary")>0,"10",""),IF(COUNTIFS(tl_sub,$A5,tl_sdg,11,tl_align,"Secondary")>0,"11",""),IF(COUNTIFS(tl_sub,$A5,tl_sdg,12,tl_align,"Secondary")>0,"12",""),IF(COUNTIFS(tl_sub,$A5,tl_sdg,13,tl_align,"Secondary")>0,"13",""),IF(COUNTIFS(tl_sub,$A5,tl_sdg,14,tl_align,"Secondary")>0,"14",""),IF(COUNTIFS(tl_sub,$A5,tl_sdg,15,tl_align,"Secondary")>0,"15",""),IF(COUNTIFS(tl_sub,$A5,tl_sdg,16,tl_align,"Secondary")>0,"16",""),IF(COUNTIFS(tl_sub,$A5,tl_sdg,17,tl_align,"Secondary")>0,"17","")) -> 9, 13, 17 | J5: 11.3, 11.a | K5: 9.1, 13.2, 17.14, 17.16, 17.17 | L5: =COUNTIF(tl_sub,A5) -> 7 | M5: =COUNTIF(il_sub,A5) -> 10 | N5: Integrated spatial, economic and environmental planning creates coherent infrastructure systems and sustainable value chains. | O5: NT/PFMA; MTEF; NDP; NIP 2050; NSDF; NLTF; WCSDF 2035; MSDF; PLTF; PSP 2025-2030; G4J; WCIF; IUDF; IDWRP; EPWP; GPS (DEA&DP 2024); MFMA; CEF; UIDG; COGTA; CIDB; LTFP; IGM; SDBIP; C-AMP (GIAMA); U-AMP (GIAMA).
A6: PP2.3 | B6: PP2 | C6: Localised Resource Utilisation | D6: Localised resources | E6: 8 | F6: Reduce socio-ecological costs by sourcing inputs locally and minimising resource transportation needs (this includes consideration of Biodiversity Offsets). | G6: Does the project offer clear evidence of innovations that foster resilience, sustainable and regenerative aspects in the infrastructure and project value chains at a local level? | H6: =_xlfn.TEXTJOIN(", ",TRUE(),IF(COUNTIFS(tl_sub,$A6,tl_sdg,1,tl_align,"Primary")>0,"1",""),IF(COUNTIFS(tl_sub,$A6,tl_sdg,2,tl_align,"Primary")>0,"2",""),IF(COUNTIFS(tl_sub,$A6,tl_sdg,3,tl_align,"Primary")>0,"3",""),IF(COUNTIFS(tl_sub,$A6,tl_sdg,4,tl_align,"Primary")>0,"4",""),IF(COUNTIFS(tl_sub,$A6,tl_sdg,5,tl_align,"Primary")>0,"5",""),IF(COUNTIFS(tl_sub,$A6,tl_sdg,6,tl_align,"Primary")>0,"6",""),IF(COUNTIFS(tl_sub,$A6,tl_sdg,7,tl_align,"Primary")>0,"7",""),IF(COUNTIFS(tl_sub,$A6,tl_sdg,8,tl_align,"Primary")>0,"8",""),IF(COUNTIFS(tl_sub,$A6,tl_sdg,9,tl_align,"Primary")>0,"9",""),IF(COUNTIFS(tl_sub,$A6,tl_sdg,10,tl_align,"Primary")>0,"10",""),IF(COUNTIFS(tl_sub,$A6,tl_sdg,11,tl_align,"Primary")>0,"11",""),IF(COUNTIFS(tl_sub,$A6,tl_sdg,12,tl_align,"Primary")>0,"12",""),IF(COUNTIFS(tl_sub,$A6,tl_sdg,13,tl_align,"Primary")>0,"13",""),IF(COUNTIFS(tl_sub,$A6,tl_sdg,14,tl_align,"Primary")>0,"14",""),IF(COUNTIFS(tl_sub,$A6,tl_sdg,15,tl_align,"Primary")>0,"15",""),IF(COUNTIFS(tl_sub,$A6,tl_sdg,16,tl_align,"Primary")>0,"16",""),IF(COUNTIFS(tl_sub,$A6,tl_sdg,17,tl_align,"Primary")>0,"17","")) -> 12 | I6: =_xlfn.TEXTJOIN(", ",TRUE(),IF(COUNTIFS(tl_sub,$A6,tl_sdg,1,tl_align,"Secondary")>0,"1",""),IF(COUNTIFS(tl_sub,$A6,tl_sdg,2,tl_align,"Secondary")>0,"2",""),IF(COUNTIFS(tl_sub,$A6,tl_sdg,3,tl_align,"Secondary")>0,"3",""),IF(COUNTIFS(tl_sub,$A6,tl_sdg,4,tl_align,"Secondary")>0,"4",""),IF(COUNTIFS(tl_sub,$A6,tl_sdg,5,tl_align,"Secondary")>0,"5",""),IF(COUNTIFS(tl_sub,$A6,tl_sdg,6,tl_align,"Secondary")>0,"6",""),IF(COUNTIFS(tl_sub,$A6,tl_sdg,7,tl_align,"Secondary")>0,"7",""),IF(COUNTIFS(tl_sub,$A6,tl_sdg,8,tl_align,"Secondary")>0,"8",""),IF(COUNTIFS(tl_sub,$A6,tl_sdg,9,tl_align,"Secondary")>0,"9",""),IF(COUNTIFS(tl_sub,$A6,tl_sdg,10,tl_align,"Secondary")>0,"10",""),IF(COUNTIFS(tl_sub,$A6,tl_sdg,11,tl_align,"Secondary")>0,"11",""),IF(COUNTIFS(tl_sub,$A6,tl_sdg,12,tl_align,"Secondary")>0,"12",""),IF(COUNTIFS(tl_sub,$A6,tl_sdg,13,tl_align,"Secondary")>0,"13",""),IF(COUNTIFS(tl_sub,$A6,tl_sdg,14,tl_align,"Secondary")>0,"14",""),IF(COUNTIFS(tl_sub,$A6,tl_sdg,15,tl_align,"Secondary")>0,"15",""),IF(COUNTIFS(tl_sub,$A6,tl_sdg,16,tl_align,"Secondary")>0,"16",""),IF(COUNTIFS(tl_sub,$A6,tl_sdg,17,tl_align,"Secondary")>0,"17","")) -> 8, 9, 11, 13 | J6: 12.2, 12.7 | K6: 8.3, 9.4, 11.6, 13.2 | L6: =COUNTIF(tl_sub,A6) -> 6 | M6: =COUNTIF(il_sub,A6) -> 9 | N6: Local sourcing and sustainable procurement reduce transport impacts, embodied emissions and resource costs while stimulating local economies. | O6: NDC; CCA 2024; JTF; Green BCSA; King IV; WCIF; WCCCRS; WCEIIF; CIDB; C-AMP (GIAMA); U-AMP (GIAMA).
A7: PP3.1 | B7: PP3 | C7: Geolocation relative to Spatial Zones | D7: Spatial-zone geolocation | E7: 8 | F7: Align infrastructure development to counter spatial inaccessibility via equitable access, capacity building and knowledge management of spatial justice. | G7: Does the project offer clear evidence of sustainable stakeholder value fostering trust in context of spatial justice and improved access to infrastructure? | H7: =_xlfn.TEXTJOIN(", ",TRUE(),IF(COUNTIFS(tl_sub,$A7,tl_sdg,1,tl_align,"Primary")>0,"1",""),IF(COUNTIFS(tl_sub,$A7,tl_sdg,2,tl_align,"Primary")>0,"2",""),IF(COUNTIFS(tl_sub,$A7,tl_sdg,3,tl_align,"Primary")>0,"3",""),IF(COUNTIFS(tl_sub,$A7,tl_sdg,4,tl_align,"Primary")>0,"4",""),IF(COUNTIFS(tl_sub,$A7,tl_sdg,5,tl_align,"Primary")>0,"5",""),IF(COUNTIFS(tl_sub,$A7,tl_sdg,6,tl_align,"Primary")>0,"6",""),IF(COUNTIFS(tl_sub,$A7,tl_sdg,7,tl_align,"Primary")>0,"7",""),IF(COUNTIFS(tl_sub,$A7,tl_sdg,8,tl_align,"Primary")>0,"8",""),IF(COUNTIFS(tl_sub,$A7,tl_sdg,9,tl_align,"Primary")>0,"9",""),IF(COUNTIFS(tl_sub,$A7,tl_sdg,10,tl_align,"Primary")>0,"10",""),IF(COUNTIFS(tl_sub,$A7,tl_sdg,11,tl_align,"Primary")>0,"11",""),IF(COUNTIFS(tl_sub,$A7,tl_sdg,12,tl_align,"Primary")>0,"12",""),IF(COUNTIFS(tl_sub,$A7,tl_sdg,13,tl_align,"Primary")>0,"13",""),IF(COUNTIFS(tl_sub,$A7,tl_sdg,14,tl_align,"Primary")>0,"14",""),IF(COUNTIFS(tl_sub,$A7,tl_sdg,15,tl_align,"Primary")>0,"15",""),IF(COUNTIFS(tl_sub,$A7,tl_sdg,16,tl_align,"Primary")>0,"16",""),IF(COUNTIFS(tl_sub,$A7,tl_sdg,17,tl_align,"Primary")>0,"17","")) -> 11 | I7: =_xlfn.TEXTJOIN(", ",TRUE(),IF(COUNTIFS(tl_sub,$A7,tl_sdg,1,tl_align,"Secondary")>0,"1",""),IF(COUNTIFS(tl_sub,$A7,tl_sdg,2,tl_align,"Secondary")>0,"2",""),IF(COUNTIFS(tl_sub,$A7,tl_sdg,3,tl_align,"Secondary")>0,"3",""),IF(COUNTIFS(tl_sub,$A7,tl_sdg,4,tl_align,"Secondary")>0,"4",""),IF(COUNTIFS(tl_sub,$A7,tl_sdg,5,tl_align,"Secondary")>0,"5",""),IF(COUNTIFS(tl_sub,$A7,tl_sdg,6,tl_align,"Secondary")>0,"6",""),IF(COUNTIFS(tl_sub,$A7,tl_sdg,7,tl_align,"Secondary")>0,"7",""),IF(COUNTIFS(tl_sub,$A7,tl_sdg,8,tl_align,"Secondary")>0,"8",""),IF(COUNTIFS(tl_sub,$A7,tl_sdg,9,tl_align,"Secondary")>0,"9",""),IF(COUNTIFS(tl_sub,$A7,tl_sdg,10,tl_align,"Secondary")>0,"10",""),IF(COUNTIFS(tl_sub,$A7,tl_sdg,11,tl_align,"Secondary")>0,"11",""),IF(COUNTIFS(tl_sub,$A7,tl_sdg,12,tl_align,"Secondary")>0,"12",""),IF(COUNTIFS(tl_sub,$A7,tl_sdg,13,tl_align,"Secondary")>0,"13",""),IF(COUNTIFS(tl_sub,$A7,tl_sdg,14,tl_align,"Secondary")>0,"14",""),IF(COUNTIFS(tl_sub,$A7,tl_sdg,15,tl_align,"Secondary")>0,"15",""),IF(COUNTIFS(tl_sub,$A7,tl_sdg,16,tl_align,"Secondary")>0,"16",""),IF(COUNTIFS(tl_sub,$A7,tl_sdg,17,tl_align,"Secondary")>0,"17","")) -> 4, 9, 10 | J7: 11.1, 11.2, 11.3, 11.a | K7: 4.4, 9.1, 10.2 | L7: =COUNTIF(tl_sub,A7) -> 7 | M7: =COUNTIF(il_sub,A7) -> 9 | N7: Locating infrastructure strategically can reduce spatial exclusion and improve equitable access to services, opportunities, knowledge and capacity. | O7: SDGs; NDP; NIP 2050; SPLUMA; NSDF; WCSDF 2030; PSP 2025-2030; MSDF; WCIF; PLTF; GPS; State of Development Planning Report and Spatial Performance Report (DEA&DP 2024); RPG-TWG; DEA&DP (Development Planning Report + Spatial Performance Report 2024); CEF; UIDF; MTSF; COGTA; CIF; SDBIP; U-AMP (GIAMA); C-AMP (GIAMA). All planned interventions (projects & programs) to be geo-located & spatially represented, including their expenditure to be expressed spatially.
A8: PP3.2 | B8: PP3 | C8: Public Value and Spatial Justice Innovations | D8: Public value & spatial justice | E8: 8 | F8: Deliver equitable public value while addressing spatial inequities through innovative projects, fostering inclusive planning & development, with a focus on WYPD. | G8: Does the project offer clear evidence of innovations to counter spatial inequalities, to promote inclusive planning and development? | H8: =_xlfn.TEXTJOIN(", ",TRUE(),IF(COUNTIFS(tl_sub,$A8,tl_sdg,1,tl_align,"Primary")>0,"1",""),IF(COUNTIFS(tl_sub,$A8,tl_sdg,2,tl_align,"Primary")>0,"2",""),IF(COUNTIFS(tl_sub,$A8,tl_sdg,3,tl_align,"Primary")>0,"3",""),IF(COUNTIFS(tl_sub,$A8,tl_sdg,4,tl_align,"Primary")>0,"4",""),IF(COUNTIFS(tl_sub,$A8,tl_sdg,5,tl_align,"Primary")>0,"5",""),IF(COUNTIFS(tl_sub,$A8,tl_sdg,6,tl_align,"Primary")>0,"6",""),IF(COUNTIFS(tl_sub,$A8,tl_sdg,7,tl_align,"Primary")>0,"7",""),IF(COUNTIFS(tl_sub,$A8,tl_sdg,8,tl_align,"Primary")>0,"8",""),IF(COUNTIFS(tl_sub,$A8,tl_sdg,9,tl_align,"Primary")>0,"9",""),IF(COUNTIFS(tl_sub,$A8,tl_sdg,10,tl_align,"Primary")>0,"10",""),IF(COUNTIFS(tl_sub,$A8,tl_sdg,11,tl_align,"Primary")>0,"11",""),IF(COUNTIFS(tl_sub,$A8,tl_sdg,12,tl_align,"Primary")>0,"12",""),IF(COUNTIFS(tl_sub,$A8,tl_sdg,13,tl_align,"Primary")>0,"13",""),IF(COUNTIFS(tl_sub,$A8,tl_sdg,14,tl_align,"Primary")>0,"14",""),IF(COUNTIFS(tl_sub,$A8,tl_sdg,15,tl_align,"Primary")>0,"15",""),IF(COUNTIFS(tl_sub,$A8,tl_sdg,16,tl_align,"Primary")>0,"16",""),IF(COUNTIFS(tl_sub,$A8,tl_sdg,17,tl_align,"Primary")>0,"17","")) -> 10, 11 | I8: =_xlfn.TEXTJOIN(", ",TRUE(),IF(COUNTIFS(tl_sub,$A8,tl_sdg,1,tl_align,"Secondary")>0,"1",""),IF(COUNTIFS(tl_sub,$A8,tl_sdg,2,tl_align,"Secondary")>0,"2",""),IF(COUNTIFS(tl_sub,$A8,tl_sdg,3,tl_align,"Secondary")>0,"3",""),IF(COUNTIFS(tl_sub,$A8,tl_sdg,4,tl_align,"Secondary")>0,"4",""),IF(COUNTIFS(tl_sub,$A8,tl_sdg,5,tl_align,"Secondary")>0,"5",""),IF(COUNTIFS(tl_sub,$A8,tl_sdg,6,tl_align,"Secondary")>0,"6",""),IF(COUNTIFS(tl_sub,$A8,tl_sdg,7,tl_align,"Secondary")>0,"7",""),IF(COUNTIFS(tl_sub,$A8,tl_sdg,8,tl_align,"Secondary")>0,"8",""),IF(COUNTIFS(tl_sub,$A8,tl_sdg,9,tl_align,"Secondary")>0,"9",""),IF(COUNTIFS(tl_sub,$A8,tl_sdg,10,tl_align,"Secondary")>0,"10",""),IF(COUNTIFS(tl_sub,$A8,tl_sdg,11,tl_align,"Secondary")>0,"11",""),IF(COUNTIFS(tl_sub,$A8,tl_sdg,12,tl_align,"Secondary")>0,"12",""),IF(COUNTIFS(tl_sub,$A8,tl_sdg,13,tl_align,"Secondary")>0,"13",""),IF(COUNTIFS(tl_sub,$A8,tl_sdg,14,tl_align,"Secondary")>0,"14",""),IF(COUNTIFS(tl_sub,$A8,tl_sdg,15,tl_align,"Secondary")>0,"15",""),IF(COUNTIFS(tl_sub,$A8,tl_sdg,16,tl_align,"Secondary")>0,"16",""),IF(COUNTIFS(tl_sub,$A8,tl_sdg,17,tl_align,"Secondary")>0,"17","")) -> 1, 9, 16 | J8: 10.2, 11.3 | K8: 1.4, 9.1, 16.7 | L8: =COUNTIF(tl_sub,A8) -> 5 | M8: =COUNTIF(il_sub,A8) -> 9 | N8: Promotes equitable public value, inclusive planning and innovative interventions that correct historic and geographic inequalities. | O8: NSDF; WCSDF 2030; MSDF; WCIF (MOIP); PLTF; GPS; DEA&DP (Development Planning Report + Spatial Performance Report 2024); UIDF; UIDG; CIF; CEF; SDBIP.
A9: PP3.3 | B9: PP3 | C9: Partnerships and Localisation Compliance | D9: Partnerships & localisation | E9: 16 | F9: Effective partnerships that demonstrates implementation innovation regarding Risk-Reward sharing; And the use of localised value chains to deliver socio-economic benefits, trust, and stakeholder equity. | G9: Does the project offer clear evidence of desired Partnership models favouring equitable Localised value chain development and risk-sharing? | H9: =_xlfn.TEXTJOIN(", ",TRUE(),IF(COUNTIFS(tl_sub,$A9,tl_sdg,1,tl_align,"Primary")>0,"1",""),IF(COUNTIFS(tl_sub,$A9,tl_sdg,2,tl_align,"Primary")>0,"2",""),IF(COUNTIFS(tl_sub,$A9,tl_sdg,3,tl_align,"Primary")>0,"3",""),IF(COUNTIFS(tl_sub,$A9,tl_sdg,4,tl_align,"Primary")>0,"4",""),IF(COUNTIFS(tl_sub,$A9,tl_sdg,5,tl_align,"Primary")>0,"5",""),IF(COUNTIFS(tl_sub,$A9,tl_sdg,6,tl_align,"Primary")>0,"6",""),IF(COUNTIFS(tl_sub,$A9,tl_sdg,7,tl_align,"Primary")>0,"7",""),IF(COUNTIFS(tl_sub,$A9,tl_sdg,8,tl_align,"Primary")>0,"8",""),IF(COUNTIFS(tl_sub,$A9,tl_sdg,9,tl_align,"Primary")>0,"9",""),IF(COUNTIFS(tl_sub,$A9,tl_sdg,10,tl_align,"Primary")>0,"10",""),IF(COUNTIFS(tl_sub,$A9,tl_sdg,11,tl_align,"Primary")>0,"11",""),IF(COUNTIFS(tl_sub,$A9,tl_sdg,12,tl_align,"Primary")>0,"12",""),IF(COUNTIFS(tl_sub,$A9,tl_sdg,13,tl_align,"Primary")>0,"13",""),IF(COUNTIFS(tl_sub,$A9,tl_sdg,14,tl_align,"Primary")>0,"14",""),IF(COUNTIFS(tl_sub,$A9,tl_sdg,15,tl_align,"Primary")>0,"15",""),IF(COUNTIFS(tl_sub,$A9,tl_sdg,16,tl_align,"Primary")>0,"16",""),IF(COUNTIFS(tl_sub,$A9,tl_sdg,17,tl_align,"Primary")>0,"17","")) -> 17 | I9: =_xlfn.TEXTJOIN(", ",TRUE(),IF(COUNTIFS(tl_sub,$A9,tl_sdg,1,tl_align,"Secondary")>0,"1",""),IF(COUNTIFS(tl_sub,$A9,tl_sdg,2,tl_align,"Secondary")>0,"2",""),IF(COUNTIFS(tl_sub,$A9,tl_sdg,3,tl_align,"Secondary")>0,"3",""),IF(COUNTIFS(tl_sub,$A9,tl_sdg,4,tl_align,"Secondary")>0,"4",""),IF(COUNTIFS(tl_sub,$A9,tl_sdg,5,tl_align,"Secondary")>0,"5",""),IF(COUNTIFS(tl_sub,$A9,tl_sdg,6,tl_align,"Secondary")>0,"6",""),IF(COUNTIFS(tl_sub,$A9,tl_sdg,7,tl_align,"Secondary")>0,"7",""),IF(COUNTIFS(tl_sub,$A9,tl_sdg,8,tl_align,"Secondary")>0,"8",""),IF(COUNTIFS(tl_sub,$A9,tl_sdg,9,tl_align,"Secondary")>0,"9",""),IF(COUNTIFS(tl_sub,$A9,tl_sdg,10,tl_align,"Secondary")>0,"10",""),IF(COUNTIFS(tl_sub,$A9,tl_sdg,11,tl_align,"Secondary")>0,"11",""),IF(COUNTIFS(tl_sub,$A9,tl_sdg,12,tl_align,"Secondary")>0,"12",""),IF(COUNTIFS(tl_sub,$A9,tl_sdg,13,tl_align,"Secondary")>0,"13",""),IF(COUNTIFS(tl_sub,$A9,tl_sdg,14,tl_align,"Secondary")>0,"14",""),IF(COUNTIFS(tl_sub,$A9,tl_sdg,15,tl_align,"Secondary")>0,"15",""),IF(COUNTIFS(tl_sub,$A9,tl_sdg,16,tl_align,"Secondary")>0,"16",""),IF(COUNTIFS(tl_sub,$A9,tl_sdg,17,tl_align,"Secondary")>0,"17","")) -> 8, 10, 12, 16 | J9: 17.16, 17.17 | K9: 8.3, 8.5, 10.2, 12.7, 16.6, 16.7 | L9: =COUNTIF(tl_sub,A9) -> 8 | M9: =COUNTIF(il_sub,A9) -> 11 | N9: Fair risk-and-reward arrangements, stakeholder trust and local value chains support equitable partnerships and locally retained socio-economic benefits. | O9: NT/PFMA; MTEF; NDP; NIP 2050; NLTF; PLTF; NSDF; PSDF; MSDF; PSP 2025-2030; G4J; WCIF; BSA; SABS; UIDF; MTSF; COGTA; CIDB; MSDG; IGM.
A10: PP4.1 | B10: PP4 | C10: Funding, Financing and Budget Governance and Compliance | D10: Funding & budget compliance | E10: 20 | F10: Compliance with provincial, national and international financial and budgetary frameworks to ensure funding sustainability and fiscal discipline. | G10: Does the project offer funding and financing governance frameworks (financial model, etc.) and PFMA and MFMA budgetary compliances; and taking into consideration the IFRS when necessary? | H10: =_xlfn.TEXTJOIN(", ",TRUE(),IF(COUNTIFS(tl_sub,$A10,tl_sdg,1,tl_align,"Primary")>0,"1",""),IF(COUNTIFS(tl_sub,$A10,tl_sdg,2,tl_align,"Primary")>0,"2",""),IF(COUNTIFS(tl_sub,$A10,tl_sdg,3,tl_align,"Primary")>0,"3",""),IF(COUNTIFS(tl_sub,$A10,tl_sdg,4,tl_align,"Primary")>0,"4",""),IF(COUNTIFS(tl_sub,$A10,tl_sdg,5,tl_align,"Primary")>0,"5",""),IF(COUNTIFS(tl_sub,$A10,tl_sdg,6,tl_align,"Primary")>0,"6",""),IF(COUNTIFS(tl_sub,$A10,tl_sdg,7,tl_align,"Primary")>0,"7",""),IF(COUNTIFS(tl_sub,$A10,tl_sdg,8,tl_align,"Primary")>0,"8",""),IF(COUNTIFS(tl_sub,$A10,tl_sdg,9,tl_align,"Primary")>0,"9",""),IF(COUNTIFS(tl_sub,$A10,tl_sdg,10,tl_align,"Primary")>0,"10",""),IF(COUNTIFS(tl_sub,$A10,tl_sdg,11,tl_align,"Primary")>0,"11",""),IF(COUNTIFS(tl_sub,$A10,tl_sdg,12,tl_align,"Primary")>0,"12",""),IF(COUNTIFS(tl_sub,$A10,tl_sdg,13,tl_align,"Primary")>0,"13",""),IF(COUNTIFS(tl_sub,$A10,tl_sdg,14,tl_align,"Primary")>0,"14",""),IF(COUNTIFS(tl_sub,$A10,tl_sdg,15,tl_align,"Primary")>0,"15",""),IF(COUNTIFS(tl_sub,$A10,tl_sdg,16,tl_align,"Primary")>0,"16",""),IF(COUNTIFS(tl_sub,$A10,tl_sdg,17,tl_align,"Primary")>0,"17","")) -> 16 | I10: =_xlfn.TEXTJOIN(", ",TRUE(),IF(COUNTIFS(tl_sub,$A10,tl_sdg,1,tl_align,"Secondary")>0,"1",""),IF(COUNTIFS(tl_sub,$A10,tl_sdg,2,tl_align,"Secondary")>0,"2",""),IF(COUNTIFS(tl_sub,$A10,tl_sdg,3,tl_align,"Secondary")>0,"3",""),IF(COUNTIFS(tl_sub,$A10,tl_sdg,4,tl_align,"Secondary")>0,"4",""),IF(COUNTIFS(tl_sub,$A10,tl_sdg,5,tl_align,"Secondary")>0,"5",""),IF(COUNTIFS(tl_sub,$A10,tl_sdg,6,tl_align,"Secondary")>0,"6",""),IF(COUNTIFS(tl_sub,$A10,tl_sdg,7,tl_align,"Secondary")>0,"7",""),IF(COUNTIFS(tl_sub,$A10,tl_sdg,8,tl_align,"Secondary")>0,"8",""),IF(COUNTIFS(tl_sub,$A10,tl_sdg,9,tl_align,"Secondary")>0,"9",""),IF(COUNTIFS(tl_sub,$A10,tl_sdg,10,tl_align,"Secondary")>0,"10",""),IF(COUNTIFS(tl_sub,$A10,tl_sdg,11,tl_align,"Secondary")>0,"11",""),IF(COUNTIFS(tl_sub,$A10,tl_sdg,12,tl_align,"Secondary")>0,"12",""),IF(COUNTIFS(tl_sub,$A10,tl_sdg,13,tl_align,"Secondary")>0,"13",""),IF(COUNTIFS(tl_sub,$A10,tl_sdg,14,tl_align,"Secondary")>0,"14",""),IF(COUNTIFS(tl_sub,$A10,tl_sdg,15,tl_align,"Secondary")>0,"15",""),IF(COUNTIFS(tl_sub,$A10,tl_sdg,16,tl_align,"Secondary")>0,"16",""),IF(COUNTIFS(tl_sub,$A10,tl_sdg,17,tl_align,"Secondary")>0,"17","")) -> 17 | J10: 16.6 | K10: 17.1, 17.3, 17.4, 17.14 | L10: =COUNTIF(tl_sub,A10) -> 5 | M10: =COUNTIF(il_sub,A10) -> 8 | N10: Compliance with financial and budget frameworks strengthens fiscal discipline, accountability, institutional effectiveness and sustainable infrastructure funding. | O10: NT/PFMA; MTEF; NDP; NIP 2050; PT; G4J; WCIF; MFMA; MTSF; CEF; UIDG; COGTA; LTFP; CIP; IGM; SDIP; C-AMP (GIAMA); U-AMP (GIAMA).
A11: PP4.2 | B11: PP4 | C11: Socio-economic Compliance | D11: Socio-economic compliance | E11: 8 | F11: Adherence to socio-economic planning frameworks and policies, aligning infrastructure projects with growth development priorities and policy objectives as part of effective governance and transversal planning (also take into consideration decommissioning and repurposing). | G11: Does the project offer clear evidence of alignment of socio-economic growth and development priorities required by transversal planning prescripts? | H11: =_xlfn.TEXTJOIN(", ",TRUE(),IF(COUNTIFS(tl_sub,$A11,tl_sdg,1,tl_align,"Primary")>0,"1",""),IF(COUNTIFS(tl_sub,$A11,tl_sdg,2,tl_align,"Primary")>0,"2",""),IF(COUNTIFS(tl_sub,$A11,tl_sdg,3,tl_align,"Primary")>0,"3",""),IF(COUNTIFS(tl_sub,$A11,tl_sdg,4,tl_align,"Primary")>0,"4",""),IF(COUNTIFS(tl_sub,$A11,tl_sdg,5,tl_align,"Primary")>0,"5",""),IF(COUNTIFS(tl_sub,$A11,tl_sdg,6,tl_align,"Primary")>0,"6",""),IF(COUNTIFS(tl_sub,$A11,tl_sdg,7,tl_align,"Primary")>0,"7",""),IF(COUNTIFS(tl_sub,$A11,tl_sdg,8,tl_align,"Primary")>0,"8",""),IF(COUNTIFS(tl_sub,$A11,tl_sdg,9,tl_align,"Primary")>0,"9",""),IF(COUNTIFS(tl_sub,$A11,tl_sdg,10,tl_align,"Primary")>0,"10",""),IF(COUNTIFS(tl_sub,$A11,tl_sdg,11,tl_align,"Primary")>0,"11",""),IF(COUNTIFS(tl_sub,$A11,tl_sdg,12,tl_align,"Primary")>0,"12",""),IF(COUNTIFS(tl_sub,$A11,tl_sdg,13,tl_align,"Primary")>0,"13",""),IF(COUNTIFS(tl_sub,$A11,tl_sdg,14,tl_align,"Primary")>0,"14",""),IF(COUNTIFS(tl_sub,$A11,tl_sdg,15,tl_align,"Primary")>0,"15",""),IF(COUNTIFS(tl_sub,$A11,tl_sdg,16,tl_align,"Primary")>0,"16",""),IF(COUNTIFS(tl_sub,$A11,tl_sdg,17,tl_align,"Primary")>0,"17","")) -> 16 | I11: =_xlfn.TEXTJOIN(", ",TRUE(),IF(COUNTIFS(tl_sub,$A11,tl_sdg,1,tl_align,"Secondary")>0,"1",""),IF(COUNTIFS(tl_sub,$A11,tl_sdg,2,tl_align,"Secondary")>0,"2",""),IF(COUNTIFS(tl_sub,$A11,tl_sdg,3,tl_align,"Secondary")>0,"3",""),IF(COUNTIFS(tl_sub,$A11,tl_sdg,4,tl_align,"Secondary")>0,"4",""),IF(COUNTIFS(tl_sub,$A11,tl_sdg,5,tl_align,"Secondary")>0,"5",""),IF(COUNTIFS(tl_sub,$A11,tl_sdg,6,tl_align,"Secondary")>0,"6",""),IF(COUNTIFS(tl_sub,$A11,tl_sdg,7,tl_align,"Secondary")>0,"7",""),IF(COUNTIFS(tl_sub,$A11,tl_sdg,8,tl_align,"Secondary")>0,"8",""),IF(COUNTIFS(tl_sub,$A11,tl_sdg,9,tl_align,"Secondary")>0,"9",""),IF(COUNTIFS(tl_sub,$A11,tl_sdg,10,tl_align,"Secondary")>0,"10",""),IF(COUNTIFS(tl_sub,$A11,tl_sdg,11,tl_align,"Secondary")>0,"11",""),IF(COUNTIFS(tl_sub,$A11,tl_sdg,12,tl_align,"Secondary")>0,"12",""),IF(COUNTIFS(tl_sub,$A11,tl_sdg,13,tl_align,"Secondary")>0,"13",""),IF(COUNTIFS(tl_sub,$A11,tl_sdg,14,tl_align,"Secondary")>0,"14",""),IF(COUNTIFS(tl_sub,$A11,tl_sdg,15,tl_align,"Secondary")>0,"15",""),IF(COUNTIFS(tl_sub,$A11,tl_sdg,16,tl_align,"Secondary")>0,"16",""),IF(COUNTIFS(tl_sub,$A11,tl_sdg,17,tl_align,"Secondary")>0,"17","")) -> 8, 10, 11, 17 | J11: 16.6, 16.7 | K11: 8.3, 10.2, 11.a, 17.14 | L11: =COUNTIF(tl_sub,A11) -> 6 | M11: =COUNTIF(il_sub,A11) -> 8 | N11: Alignment with socio-economic policies and development priorities enables accountable governance, coordinated planning and inclusive growth. | O11: NSDF; WCSDF 2030; MSDF; WCIF; PLTF; MOIP; G4J; UID; MTSF; COGTA; CIDB; LTFP; CIF; CEF; SDBIP.
D12: Total | E12: =SUM(E2:E11) -> 100 | L12: =SUM(L2:L11) -> 66 | M12: =SUM(M2:M11) -> 103

Sheet Target links
A1: Link ID | B1: Principle | C1: Sub-principle | D1: SDG | E1: SDG name | F1: Target | G1: Target short name | H1: Target text (UNSD) | I1: Alignment | J1: Department label | K1: Indicators
A2: PP1.1|9.1 | B2: PP1 | C2: PP1.1 | D2: 9 | E2: Industry, Innovation and Infrastructure | F2: 9.1 | G2: Quality, resilient infrastructure | H2: Develop quality, reliable, sustainable and resilient infrastructure, including regional and transborder infrastructure, to support economic development and human well-being, with a focus on affordable and equitable access for all | I2: Primary | K2: =COUNTIF('Indicator links'!$A$2:$A$500,A2) -> 2
A3: PP1.1|9.4 | B3: PP1 | C3: PP1.1 | D3: 9 | E3: Industry, Innovation and Infrastructure | F3: 9.4 | G3: Sustainable, retrofitted infrastructure | H3: By 2030, upgrade infrastructure and retrofit industries to make them sustainable, with increased resource-use efficiency and greater adoption of clean and environmentally sound technologies and industrial processes, with all countries taking action in accordance with their respective capabilities | I3: Primary | K3: =COUNTIF('Indicator links'!$A$2:$A$500,A3) -> 1
A4: PP1.1|9.5 | B4: PP1 | C4: PP1.1 | D4: 9 | E4: Industry, Innovation and Infrastructure | F4: 9.5 | G4: Research and technological capability | H4: Enhance scientific research, upgrade the technological capabilities of industrial sectors in all countries, in particular developing countries, including, by 2030, encouraging innovation and substantially increasing the number of research and development workers per 1 million people and public and private research and development spending | I4: Primary | K4: =COUNTIF('Indicator links'!$A$2:$A$500,A4) -> 2
A5: PP1.1|8.2 | B5: PP1 | C5: PP1.1 | D5: 8 | E5: Decent Work and Economic Growth | F5: 8.2 | G5: Productivity through innovation | H5: Achieve higher levels of economic productivity through diversification, technological upgrading and innovation, including through a focus on high-value added and labour-intensive sectors | I5: Secondary | J5: innovation-led productivity | K5: =COUNTIF('Indicator links'!$A$2:$A$500,A5) -> 1
A6: PP1.1|11.3 | B6: PP1 | C6: PP1.1 | D6: 11 | E6: Sustainable Cities and Communities | F6: 11.3 | G6: Inclusive, integrated urban planning | H6: By 2030, enhance inclusive and sustainable urbanization and capacity for participatory, integrated and sustainable human settlement planning and management in all countries | I6: Secondary | J6: integrated urban planning | K6: =COUNTIF('Indicator links'!$A$2:$A$500,A6) -> 2
A7: PP1.1|12.2 | B7: PP1 | C7: PP1.1 | D7: 12 | E7: Responsible Consumption and Production | F7: 12.2 | G7: Sustainable use of natural resources | H7: By 2030, achieve the sustainable management and efficient use of natural resources | I7: Secondary | J7: efficient use of natural resources | K7: =COUNTIF('Indicator links'!$A$2:$A$500,A7) -> 2
A8: PP1.2|9.5 | B8: PP1 | C8: PP1.2 | D8: 9 | E8: Industry, Innovation and Infrastructure | F8: 9.5 | G8: Research and technological capability | H8: Enhance scientific research, upgrade the technological capabilities of industrial sectors in all countries, in particular developing countries, including, by 2030, encouraging innovation and substantially increasing the number of research and development workers per 1 million people and public and private research and development spending | I8: Primary | K8: =COUNTIF('Indicator links'!$A$2:$A$500,A8) -> 2
A9: PP1.2|9.c | B9: PP1 | C9: PP1.2 | D9: 9 | E9: Industry, Innovation and Infrastructure | F9: 9.c | G9: Access to ICT and the internet | H9: Significantly increase access to information and communications technology and strive to provide universal and affordable access to the Internet in least developed countries by 2020 | I9: Primary | K9: =COUNTIF('Indicator links'!$A$2:$A$500,A9) -> 1
A10: PP1.2|8.2 | B10: PP1 | C10: PP1.2 | D10: 8 | E10: Decent Work and Economic Growth | F10: 8.2 | G10: Productivity through innovation | H10: Achieve higher levels of economic productivity through diversification, technological upgrading and innovation, including through a focus on high-value added and labour-intensive sectors | I10: Secondary | J10: technological upgrading | K10: =COUNTIF('Indicator links'!$A$2:$A$500,A10) -> 1
A11: PP1.2|16.6 | B11: PP1 | C11: PP1.2 | D11: 16 | E11: Peace, Justice and Strong Institutions | F11: 16.6 | G11: Effective, accountable institutions | H11: Develop effective, accountable and transparent institutions at all levels | I11: Secondary | J11: effective institutions | K11: =COUNTIF('Indicator links'!$A$2:$A$500,A11) -> 2
A12: PP1.2|16.10 | B12: PP1 | C12: PP1.2 | D12: 16 | E12: Peace, Justice and Strong Institutions | F12: 16.10 | G12: Public access to information | H12: Ensure public access to information and protect fundamental freedoms, in accordance with national legislation and international agreements | I12: Secondary | J12: access to information | K12: =COUNTIF('Indicator links'!$A$2:$A$500,A12) -> 2
A13: PP1.2|17.8 | B13: PP1 | C13: PP1.2 | D13: 17 | E13: Partnerships for the Goals | F13: 17.8 | G13: Enabling technology and ICT | H13: Fully operationalize the technology bank and science, technology and innovation capacity-building mechanism for least developed countries by 2017 and enhance the use of enabling technology, in particular information and communications technology | I13: Secondary | J13: enabling technology | K13: =COUNTIF('Indicator links'!$A$2:$A$500,A13) -> 1
A14: PP2.1|9.1 | B14: PP2 | C14: PP2.1 | D14: 9 | E14: Industry, Innovation and Infrastructure | F14: 9.1 | G14: Quality, resilient infrastructure | H14: Develop quality, reliable, sustainable and resilient infrastructure, including regional and transborder infrastructure, to support economic development and human well-being, with a focus on affordable and equitable access for all | I14: Primary | K14: =COUNTIF('Indicator links'!$A$2:$A$500,A14) -> 2
A15: PP2.1|13.1 | B15: PP2 | C15: PP2.1 | D15: 13 | E15: Climate Action | F15: 13.1 | G15: Climate resilience and adaptive capacity | H15: Strengthen resilience and adaptive capacity to climate-related hazards and natural disasters in all countries | I15: Primary | K15: =COUNTIF('Indicator links'!$A$2:$A$500,A15) -> 3
A16: PP2.1|13.2 | B16: PP2 | C16: PP2.1 | D16: 13 | E16: Climate Action | F16: 13.2 | G16: Climate measures in plans and policies | H16: Integrate climate change measures into national policies, strategies and planning | I16: Primary | K16: =COUNTIF('Indicator links'!$A$2:$A$500,A16) -> 2
A17: PP2.1|6.4 | B17: PP2 | C17: PP2.1 | D17: 6 | E17: Clean Water and Sanitation | F17: 6.4 | G17: Water-use efficiency | H17: By 2030, substantially increase water-use efficiency across all sectors and ensure sustainable withdrawals and supply of freshwater to address water scarcity and substantially reduce the number of people suffering from water scarcity | I17: Secondary | J17: water efficiency and integrated management | K17: =COUNTIF('Indicator links'!$A$2:$A$500,A17) -> 2
A18: PP2.1|6.5 | B18: PP2 | C18: PP2.1 | D18: 6 | E18: Clean Water and Sanitation | F18: 6.5 | G18: Integrated water resources management | H18: By 2030, implement integrated water resources management at all levels, including through transboundary cooperation as appropriate | I18: Secondary | J18: water efficiency and integrated management | K18: =COUNTIF('Indicator links'!$A$2:$A$500,A18) -> 2
A19: PP2.1|7.2 | B19: PP2 | C19: PP2.1 | D19: 7 | E19: Affordable and Clean Energy | F19: 7.2 | G19: Renewable energy share | H19: By 2030, increase substantially the share of renewable energy in the global energy mix | I19: Secondary | J19: renewable energy and energy efficiency | K19: =COUNTIF('Indicator links'!$A$2:$A$500,A19) -> 1
A20: PP2.1|7.3 | B20: PP2 | C20: PP2.1 | D20: 7 | E20: Affordable and Clean Energy | F20: 7.3 | G20: Energy efficiency | H20: By 2030, double the global rate of improvement in energy efficiency | I20: Secondary | J20: renewable energy and energy efficiency | K20: =COUNTIF('Indicator links'!$A$2:$A$500,A20) -> 1
A21: PP2.1|11.5 | B21: PP2 | C21: PP2.1 | D21: 11 | E21: Sustainable Cities and Communities | F21: 11.5 | G21: Reduced disaster losses | H21: By 2030, significantly reduce the number of deaths and the number of people affected and substantially decrease the direct economic losses relative to global gross domestic product caused by disasters, including water-related disasters, with a focus on protecting the poor and people in vulnerable situations | I21: Secondary | J21: disaster resilience | K21: =COUNTIF('Indicator links'!$A$2:$A$500,A21) -> 3
A22: PP2.1|11.b | B22: PP2 | C22: PP2.1 | D22: 11 | E22: Sustainable Cities and Communities | F22: 11.b | G22: Integrated climate and disaster-risk policies | H22: By 2020, substantially increase the number of cities and human settlements adopting and implementing integrated policies and plans towards inclusion, resource efficiency, mitigation and adaptation to climate change, resilience to disasters, and develop and implement, in line with the Sendai Framework for Disaster Risk Reduction 2015–2030, holistic disaster risk management at all levels | I22: Secondary | J22: disaster resilience | K22: =COUNTIF('Indicator links'!$A$2:$A$500,A22) -> 2
A23: PP2.1|12.2 | B23: PP2 | C23: PP2.1 | D23: 12 | E23: Responsible Consumption and Production | F23: 12.2 | G23: Sustainable use of natural resources | H23: By 2030, achieve the sustainable management and efficient use of natural resources | I23: Secondary | J23: sustainable resource use | K23: =COUNTIF('Indicator links'!$A$2:$A$500,A23) -> 2
A24: PP2.2|11.3 | B24: PP2 | C24: PP2.2 | D24: 11 | E24: Sustainable Cities and Communities | F24: 11.3 | G24: Inclusive, integrated urban planning | H24: By 2030, enhance inclusive and sustainable urbanization and capacity for participatory, integrated and sustainable human settlement planning and management in all countries | I24: Primary | K24: =COUNTIF('Indicator links'!$A$2:$A$500,A24) -> 2
A25: PP2.2|11.a | B25: PP2 | C25: PP2.2 | D25: 11 | E25: Sustainable Cities and Communities | F25: 11.a | G25: Urban–rural planning links | H25: Support positive economic, social and environmental links between urban, peri-urban and rural areas by strengthening national and regional development planning | I25: Primary | K25: =COUNTIF('Indicator links'!$A$2:$A$500,A25) -> 1
A26: PP2.2|9.1 | B26: PP2 | C26: PP2.2 | D26: 9 | E26: Industry, Innovation and Infrastructure | F26: 9.1 | G26: Quality, resilient infrastructure | H26: Develop quality, reliable, sustainable and resilient infrastructure, including regional and transborder infrastructure, to support economic development and human well-being, with a focus on affordable and equitable access for all | I26: Secondary | J26: sustainable infrastructure | K26: =COUNTIF('Indicator links'!$A$2:$A$500,A26) -> 2
A27: PP2.2|13.2 | B27: PP2 | C27: PP2.2 | D27: 13 | E27: Climate Action | F27: 13.2 | G27: Climate measures in plans and policies | H27: Integrate climate change measures into national policies, strategies and planning | I27: Secondary | J27: climate integration | K27: =COUNTIF('Indicator links'!$A$2:$A$500,A27) -> 2
A28: PP2.2|17.14 | B28: PP2 | C28: PP2.2 | D28: 17 | E28: Partnerships for the Goals | F28: 17.14 | G28: Policy coherence | H28: Enhance policy coherence for sustainable development | I28: Secondary | J28: policy coherence | K28: =COUNTIF('Indicator links'!$A$2:$A$500,A28) -> 1
A29: PP2.2|17.16 | B29: PP2 | C29: PP2.2 | D29: 17 | E29: Partnerships for the Goals | F29: 17.16 | G29: Multi-stakeholder partnerships | H29: Enhance the Global Partnership for Sustainable Development, complemented by multi-stakeholder partnerships that mobilize and share knowledge, expertise, technology and financial resources, to support the achievement of the Sustainable Development Goals in all countries, in particular developing countries | I29: Secondary | J29: partnerships | K29: =COUNTIF('Indicator links'!$A$2:$A$500,A29) -> 1
A30: PP2.2|17.17 | B30: PP2 | C30: PP2.2 | D30: 17 | E30: Partnerships for the Goals | F30: 17.17 | G30: Public, public-private and civil society partnerships | H30: Encourage and promote effective public, public-private and civil society partnerships, building on the experience and resourcing strategies of partnerships | I30: Secondary | J30: partnerships | K30: =COUNTIF('Indicator links'!$A$2:$A$500,A30) -> 1
A31: PP2.3|12.2 | B31: PP2 | C31: PP2.3 | D31: 12 | E31: Responsible Consumption and Production | F31: 12.2 | G31: Sustainable use of natural resources | H31: By 2030, achieve the sustainable management and efficient use of natural resources | I31: Primary | K31: =COUNTIF('Indicator links'!$A$2:$A$500,A31) -> 2
A32: PP2.3|12.7 | B32: PP2 | C32: PP2.3 | D32: 12 | E32: Responsible Consumption and Production | F32: 12.7 | G32: Sustainable public procurement | H32: Promote public procurement practices that are sustainable, in accordance with national policies and priorities | I32: Primary | K32: =COUNTIF('Indicator links'!$A$2:$A$500,A32) -> 1
A33: PP2.3|8.3 | B33: PP2 | C33: PP2.3 | D33: 8 | E33: Decent Work and Economic Growth | F33: 8.3 | G33: Enterprise and small-business growth | H33: Promote development-oriented policies that support productive activities, decent job creation, entrepreneurship, creativity and innovation, and encourage the formalization and growth of micro-, small- and medium-sized enterprises, including through access to financial services | I33: Secondary | J33: local enterprise development | K33: =COUNTIF('Indicator links'!$A$2:$A$500,A33) -> 1
A34: PP2.3|9.4 | B34: PP2 | C34: PP2.3 | D34: 9 | E34: Industry, Innovation and Infrastructure | F34: 9.4 | G34: Sustainable, retrofitted infrastructure | H34: By 2030, upgrade infrastructure and retrofit industries to make them sustainable, with increased resource-use efficiency and greater adoption of clean and environmentally sound technologies and industrial processes, with all countries taking action in accordance with their respective capabilities | I34: Secondary | J34: resource-efficient industry | K34: =COUNTIF('Indicator links'!$A$2:$A$500,A34) -> 1
A35: PP2.3|11.6 | B35: PP2 | C35: PP2.3 | D35: 11 | E35: Sustainable Cities and Communities | F35: 11.6 | G35: Lower urban environmental impact | H35: By 2030, reduce the adverse per capita environmental impact of cities, including by paying special attention to air quality and municipal and other waste management | I35: Secondary | J35: lower urban environmental impact | K35: =COUNTIF('Indicator links'!$A$2:$A$500,A35) -> 2
A36: PP2.3|13.2 | B36: PP2 | C36: PP2.3 | D36: 13 | E36: Climate Action | F36: 13.2 | G36: Climate measures in plans and policies | H36: Integrate climate change measures into national policies, strategies and planning | I36: Secondary | J36: climate considerations | K36: =COUNTIF('Indicator links'!$A$2:$A$500,A36) -> 2
A37: PP3.1|11.1 | B37: PP3 | C37: PP3.1 | D37: 11 | E37: Sustainable Cities and Communities | F37: 11.1 | G37: Adequate housing and basic services | H37: By 2030, ensure access for all to adequate, safe and affordable housing and basic services and upgrade slums | I37: Primary | K37: =COUNTIF('Indicator links'!$A$2:$A$500,A37) -> 1
A38: PP3.1|11.2 | B38: PP3 | C38: PP3.1 | D38: 11 | E38: Sustainable Cities and Communities | F38: 11.2 | G38: Sustainable transport systems | H38: By 2030, provide access to safe, affordable, accessible and sustainable transport systems for all, improving road safety, notably by expanding public transport, with special attention to the needs of those in vulnerable situations, women, children, persons with disabilities and older persons | I38: Primary | K38: =COUNTIF('Indicator links'!$A$2:$A$500,A38) -> 1
A39: PP3.1|11.3 | B39: PP3 | C39: PP3.1 | D39: 11 | E39: Sustainable Cities and Communities | F39: 11.3 | G39: Inclusive, integrated urban planning | H39: By 2030, enhance inclusive and sustainable urbanization and capacity for participatory, integrated and sustainable human settlement planning and management in all countries | I39: Primary | K39: =COUNTIF('Indicator links'!$A$2:$A$500,A39) -> 2
A40: PP3.1|11.a | B40: PP3 | C40: PP3.1 | D40: 11 | E40: Sustainable Cities and Communities | F40: 11.a | G40: Urban–rural planning links | H40: Support positive economic, social and environmental links between urban, peri-urban and rural areas by strengthening national and regional development planning | I40: Primary | K40: =COUNTIF('Indicator links'!$A$2:$A$500,A40) -> 1
A41: PP3.1|4.4 | B41: PP3 | C41: PP3.1 | D41: 4 | E41: Quality Education | F41: 4.4 | G41: Relevant skills for work | H41: By 2030, substantially increase the number of youth and adults who have relevant skills, including technical and vocational skills, for employment, decent jobs and entrepreneurship | I41: Secondary | J41: skills and capacity development | K41: =COUNTIF('Indicator links'!$A$2:$A$500,A41) -> 1
A42: PP3.1|9.1 | B42: PP3 | C42: PP3.1 | D42: 9 | E42: Industry, Innovation and Infrastructure | F42: 9.1 | G42: Quality, resilient infrastructure | H42: Develop quality, reliable, sustainable and resilient infrastructure, including regional and transborder infrastructure, to support economic development and human well-being, with a focus on affordable and equitable access for all | I42: Secondary | J42: equitable access to infrastructure | K42: =COUNTIF('Indicator links'!$A$2:$A$500,A42) -> 2
A43: PP3.1|10.2 | B43: PP3 | C43: PP3.1 | D43: 10 | E43: Reduced Inequalities | F43: 10.2 | G43: Social, economic and political inclusion | H43: By 2030, empower and promote the social, economic and political inclusion of all, irrespective of age, sex, disability, race, ethnicity, origin, religion or economic or other status | I43: Secondary | J43: social and economic inclusion | K43: =COUNTIF('Indicator links'!$A$2:$A$500,A43) -> 1
A44: PP3.2|10.2 | B44: PP3 | C44: PP3.2 | D44: 10 | E44: Reduced Inequalities | F44: 10.2 | G44: Social, economic and political inclusion | H44: By 2030, empower and promote the social, economic and political inclusion of all, irrespective of age, sex, disability, race, ethnicity, origin, religion or economic or other status | I44: Primary | K44: =COUNTIF('Indicator links'!$A$2:$A$500,A44) -> 1
A45: PP3.2|11.3 | B45: PP3 | C45: PP3.2 | D45: 11 | E45: Sustainable Cities and Communities | F45: 11.3 | G45: Inclusive, integrated urban planning | H45: By 2030, enhance inclusive and sustainable urbanization and capacity for participatory, integrated and sustainable human settlement planning and management in all countries | I45: Primary | K45: =COUNTIF('Indicator links'!$A$2:$A$500,A45) -> 2
A46: PP3.2|1.4 | B46: PP3 | C46: PP3.2 | D46: 1 | E46: No Poverty | F46: 1.4 | G46: Equal access to basic services and resources | H46: By 2030, ensure that all men and women, in particular the poor and the vulnerable, have equal rights to economic resources, as well as access to basic services, ownership and control over land and other forms of property, inheritance, natural resources, appropriate new technology and financial services, including microfinance | I46: Secondary | J46: access to basic services and economic resources | K46: =COUNTIF('Indicator links'!$A$2:$A$500,A46) -> 2
A47: PP3.2|9.1 | B47: PP3 | C47: PP3.2 | D47: 9 | E47: Industry, Innovation and Infrastructure | F47: 9.1 | G47: Quality, resilient infrastructure | H47: Develop quality, reliable, sustainable and resilient infrastructure, including regional and transborder infrastructure, to support economic development and human well-being, with a focus on affordable and equitable access for all | I47: Secondary | J47: affordable and equitable access | K47: =COUNTIF('Indicator links'!$A$2:$A$500,A47) -> 2
A48: PP3.2|16.7 | B48: PP3 | C48: PP3.2 | D48: 16 | E48: Peace, Justice and Strong Institutions | F48: 16.7 | G48: Inclusive, participatory decision-making | H48: Ensure responsive, inclusive, participatory and representative decision-making at all levels | I48: Secondary | J48: inclusive decision-making | K48: =COUNTIF('Indicator links'!$A$2:$A$500,A48) -> 2
A49: PP3.3|17.16 | B49: PP3 | C49: PP3.3 | D49: 17 | E49: Partnerships for the Goals | F49: 17.16 | G49: Multi-stakeholder partnerships | H49: Enhance the Global Partnership for Sustainable Development, complemented by multi-stakeholder partnerships that mobilize and share knowledge, expertise, technology and financial resources, to support the achievement of the Sustainable Development Goals in all countries, in particular developing countries | I49: Primary | K49: =COUNTIF('Indicator links'!$A$2:$A$500,A49) -> 1
A50: PP3.3|17.17 | B50: PP3 | C50: PP3.3 | D50: 17 | E50: Partnerships for the Goals | F50: 17.17 | G50: Public, public-private and civil society partnerships | H50: Encourage and promote effective public, public-private and civil society partnerships, building on the experience and resourcing strategies of partnerships | I50: Primary | K50: =COUNTIF('Indicator links'!$A$2:$A$500,A50) -> 1
A51: PP3.3|8.3 | B51: PP3 | C51: PP3.3 | D51: 8 | E51: Decent Work and Economic Growth | F51: 8.3 | G51: Enterprise and small-business growth | H51: Promote development-oriented policies that support productive activities, decent job creation, entrepreneurship, creativity and innovation, and encourage the formalization and growth of micro-, small- and medium-sized enterprises, including through access to financial services | I51: Secondary | J51: enterprise and decent work | K51: =COUNTIF('Indicator links'!$A$2:$A$500,A51) -> 1
A52: PP3.3|8.5 | B52: PP3 | C52: PP3.3 | D52: 8 | E52: Decent Work and Economic Growth | F52: 8.5 | G52: Full employment and decent work | H52: By 2030, achieve full and productive employment and decent work for all women and men, including for young people and persons with disabilities, and equal pay for work of equal value | I52: Secondary | J52: enterprise and decent work | K52: =COUNTIF('Indicator links'!$A$2:$A$500,A52) -> 2
A53: PP3.3|10.2 | B53: PP3 | C53: PP3.3 | D53: 10 | E53: Reduced Inequalities | F53: 10.2 | G53: Social, economic and political inclusion | H53: By 2030, empower and promote the social, economic and political inclusion of all, irrespective of age, sex, disability, race, ethnicity, origin, religion or economic or other status | I53: Secondary | J53: inclusion | K53: =COUNTIF('Indicator links'!$A$2:$A$500,A53) -> 1
A54: PP3.3|12.7 | B54: PP3 | C54: PP3.3 | D54: 12 | E54: Responsible Consumption and Production | F54: 12.7 | G54: Sustainable public procurement | H54: Promote public procurement practices that are sustainable, in accordance with national policies and priorities | I54: Secondary | J54: sustainable procurement | K54: =COUNTIF('Indicator links'!$A$2:$A$500,A54) -> 1
A55: PP3.3|16.6 | B55: PP3 | C55: PP3.3 | D55: 16 | E55: Peace, Justice and Strong Institutions | F55: 16.6 | G55: Effective, accountable institutions | H55: Develop effective, accountable and transparent institutions at all levels | I55: Secondary | J55: accountability and participation | K55: =COUNTIF('Indicator links'!$A$2:$A$500,A55) -> 2
A56: PP3.3|16.7 | B56: PP3 | C56: PP3.3 | D56: 16 | E56: Peace, Justice and Strong Institutions | F56: 16.7 | G56: Inclusive, participatory decision-making | H56: Ensure responsive, inclusive, participatory and representative decision-making at all levels | I56: Secondary | J56: accountability and participation | K56: =COUNTIF('Indicator links'!$A$2:$A$500,A56) -> 2
A57: PP4.1|16.6 | B57: PP4 | C57: PP4.1 | D57: 16 | E57: Peace, Justice and Strong Institutions | F57: 16.6 | G57: Effective, accountable institutions | H57: Develop effective, accountable and transparent institutions at all levels | I57: Primary | K57: =COUNTIF('Indicator links'!$A$2:$A$500,A57) -> 2
A58: PP4.1|17.1 | B58: PP4 | C58: PP4.1 | D58: 17 | E58: Partnerships for the Goals | F58: 17.1 | G58: Domestic resource mobilisation | H58: Strengthen domestic resource mobilization, including through international support to developing countries, to improve domestic capacity for tax and other revenue collection | I58: Secondary | J58: domestic resource mobilisation | K58: =COUNTIF('Indicator links'!$A$2:$A$500,A58) -> 2
A59: PP4.1|17.3 | B59: PP4 | C59: PP4.1 | D59: 17 | E59: Partnerships for the Goals | F59: 17.3 | G59: Additional financial resources | H59: Mobilize additional financial resources for developing countries from multiple sources | I59: Secondary | J59: additional financial resources | K59: =COUNTIF('Indicator links'!$A$2:$A$500,A59) -> 2
A60: PP4.1|17.4 | B60: PP4 | C60: PP4.1 | D60: 17 | E60: Partnerships for the Goals | F60: 17.4 | G60: Debt sustainability | H60: Assist developing countries in attaining long-term debt sustainability through coordinated policies aimed at fostering debt financing, debt relief and debt restructuring, as appropriate, and address the external debt of highly indebted poor countries to reduce debt distress | I60: Secondary | J60: long-term financial sustainability | K60: =COUNTIF('Indicator links'!$A$2:$A$500,A60) -> 1
A61: PP4.1|17.14 | B61: PP4 | C61: PP4.1 | D61: 17 | E61: Partnerships for the Goals | F61: 17.14 | G61: Policy coherence | H61: Enhance policy coherence for sustainable development | I61: Secondary | J61: policy coherence | K61: =COUNTIF('Indicator links'!$A$2:$A$500,A61) -> 1
A62: PP4.2|16.6 | B62: PP4 | C62: PP4.2 | D62: 16 | E62: Peace, Justice and Strong Institutions | F62: 16.6 | G62: Effective, accountable institutions | H62: Develop effective, accountable and transparent institutions at all levels | I62: Primary | K62: =COUNTIF('Indicator links'!$A$2:$A$500,A62) -> 2
A63: PP4.2|16.7 | B63: PP4 | C63: PP4.2 | D63: 16 | E63: Peace, Justice and Strong Institutions | F63: 16.7 | G63: Inclusive, participatory decision-making | H63: Ensure responsive, inclusive, participatory and representative decision-making at all levels | I63: Primary | K63: =COUNTIF('Indicator links'!$A$2:$A$500,A63) -> 2
A64: PP4.2|8.3 | B64: PP4 | C64: PP4.2 | D64: 8 | E64: Decent Work and Economic Growth | F64: 8.3 | G64: Enterprise and small-business growth | H64: Promote development-oriented policies that support productive activities, decent job creation, entrepreneurship, creativity and innovation, and encourage the formalization and growth of micro-, small- and medium-sized enterprises, including through access to financial services | I64: Secondary | J64: development-oriented policies | K64: =COUNTIF('Indicator links'!$A$2:$A$500,A64) -> 1
A65: PP4.2|10.2 | B65: PP4 | C65: PP4.2 | D65: 10 | E65: Reduced Inequalities | F65: 10.2 | G65: Social, economic and political inclusion | H65: By 2030, empower and promote the social, economic and political inclusion of all, irrespective of age, sex, disability, race, ethnicity, origin, religion or economic or other status | I65: Secondary | J65: inclusion | K65: =COUNTIF('Indicator links'!$A$2:$A$500,A65) -> 1
A66: PP4.2|11.a | B66: PP4 | C66: PP4.2 | D66: 11 | E66: Sustainable Cities and Communities | F66: 11.a | G66: Urban–rural planning links | H66: Support positive economic, social and environmental links between urban, peri-urban and rural areas by strengthening national and regional development planning | I66: Secondary | J66: alignment of spatial and development planning | K66: =COUNTIF('Indicator links'!$A$2:$A$500,A66) -> 1
A67: PP4.2|17.14 | B67: PP4 | C67: PP4.2 | D67: 17 | E67: Partnerships for the Goals | F67: 17.14 | G67: Policy coherence | H67: Enhance policy coherence for sustainable development | I67: Secondary | J67: policy coherence | K67: =COUNTIF('Indicator links'!$A$2:$A$500,A67) -> 1

Sheet Indicator links
A1: Link ID | B1: Sub-principle | C1: SDG | D1: Target | E1: Indicator | F1: Indicator text (UNSD) | G1: Alignment | H1: Also listed under
A2: PP1.1|9.1 | B2: PP1.1 | C2: 9 | D2: 9.1 | E2: 9.1.1 | F2: Proportion of the rural population who live within 2 km of an all-season road | G2: Primary
A3: PP1.1|9.1 | B3: PP1.1 | C3: 9 | D3: 9.1 | E3: 9.1.2 | F3: Passenger and freight volumes, by mode of transport | G3: Primary
A4: PP1.1|9.4 | B4: PP1.1 | C4: 9 | D4: 9.4 | E4: 9.4.1 | F4: CO2 emission per unit of value added | G4: Primary
A5: PP1.1|9.5 | B5: PP1.1 | C5: 9 | D5: 9.5 | E5: 9.5.1 | F5: Research and development expenditure as a proportion of GDP | G5: Primary
A6: PP1.1|9.5 | B6: PP1.1 | C6: 9 | D6: 9.5 | E6: 9.5.2 | F6: Researchers (in full-time equivalent) per million inhabitants | G6: Primary
A7: PP1.1|8.2 | B7: PP1.1 | C7: 8 | D7: 8.2 | E7: 8.2.1 | F7: Annual growth rate of real GDP per employed person | G7: Secondary
A8: PP1.1|11.3 | B8: PP1.1 | C8: 11 | D8: 11.3 | E8: 11.3.1 | F8: Ratio of land consumption rate to population growth rate | G8: Secondary
A9: PP1.1|11.3 | B9: PP1.1 | C9: 11 | D9: 11.3 | E9: 11.3.2 | F9: Proportion of cities with a direct participation structure of civil society in urban planning and management that operate regularly and democratically | G9: Secondary
A10: PP1.1|12.2 | B10: PP1.1 | C10: 12 | D10: 12.2 | E10: 12.2.1 | F10: Material footprint, material footprint per capita, and material footprint per GDP | G10: Secondary | H10: 8.4.1
A11: PP1.1|12.2 | B11: PP1.1 | C11: 12 | D11: 12.2 | E11: 12.2.2 | F11: Domestic material consumption, domestic material consumption per capita, and domestic material consumption per GDP | G11: Secondary | H11: 8.4.2
A12: PP1.2|9.5 | B12: PP1.2 | C12: 9 | D12: 9.5 | E12: 9.5.1 | F12: Research and development expenditure as a proportion of GDP | G12: Primary
A13: PP1.2|9.5 | B13: PP1.2 | C13: 9 | D13: 9.5 | E13: 9.5.2 | F13: Researchers (in full-time equivalent) per million inhabitants | G13: Primary
A14: PP1.2|9.c | B14: PP1.2 | C14: 9 | D14: 9.c | E14: 9.c.1 | F14: Proportion of population covered by a mobile network, by technology | G14: Primary
A15: PP1.2|8.2 | B15: PP1.2 | C15: 8 | D15: 8.2 | E15: 8.2.1 | F15: Annual growth rate of real GDP per employed person | G15: Secondary
A16: PP1.2|16.6 | B16: PP1.2 | C16: 16 | D16: 16.6 | E16: 16.6.1 | F16: Primary government expenditures as a proportion of original approved budget, by sector (or by budget codes or similar) | G16: Secondary
A17: PP1.2|16.6 | B17: PP1.2 | C17: 16 | D17: 16.6 | E17: 16.6.2 | F17: Proportion of population satisfied with their last experience of public services | G17: Secondary
A18: PP1.2|16.10 | B18: PP1.2 | C18: 16 | D18: 16.10 | E18: 16.10.1 | F18: Number of verified cases of killing, kidnapping, enforced disappearance, arbitrary detention and torture of journalists, associated media personnel, trade unionists and human rights advocates in the previous 12 months | G18: Secondary
A19: PP1.2|16.10 | B19: PP1.2 | C19: 16 | D19: 16.10 | E19: 16.10.2 | F19: Number of countries that adopt and implement constitutional, statutory and/or policy guarantees for public access to information | G19: Secondary
A20: PP1.2|17.8 | B20: PP1.2 | C20: 17 | D20: 17.8 | E20: 17.8.1 | F20: Proportion of individuals using the Internet | G20: Secondary
A21: PP2.1|9.1 | B21: PP2.1 | C21: 9 | D21: 9.1 | E21: 9.1.1 | F21: Proportion of the rural population who live within 2 km of an all-season road | G21: Primary
A22: PP2.1|9.1 | B22: PP2.1 | C22: 9 | D22: 9.1 | E22: 9.1.2 | F22: Passenger and freight volumes, by mode of transport | G22: Primary
A23: PP2.1|13.1 | B23: PP2.1 | C23: 13 | D23: 13.1 | E23: 13.1.1 | F23: Number of deaths, missing persons and directly affected persons attributed to disasters per 100,000 population | G23: Primary | H23: 1.5.1, 11.5.1
A24: PP2.1|13.1 | B24: PP2.1 | C24: 13 | D24: 13.1 | E24: 13.1.2 | F24: Number of countries that adopt and implement national disaster risk reduction strategies in line with the Sendai Framework for Disaster Risk Reduction 2015–2030 | G24: Primary | H24: 1.5.3, 11.b.1
A25: PP2.1|13.1 | B25: PP2.1 | C25: 13 | D25: 13.1 | E25: 13.1.3 | F25: Proportion of local governments that adopt and implement local disaster risk reduction strategies in line with national disaster risk reduction strategies | G25: Primary | H25: 1.5.4, 11.b.2
A26: PP2.1|13.2 | B26: PP2.1 | C26: 13 | D26: 13.2 | E26: 13.2.1 | F26: Number of countries with reports under the Paris Agreement, as submitted to the secretariat of the United Nations Framework Convention on Climate Change | G26: Primary
A27: PP2.1|13.2 | B27: PP2.1 | C27: 13 | D27: 13.2 | E27: 13.2.2 | F27: Total greenhouse gas emissions per year | G27: Primary
A28: PP2.1|6.4 | B28: PP2.1 | C28: 6 | D28: 6.4 | E28: 6.4.1 | F28: Change in water-use efficiency over time | G28: Secondary
A29: PP2.1|6.4 | B29: PP2.1 | C29: 6 | D29: 6.4 | E29: 6.4.2 | F29: Level of water stress: freshwater withdrawal as a proportion of available freshwater resources | G29: Secondary
A30: PP2.1|6.5 | B30: PP2.1 | C30: 6 | D30: 6.5 | E30: 6.5.1 | F30: Degree of integrated water resources management | G30: Secondary
A31: PP2.1|6.5 | B31: PP2.1 | C31: 6 | D31: 6.5 | E31: 6.5.2 | F31: Proportion of transboundary basin area with an operational arrangement for water cooperation | G31: Secondary
A32: PP2.1|7.2 | B32: PP2.1 | C32: 7 | D32: 7.2 | E32: 7.2.1 | F32: Renewable energy share in the total final energy consumption | G32: Secondary
A33: PP2.1|7.3 | B33: PP2.1 | C33: 7 | D33: 7.3 | E33: 7.3.1 | F33: Energy intensity measured in terms of primary energy and GDP | G33: Secondary
A34: PP2.1|11.5 | B34: PP2.1 | C34: 11 | D34: 11.5 | E34: 11.5.1 | F34: Number of deaths, missing persons and directly affected persons attributed to disasters per 100,000 population | G34: Secondary | H34: 1.5.1, 13.1.1
A35: PP2.1|11.5 | B35: PP2.1 | C35: 11 | D35: 11.5 | E35: 11.5.2 | F35: Direct economic loss attributed to disasters in relation to global gross domestic product (GDP) | G35: Secondary | H35: 1.5.2
A36: PP2.1|11.5 | B36: PP2.1 | C36: 11 | D36: 11.5 | E36: 11.5.3 | F36: (a) Damage to critical infrastructure and (b) number of disruptions to basic services, attributed to disasters | G36: Secondary
A37: PP2.1|11.b | B37: PP2.1 | C37: 11 | D37: 11.b | E37: 11.b.1 | F37: Number of countries that adopt and implement national disaster risk reduction strategies in line with the Sendai Framework for Disaster Risk Reduction 2015–2030 | G37: Secondary | H37: 1.5.3, 13.1.2
A38: PP2.1|11.b | B38: PP2.1 | C38: 11 | D38: 11.b | E38: 11.b.2 | F38: Proportion of local governments that adopt and implement local disaster risk reduction strategies in line with national disaster risk reduction strategies | G38: Secondary | H38: 1.5.4, 13.1.3
A39: PP2.1|12.2 | B39: PP2.1 | C39: 12 | D39: 12.2 | E39: 12.2.1 | F39: Material footprint, material footprint per capita, and material footprint per GDP | G39: Secondary | H39: 8.4.1
A40: PP2.1|12.2 | B40: PP2.1 | C40: 12 | D40: 12.2 | E40: 12.2.2 | F40: Domestic material consumption, domestic material consumption per capita, and domestic material consumption per GDP | G40: Secondary | H40: 8.4.2
A41: PP2.2|11.3 | B41: PP2.2 | C41: 11 | D41: 11.3 | E41: 11.3.1 | F41: Ratio of land consumption rate to population growth rate | G41: Primary
A42: PP2.2|11.3 | B42: PP2.2 | C42: 11 | D42: 11.3 | E42: 11.3.2 | F42: Proportion of cities with a direct participation structure of civil society in urban planning and management that operate regularly and democratically | G42: Primary
A43: PP2.2|11.a | B43: PP2.2 | C43: 11 | D43: 11.a | E43: 11.a.1 | F43: Number of countries that have national urban policies or regional development plans that (a) respond to population dynamics; (b) ensure balanced territorial development; and (c) increase local fiscal space | G43: Primary
A44: PP2.2|9.1 | B44: PP2.2 | C44: 9 | D44: 9.1 | E44: 9.1.1 | F44: Proportion of the rural population who live within 2 km of an all-season road | G44: Secondary
A45: PP2.2|9.1 | B45: PP2.2 | C45: 9 | D45: 9.1 | E45: 9.1.2 | F45: Passenger and freight volumes, by mode of transport | G45: Secondary
A46: PP2.2|13.2 | B46: PP2.2 | C46: 13 | D46: 13.2 | E46: 13.2.1 | F46: Number of countries with reports under the Paris Agreement, as submitted to the secretariat of the United Nations Framework Convention on Climate Change | G46: Secondary
A47: PP2.2|13.2 | B47: PP2.2 | C47: 13 | D47: 13.2 | E47: 13.2.2 | F47: Total greenhouse gas emissions per year | G47: Secondary
A48: PP2.2|17.14 | B48: PP2.2 | C48: 17 | D48: 17.14 | E48: 17.14.1 | F48: Number of countries with mechanisms in place to enhance policy coherence of sustainable development | G48: Secondary
A49: PP2.2|17.16 | B49: PP2.2 | C49: 17 | D49: 17.16 | E49: 17.16.1 | F49: Number of countries reporting progress in multi-stakeholder development effectiveness monitoring frameworks that support the achievement of the Sustainable Development Goals | G49: Secondary
A50: PP2.2|17.17 | B50: PP2.2 | C50: 17 | D50: 17.17 | E50: 17.17.1 | F50: Amount in United States dollars committed to public-private partnerships for infrastructure | G50: Secondary
A51: PP2.3|12.2 | B51: PP2.3 | C51: 12 | D51: 12.2 | E51: 12.2.1 | F51: Material footprint, material footprint per capita, and material footprint per GDP | G51: Primary | H51: 8.4.1
A52: PP2.3|12.2 | B52: PP2.3 | C52: 12 | D52: 12.2 | E52: 12.2.2 | F52: Domestic material consumption, domestic material consumption per capita, and domestic material consumption per GDP | G52: Primary | H52: 8.4.2
A53: PP2.3|12.7 | B53: PP2.3 | C53: 12 | D53: 12.7 | E53: 12.7.1 | F53: Number of countries implementing sustainable public procurement policies and action plans | G53: Primary
A54: PP2.3|8.3 | B54: PP2.3 | C54: 8 | D54: 8.3 | E54: 8.3.1 | F54: Proportion of informal employment in total employment, by sector and sex | G54: Secondary
A55: PP2.3|9.4 | B55: PP2.3 | C55: 9 | D55: 9.4 | E55: 9.4.1 | F55: CO2 emission per unit of value added | G55: Secondary
A56: PP2.3|11.6 | B56: PP2.3 | C56: 11 | D56: 11.6 | E56: 11.6.1 | F56: Proportion of municipal solid waste collected and managed in controlled facilities out of total municipal waste generated, by cities | G56: Secondary
A57: PP2.3|11.6 | B57: PP2.3 | C57: 11 | D57: 11.6 | E57: 11.6.2 | F57: Annual mean levels of fine particulate matter (e.g. PM2.5 and PM10) in cities (population weighted) | G57: Secondary
A58: PP2.3|13.2 | B58: PP2.3 | C58: 13 | D58: 13.2 | E58: 13.2.1 | F58: Number of countries with reports under the Paris Agreement, as submitted to the secretariat of the United Nations Framework Convention on Climate Change | G58: Secondary
A59: PP2.3|13.2 | B59: PP2.3 | C59: 13 | D59: 13.2 | E59: 13.2.2 | F59: Total greenhouse gas emissions per year | G59: Secondary
A60: PP3.1|11.1 | B60: PP3.1 | C60: 11 | D60: 11.1 | E60: 11.1.1 | F60: Proportion of urban population living in slums, informal settlements or inadequate housing | G60: Primary
A61: PP3.1|11.2 | B61: PP3.1 | C61: 11 | D61: 11.2 | E61: 11.2.1 | F61: Proportion of population that has convenient access to public transport, by sex, age and persons with disabilities | G61: Primary
A62: PP3.1|11.3 | B62: PP3.1 | C62: 11 | D62: 11.3 | E62: 11.3.1 | F62: Ratio of land consumption rate to population growth rate | G62: Primary
A63: PP3.1|11.3 | B63: PP3.1 | C63: 11 | D63: 11.3 | E63: 11.3.2 | F63: Proportion of cities with a direct participation structure of civil society in urban planning and management that operate regularly and democratically | G63: Primary
A64: PP3.1|11.a | B64: PP3.1 | C64: 11 | D64: 11.a | E64: 11.a.1 | F64: Number of countries that have national urban policies or regional development plans that (a) respond to population dynamics; (b) ensure balanced territorial development; and (c) increase local fiscal space | G64: Primary
... A104: PP4.2|17.14 | B104: PP4.2 | C104: 17 | D104: 17.14 | E104: 17.14.1 | F104: Number of countries with mechanisms in place to enhance policy coherence of sustainable development | G104: Secondary

Sheet Projects
A1: Project ID | B1: Project name | C1: Department | D1: Location | E1: Sector | F1: Stage gate | G1: Project lead | H1: Assessment date | I1: Evaluators | J1: Score | K1: Outcome
A2: P001 | B2: Elsies River CHC and BFI Sub | C2: Department of Health | D2: Groote Schuur Hospital | E2: Social | F2: Stage 3 – Design Development | G2: Milne van Leeuwen | H2: 45910 | I2: =IF(A2="","",COUNTIFS(ps_pid,A2,ps_sub,"PP1.1")) -> 6 | J2: =IF(A2="","",IFERROR(SUMIFS(ps_points,ps_pid,A2)/SUMIFS(ps_weight,ps_pid,A2),"")) -> 0.84 | K2: =IF(J2="","",IF(J2>=0.8,"Bankable portfolio",IF(J2>=0.5,"Return to step 2","Rework"))) -> Bankable portfolio
I3: =IF(A3="","",COUNTIFS(ps_pid,A3,ps_sub,"PP1.1")) | J3: =IF(A3="","",IFERROR(SUMIFS(ps_points,ps_pid,A3)/SUMIFS(ps_weight,ps_pid,A3),"")) | K3: =IF(J3="","",IF(J3>=0.8,"Bankable portfolio",IF(J3>=0.5,"Return to step 2","Rework")))
I4: =IF(A4="","",COUNTIFS(ps_pid,A4,ps_sub,"PP1.1")) | J4: =IF(A4="","",IFERROR(SUMIFS(ps_points,ps_pid,A4)/SUMIFS(ps_weight,ps_pid,A4),"")) | K4: =IF(J4="","",IF(J4>=0.8,"Bankable portfolio",IF(J4>=0.5,"Return to step 2","Rework")))
I5: =IF(A5="","",COUNTIFS(ps_pid,A5,ps_sub,"PP1.1")) | J5: =IF(A5="","",IFERROR(SUMIFS(ps_points,ps_pid,A5)/SUMIFS(ps_weight,ps_pid,A5),"")) | K5: =IF(J5="","",IF(J5>=0.8,"Bankable portfolio",IF(J5>=0.5,"Return to step 2","Rework")))
I6: =IF(A6="","",COUNTIFS(ps_pid,A6,ps_sub,"PP1.1")) | J6: =IF(A6="","",IFERROR(SUMIFS(ps_points,ps_pid,A6)/SUMIFS(ps_weight,ps_pid,A6),"")) | K6: =IF(J6="","",IF(J6>=0.8,"Bankable portfolio",IF(J6>=0.5,"Return to step 2","Rework")))
I7: =IF(A7="","",COUNTIFS(ps_pid,A7,ps_sub,"PP1.1")) | J7: =IF(A7="","",IFERROR(SUMIFS(ps_points,ps_pid,A7)/SUMIFS(ps_weight,ps_pid,A7),"")) | K7: =IF(J7="","",IF(J7>=0.8,"Bankable portfolio",IF(J7>=0.5,"Return to step 2","Rework")))
I8: =IF(A8="","",COUNTIFS(ps_pid,A8,ps_sub,"PP1.1")) | J8: =IF(A8="","",IFERROR(SUMIFS(ps_points,ps_pid,A8)/SUMIFS(ps_weight,ps_pid,A8),"")) | K8: =IF(J8="","",IF(J8>=0.8,"Bankable portfolio",IF(J8>=0.5,"Return to step 2","Rework")))
I9: =IF(A9="","",COUNTIFS(ps_pid,A9,ps_sub,"PP1.1")) | J9: =IF(A9="","",IFERROR(SUMIFS(ps_points,ps_pid,A9)/SUMIFS(ps_weight,ps_pid,A9),"")) | K9: =IF(J9="","",IF(J9>=0.8,"Bankable portfolio",IF(J9>=0.5,"Return to step 2","Rework")))
I10: =IF(A10="","",COUNTIFS(ps_pid,A10,ps_sub,"PP1.1")) | J10: =IF(A10="","",IFERROR(SUMIFS(ps_points,ps_pid,A10)/SUMIFS(ps_weight,ps_pid,A10),"")) | K10: =IF(J10="","",IF(J10>=0.8,"Bankable portfolio",IF(J10>=0.5,"Return to step 2","Rework")))
I11: =IF(A11="","",COUNTIFS(ps_pid,A11,ps_sub,"PP1.1")) | J11: =IF(A11="","",IFERROR(SUMIFS(ps_points,ps_pid,A11)/SUMIFS(ps_weight,ps_pid,A11),"")) | K11: =IF(J11="","",IF(J11>=0.8,"Bankable portfolio",IF(J11>=0.5,"Return to step 2","Rework")))
I12: =IF(A12="","",COUNTIFS(ps_pid,A12,ps_sub,"PP1.1")) | J12: =IF(A12="","",IFERROR(SUMIFS(ps_points,ps_pid,A12)/SUMIFS(ps_weight,ps_pid,A12),"")) | K12: =IF(J12="","",IF(J12>=0.8,"Bankable portfolio",IF(J12>=0.5,"Return to step 2","Rework")))
I13: =IF(A13="","",COUNTIFS(ps_pid,A13,ps_sub,"PP1.1")) | J13: =IF(A13="","",IFERROR(SUMIFS(ps_points,ps_pid,A13)/SUMIFS(ps_weight,ps_pid,A13),"")) | K13: =IF(J13="","",IF(J13>=0.8,"Bankable portfolio",IF(J13>=0.5,"Return to step 2","Rework")))
I14: =IF(A14="","",COUNTIFS(ps_pid,A14,ps_sub,"PP1.1")) | J14: =IF(A14="","",IFERROR(SUMIFS(ps_points,ps_pid,A14)/SUMIFS(ps_weight,ps_pid,A14),"")) | K14: =IF(J14="","",IF(J14>=0.8,"Bankable portfolio",IF(J14>=0.5,"Return to step 2","Rework")))
... I200: =IF(A200="","",COUNTIFS(ps_pid,A200,ps_sub,"PP1.1")) | J200: =IF(A200="","",IFERROR(SUMIFS(ps_points,ps_pid,A200)/SUMIFS(ps_weight,ps_pid,A200),"")) | K200: =IF(J200="","",IF(J200>=0.8,"Bankable portfolio",IF(J200>=0.5,"Return to step 2","Rework")))

Sheet Project scores
A1: Project ID | B1: Evaluator | C1: Sub-principle | D1: Score (1–5) | E1: Comment | F1: Weight | G1: Weighted points
A2: P001 | B2: Chris Maud | C2: PP1.1 | D2: 4 | E2: Highly specified work. Skills for Installations and infrastructure is local | F2: =IF(C2="","",IFERROR(INDEX('Sub-principles'!$E$2:$E$11,MATCH(C2,'Sub-principles'!$A$2:$A$11,0)),"")) -> 8 | G2: =IF(OR(D2="",F2=""),"",D2/5*F2) -> 6.4
A3: P001 | B3: Chris Maud | C3: PP1.2 | D3: 5 | E3: Limiting of systems which then allows ease of operations; Can be operated remotely | F3: =IF(C3="","",IFERROR(INDEX('Sub-principles'!$E$2:$E$11,MATCH(C3,'Sub-principles'!$A$2:$A$11,0)),"")) -> 8 | G3: =IF(OR(D3="",F3=""),"",D3/5*F3) -> 8
A4: P001 | B4: Chris Maud | C4: PP2.1 | D4: 5 | E4: Regenerating sustainability; Risk mitigation | F4: =IF(C4="","",IFERROR(INDEX('Sub-principles'!$E$2:$E$11,MATCH(C4,'Sub-principles'!$A$2:$A$11,0)),"")) -> 8 | G4: =IF(OR(D4="",F4=""),"",D4/5*F4) -> 8
A5: P001 | B5: Chris Maud | C5: PP2.2 | D5: 5 | E5: Collaborative planning approach; supports ecosystem viability | F5: =IF(C5="","",IFERROR(INDEX('Sub-principles'!$E$2:$E$11,MATCH(C5,'Sub-principles'!$A$2:$A$11,0)),"")) -> 8 | G5: =IF(OR(D5="",F5=""),"",D5/5*F5) -> 8
A6: P001 | B6: Chris Maud | C6: PP2.3 | D6: 4 | E6: Supervisory system which makes it easier to run the hospital (makes maintenance easier); Various ways you can monitor power flow through the network | F6: =IF(C6="","",IFERROR(INDEX('Sub-principles'!$E$2:$E$11,MATCH(C6,'Sub-principles'!$A$2:$A$11,0)),"")) -> 8 | G6: =IF(OR(D6="",F6=""),"",D6/5*F6) -> 6.4
A7: P001 | B7: Chris Maud | C7: PP3.1 | D7: 4 | E7: Supports concept of spatial justice as makes it sustainable platform of operations within a new primary system; Derisking the facility; Improving the accessibility of Groote Schuur | F7: =IF(C7="","",IFERROR(INDEX('Sub-principles'!$E$2:$E$11,MATCH(C7,'Sub-principles'!$A$2:$A$11,0)),"")) -> 8 | G7: =IF(OR(D7="",F7=""),"",D7/5*F7) -> 6.4
A8: P001 | B8: Chris Maud | C8: PP3.2 | D8: 4 | E8: Same argument as principle 3.1 | F8: =IF(C8="","",IFERROR(INDEX('Sub-principles'!$E$2:$E$11,MATCH(C8,'Sub-principles'!$A$2:$A$11,0)),"")) -> 8 | G8: =IF(OR(D8="",F8=""),"",D8/5*F8) -> 6.4
A9: P001 | B9: Chris Maud | C9: PP3.3 | D9: 3 | E9: Management contractor runs procurement process. Which is limited | F9: =IF(C9="","",IFERROR(INDEX('Sub-principles'!$E$2:$E$11,MATCH(C9,'Sub-principles'!$A$2:$A$11,0)),"")) -> 16 | G9: =IF(OR(D9="",F9=""),"",D9/5*F9) -> 9.6
A10: P001 | B10: Chris Maud | C10: PP4.1 | D10: 5 | E10: PFMA, Governance, all qualified audits are good (aligned to all prescripts) | F10: =IF(C10="","",IFERROR(INDEX('Sub-principles'!$E$2:$E$11,MATCH(C10,'Sub-principles'!$A$2:$A$11,0)),"")) -> 20 | G10: =IF(OR(D10="",F10=""),"",D10/5*F10) -> 20
A11: P001 | B11: Chris Maud | C11: PP4.2 | D11: 3 | E11: Enables sustainable developments on precinct; less job opportunities will be created- takes score down to a 3 | F11: =IF(C11="","",IFERROR(INDEX('Sub-principles'!$E$2:$E$11,MATCH(C11,'Sub-principles'!$A$2:$A$11,0)),"")) -> 8 | G11: =IF(OR(D11="",F11=""),"",D11/5*F11) -> 4.8
A12: P001 | B12: Bitshoko Chauice | C12: PP1.1 | D12: 4 | F12: =IF(C12="","",IFERROR(INDEX('Sub-principles'!$E$2:$E$11,MATCH(C12,'Sub-principles'!$A$2:$A$11,0)),"")) -> 8 | G12: =IF(OR(D12="",F12=""),"",D12/5*F12) -> 6.4
A13: P001 | B13: Bitshoko Chauice | C13: PP1.2 | D13: 5 | F13: =IF(C13="","",IFERROR(INDEX('Sub-principles'!$E$2:$E$11,MATCH(C13,'Sub-principles'!$A$2:$A$11,0)),"")) -> 8 | G13: =IF(OR(D13="",F13=""),"",D13/5*F13) -> 8
A14: P001 | B14: Bitshoko Chauice | C14: PP2.1 | D14: 5 | F14: =IF(C14="","",IFERROR(INDEX('Sub-principles'!$E$2:$E$11,MATCH(C14,'Sub-principles'!$A$2:$A$11,0)),"")) -> 8 | G14: =IF(OR(D14="",F14=""),"",D14/5*F14) -> 8
A15: P001 | B15: Bitshoko Chauice | C15: PP2.2 | D15: 5 | F15: =IF(C15="","",IFERROR(INDEX('Sub-principles'!$E$2:$E$11,MATCH(C15,'Sub-principles'!$A$2:$A$11,0)),"")) -> 8 | G15: =IF(OR(D15="",F15=""),"",D15/5*F15) -> 8
A16: P001 | B16: Bitshoko Chauice | C16: PP2.3 | D16: 4 | F16: =IF(C16="","",IFERROR(INDEX('Sub-principles'!$E$2:$E$11,MATCH(C16,'Sub-principles'!$A$2:$A$11,0)),"")) -> 8 | G16: =IF(OR(D16="",F16=""),"",D16/5*F16) -> 6.4
A17: P001 | B17: Bitshoko Chauice | C17: PP3.1 | D17: 4 | F17: =IF(C17="","",IFERROR(INDEX('Sub-principles'!$E$2:$E$11,MATCH(C17,'Sub-principles'!$A$2:$A$11,0)),"")) -> 8 | G17: =IF(OR(D17="",F17=""),"",D17/5*F17) -> 6.4
A18: P001 | B18: Bitshoko Chauice | C18: PP3.2 | D18: 4 | F18: =IF(C18="","",IFERROR(INDEX('Sub-principles'!$E$2:$E$11,MATCH(C18,'Sub-principles'!$A$2:$A$11,0)),"")) -> 8 | G18: =IF(OR(D18="",F18=""),"",D18/5*F18) -> 6.4
A19: P001 | B19: Bitshoko Chauice | C19: PP3.3 | D19: 3 | F19: =IF(C19="","",IFERROR(INDEX('Sub-principles'!$E$2:$E$11,MATCH(C19,'Sub-principles'!$A$2:$A$11,0)),"")) -> 16 | G19: =IF(OR(D19="",F19=""),"",D19/5*F19) -> 9.6
A20: P001 | B20: Bitshoko Chauice | C20: PP4.1 | D20: 5 | F20: =IF(C20="","",IFERROR(INDEX('Sub-principles'!$E$2:$E$11,MATCH(C20,'Sub-principles'!$A$2:$A$11,0)),"")) -> 20 | G20: =IF(OR(D20="",F20=""),"",D20/5*F20) -> 20
A21: P001 | B21: Bitshoko Chauice | C21: PP4.2 | D21: 3 | F21: =IF(C21="","",IFERROR(INDEX('Sub-principles'!$E$2:$E$11,MATCH(C21,'Sub-principles'!$A$2:$A$11,0)),"")) -> 8 | G21: =IF(OR(D21="",F21=""),"",D21/5*F21) -> 4.8
A22: P001 | B22: Milne van Leeuwen | C22: PP1.1 | D22: 4 | E22: Limited technology available; Mostly imported tech; do have local skills that can sell and maintain tech; Similar to new installations such as Tygerberg | F22: =IF(C22="","",IFERROR(INDEX('Sub-principles'!$E$2:$E$11,MATCH(C22,'Sub-principles'!$A$2:$A$11,0)),"")) -> 8 | G22: =IF(OR(D22="",F22=""),"",D22/5*F22) -> 6.4
A23: P001 | B23: Milne van Leeuwen | C23: PP1.2 | D23: 5 | E23: Fiber system linking electronics; remotely able to operate the system from a central point; SETA component is separate to this as it has to run on a separate ethernet; So largely standalone (separate ethernet network); Protection of cyber attack - need to understand how system runs on the speed | F23: =IF(C23="","",IFERROR(INDEX('Sub-principles'!$E$2:$E$11,MATCH(C23,'Sub-principles'!$A$2:$A$11,0)),"")) -> 8 | G23: =IF(OR(D23="",F23=""),"",D23/5*F23) -> 8
A24: P001 | B24: Milne van Leeuwen | C24: PP2.1 | D24: 5 | E24: Regenerating sustainability; Risk mitigation | F24: =IF(C24="","",IFERROR(INDEX('Sub-principles'!$E$2:$E$11,MATCH(C24,'Sub-principles'!$A$2:$A$11,0)),"")) -> 8 | G24: =IF(OR(D24="",F24=""),"",D24/5*F24) -> 8
A25: P001 | B25: Milne van Leeuwen | C25: PP2.2 | D25: 5 | E25: Collaborative planning approach; supports ecosystem viability | F25: =IF(C25="","",IFERROR(INDEX('Sub-principles'!$E$2:$E$11,MATCH(C25,'Sub-principles'!$A$2:$A$11,0)),"")) -> 8 | G25: =IF(OR(D25="",F25=""),"",D25/5*F25) -> 8
A26: P001 | B26: Milne van Leeuwen | C26: PP2.3 | D26: 4 | E26: Supervisory system which makes it easier to run the hospital (makes maintenance easier); Various ways you can monitor power flow through the network | F26: =IF(C26="","",IFERROR(INDEX('Sub-principles'!$E$2:$E$11,MATCH(C26,'Sub-principles'!$A$2:$A$11,0)),"")) -> 8 | G26: =IF(OR(D26="",F26=""),"",D26/5*F26) -> 6.4
A27: P001 | B27: Milne van Leeuwen | C27: PP3.1 | D27: 4 | E27: Supports concept of spatial justice as makes it sustainable platform of operations within a new primary system; Derisking the facility; Improving the accessibility of Groote Schuur | F27: =IF(C27="","",IFERROR(INDEX('Sub-principles'!$E$2:$E$11,MATCH(C27,'Sub-principles'!$A$2:$A$11,0)),"")) -> 8 | G27: =IF(OR(D27="",F27=""),"",D27/5*F27) -> 6.4
A28: P001 | B28: Milne van Leeuwen | C28: PP3.2 | D28: 4 | E28: Same argument as principle 3.1 | F28: =IF(C28="","",IFERROR(INDEX('Sub-principles'!$E$2:$E$11,MATCH(C28,'Sub-principles'!$A$2:$A$11,0)),"")) -> 8 | G28: =IF(OR(D28="",F28=""),"",D28/5*F28) -> 6.4
A29: P001 | B29: Milne van Leeuwen | C29: PP3.3 | D29: 3 | E29: Management contractor runs procurement process. Which is limited | F29: =IF(C29="","",IFERROR(INDEX('Sub-principles'!$E$2:$E$11,MATCH(C29,'Sub-principles'!$A$2:$A$11,0)),"")) -> 16 | G29: =IF(OR(D29="",F29=""),"",D29/5*F29) -> 9.6
A30: P001 | B30: Milne van Leeuwen | C30: PP4.1 | D30: 5 | E30: PFMA, Governance, all qualified audits are good (aligned to all prescripts) | F30: =IF(C30="","",IFERROR(INDEX('Sub-principles'!$E$2:$E$11,MATCH(C30,'Sub-principles'!$A$2:$A$11,0)),"")) -> 20 | G30: =IF(OR(D30="",F30=""),"",D30/5*F30) -> 20
A31: P001 | B31: Milne van Leeuwen | C31: PP4.2 | D31: 3 | E31: Enables sustainable developments on precinct; less job opportunities will be created- takes score down to a 3 | F31: =IF(C31="","",IFERROR(INDEX('Sub-principles'!$E$2:$E$11,MATCH(C31,'Sub-principles'!$A$2:$A$11,0)),"")) -> 8 | G31: =IF(OR(D31="",F31=""),"",D31/5*F31) -> 4.8
A32: P001 | B32: Altaf Kumandan | C32: PP1.1 | D32: 4 | E32: Limited technology available; Mostly imported tech; do have local skills that can sell and maintain tech; Similar to new installations such as Tygerberg | F32: =IF(C32="","",IFERROR(INDEX('Sub-principles'!$E$2:$E$11,MATCH(C32,'Sub-principles'!$A$2:$A$11,0)),"")) -> 8 | G32: =IF(OR(D32="",F32=""),"",D32/5*F32) -> 6.4
A33: P001 | B33: Altaf Kumandan | C33: PP1.2 | D33: 5 | E33: Fiber system linking electronics; remotely able to operate the system from a central point; SETA component is separate to this as it has to run on a separate ethernet; So largely standalone (separate ethernet network); Protection of cyber attack - need to understand how system runs on the speed | F33: =IF(C33="","",IFERROR(INDEX('Sub-principles'!$E$2:$E$11,MATCH(C33,'Sub-principles'!$A$2:$A$11,0)),"")) -> 8 | G33: =IF(OR(D33="",F33=""),"",D33/5*F33) -> 8
... A41: P001 | B41: Altaf Kumandan | C41: PP4.2 | D41: 3 | E41: Enables sustainable developments on precinct; less job opportunities will be created- takes score down to a 3 | F41: =IF(C41="","",IFERROR(INDEX('Sub-principles'!$E$2:$E$11,MATCH(C41,'Sub-principles'!$A$2:$A$11,0)),"")) -> 8 | G41: =IF(OR(D41="",F41=""),"",D41/5*F41) -> 4.8
A42: P001 | B42: KD Govender-Moller | C42: PP1.1 | D42: 4 | F42: =IF(C42="","",IFERROR(INDEX('Sub-principles'!$E$2:$E$11,MATCH(C42,'Sub-principles'!$A$2:$A$11,0)),"")) -> 8 | G42: =IF(OR(D42="",F42=""),"",D42/5*F42) -> 6.4
A43: P001 | B43: KD Govender-Moller | C43: PP1.2 | D43: 5 | F43: =IF(C43="","",IFERROR(INDEX('Sub-principles'!$E$2:$E$11,MATCH(C43,'Sub-principles'!$A$2:$A$11,0)),"")) -> 8 | G43: =IF(OR(D43="",F43=""),"",D43/5*F43) -> 8
A44: P001 | B44: KD Govender-Moller | C44: PP2.1 | D44: 5 | F44: =IF(C44="","",IFERROR(INDEX('Sub-principles'!$E$2:$E$11,MATCH(C44,'Sub-principles'!$A$2:$A$11,0)),"")) -> 8 | G44: =IF(OR(D44="",F44=""),"",D44/5*F44) -> 8
A45: P001 | B45: KD Govender-Moller | C45: PP2.2 | D45: 5 | F45: =IF(C45="","",IFERROR(INDEX('Sub-principles'!$E$2:$E$11,MATCH(C45,'Sub-principles'!$A$2:$A$11,0)),"")) -> 8 | G45: =IF(OR(D45="",F45=""),"",D45/5*F45) -> 8
A46: P001 | B46: KD Govender-Moller | C46: PP2.3 | D46: 4 | F46: =IF(C46="","",IFERROR(INDEX('Sub-principles'!$E$2:$E$11,MATCH(C46,'Sub-principles'!$A$2:$A$11,0)),"")) -> 8 | G46: =IF(OR(D46="",F46=""),"",D46/5*F46) -> 6.4
A47: P001 | B47: KD Govender-Moller | C47: PP3.1 | D47: 4 | F47: =IF(C47="","",IFERROR(INDEX('Sub-principles'!$E$2:$E$11,MATCH(C47,'Sub-principles'!$A$2:$A$11,0)),"")) -> 8 | G47: =IF(OR(D47="",F47=""),"",D47/5*F47) -> 6.4
A48: P001 | B48: KD Govender-Moller | C48: PP3.2 | D48: 4 | F48: =IF(C48="","",IFERROR(INDEX('Sub-principles'!$E$2:$E$11,MATCH(C48,'Sub-principles'!$A$2:$A$11,0)),"")) -> 8 | G48: =IF(OR(D48="",F48=""),"",D48/5*F48) -> 6.4
A49: P001 | B49: KD Govender-Moller | C49: PP3.3 | D49: 3 | F49: =IF(C49="","",IFERROR(INDEX('Sub-principles'!$E$2:$E$11,MATCH(C49,'Sub-principles'!$A$2:$A$11,0)),"")) -> 16 | G49: =IF(OR(D49="",F49=""),"",D49/5*F49) -> 9.6
A50: P001 | B50: KD Govender-Moller | C50: PP4.1 | D50: 5 | F50: =IF(C50="","",IFERROR(INDEX('Sub-principles'!$E$2:$E$11,MATCH(C50,'Sub-principles'!$A$2:$A$11,0)),"")) -> 20 | G50: =IF(OR(D50="",F50=""),"",D50/5*F50) -> 20
A51: P001 | B51: KD Govender-Moller | C51: PP4.2 | D51: 3 | F51: =IF(C51="","",IFERROR(INDEX('Sub-principles'!$E$2:$E$11,MATCH(C51,'Sub-principles'!$A$2:$A$11,0)),"")) -> 8 | G51: =IF(OR(D51="",F51=""),"",D51/5*F51) -> 4.8
A52: P001 | B52: S van Schalkwyk | C52: PP1.1 | D52: 4 | E52: Limited technology available; Mostly imported tech; do have local skills that can sell and maintain tech; Similar to new installations such as Tygerberg | F52: =IF(C52="","",IFERROR(INDEX('Sub-principles'!$E$2:$E$11,MATCH(C52,'Sub-principles'!$A$2:$A$11,0)),"")) -> 8 | G52: =IF(OR(D52="",F52=""),"",D52/5*F52) -> 6.4
A53: P001 | B53: S van Schalkwyk | C53: PP1.2 | D53: 5 | E53: Fiber system linking electronics; remotely able to operate the system from a central point; SETA component is separate to this as it has to run on a separate ethernet; So largely standalone (separate ethernet network); Protection of cyber attack - need to understand how system runs on the speed | F53: =IF(C53="","",IFERROR(INDEX('Sub-principles'!$E$2:$E$11,MATCH(C53,'Sub-principles'!$A$2:$A$11,0)),"")) -> 8 | G53: =IF(OR(D53="",F53=""),"",D53/5*F53) -> 8
A54: P001 | B54: S van Schalkwyk | C54: PP2.1 | D54: 5 | E54: Regenerating sustainability; Risk mitigation | F54: =IF(C54="","",IFERROR(INDEX('Sub-principles'!$E$2:$E$11,MATCH(C54,'Sub-principles'!$A$2:$A$11,0)),"")) -> 8 | G54: =IF(OR(D54="",F54=""),"",D54/5*F54) -> 8
A55: P001 | B55: S van Schalkwyk | C55: PP2.2 | D55: 5 | E55: Collaborative planning approach; supports ecosystem viability | F55: =IF(C55="","",IFERROR(INDEX('Sub-principles'!$E$2:$E$11,MATCH(C55,'Sub-principles'!$A$2:$A$11,0)),"")) -> 8 | G55: =IF(OR(D55="",F55=""),"",D55/5*F55) -> 8
A56: P001 | B56: S van Schalkwyk | C56: PP2.3 | D56: 4 | E56: Supervisory system which makes it easier to run the hospital (makes maintenance easier); Various ways you can monitor power flow through the network | F56: =IF(C56="","",IFERROR(INDEX('Sub-principles'!$E$2:$E$11,MATCH(C56,'Sub-principles'!$A$2:$A$11,0)),"")) -> 8 | G56: =IF(OR(D56="",F56=""),"",D56/5*F56) -> 6.4
A57: P001 | B57: S van Schalkwyk | C57: PP3.1 | D57: 4 | E57: Supports concept of spatial justice as makes it sustainable platform of operations within a new primary system; Derisking the facility; Improving the accessibility of Groote Schuur | F57: =IF(C57="","",IFERROR(INDEX('Sub-principles'!$E$2:$E$11,MATCH(C57,'Sub-principles'!$A$2:$A$11,0)),"")) -> 8 | G57: =IF(OR(D57="",F57=""),"",D57/5*F57) -> 6.4
A58: P001 | B58: S van Schalkwyk | C58: PP3.2 | D58: 4 | E58: Same argument as principle 3.1 | F58: =IF(C58="","",IFERROR(INDEX('Sub-principles'!$E$2:$E$11,MATCH(C58,'Sub-principles'!$A$2:$A$11,0)),"")) -> 8 | G58: =IF(OR(D58="",F58=""),"",D58/5*F58) -> 6.4
A59: P001 | B59: S van Schalkwyk | C59: PP3.3 | D59: 3 | E59: Management contractor runs procurement process. Which is limited | F59: =IF(C59="","",IFERROR(INDEX('Sub-principles'!$E$2:$E$11,MATCH(C59,'Sub-principles'!$A$2:$A$11,0)),"")) -> 16 | G59: =IF(OR(D59="",F59=""),"",D59/5*F59) -> 9.6
A60: P001 | B60: S van Schalkwyk | C60: PP4.1 | D60: 5 | E60: PFMA, Governance, all qualified audits are good (aligned to all prescripts) | F60: =IF(C60="","",IFERROR(INDEX('Sub-principles'!$E$2:$E$11,MATCH(C60,'Sub-principles'!$A$2:$A$11,0)),"")) -> 20 | G60: =IF(OR(D60="",F60=""),"",D60/5*F60) -> 20
A61: P001 | B61: S van Schalkwyk | C61: PP4.2 | D61: 3 | E61: Enables sustainable developments on precinct; less job opportunities will be created- takes score down to a 3 | F61: =IF(C61="","",IFERROR(INDEX('Sub-principles'!$E$2:$E$11,MATCH(C61,'Sub-principles'!$A$2:$A$11,0)),"")) -> 8 | G61: =IF(OR(D61="",F61=""),"",D61/5*F61) -> 4.8
F62: =IF(C62="","",IFERROR(INDEX('Sub-principles'!$E$2:$E$11,MATCH(C62,'Sub-principles'!$A$2:$A$11,0)),"")) | G62: =IF(OR(D62="",F62=""),"",D62/5*F62)
F63: =IF(C63="","",IFERROR(INDEX('Sub-principles'!$E$2:$E$11,MATCH(C63,'Sub-principles'!$A$2:$A$11,0)),"")) | G63: =IF(OR(D63="",F63=""),"",D63/5*F63)
F64: =IF(C64="","",IFERROR(INDEX('Sub-principles'!$E$2:$E$11,MATCH(C64,'Sub-principles'!$A$2:$A$11,0)),"")) | G64: =IF(OR(D64="",F64=""),"",D64/5*F64)
F65: =IF(C65="","",IFERROR(INDEX('Sub-principles'!$E$2:$E$11,MATCH(C65,'Sub-principles'!$A$2:$A$11,0)),"")) | G65: =IF(OR(D65="",F65=""),"",D65/5*F65)
F66: =IF(C66="","",IFERROR(INDEX('Sub-principles'!$E$2:$E$11,MATCH(C66,'Sub-principles'!$A$2:$A$11,0)),"")) | G66: =IF(OR(D66="",F66=""),"",D66/5*F66)
F67: =IF(C67="","",IFERROR(INDEX('Sub-principles'!$E$2:$E$11,MATCH(C67,'Sub-principles'!$A$2:$A$11,0)),"")) | G67: =IF(OR(D67="",F67=""),"",D67/5*F67)
F68: =IF(C68="","",IFERROR(INDEX('Sub-principles'!$E$2:$E$11,MATCH(C68,'Sub-principles'!$A$2:$A$11,0)),"")) | G68: =IF(OR(D68="",F68=""),"",D68/5*F68)
F69: =IF(C69="","",IFERROR(INDEX('Sub-principles'!$E$2:$E$11,MATCH(C69,'Sub-principles'!$A$2:$A$11,0)),"")) | G69: =IF(OR(D69="",F69=""),"",D69/5*F69)
F70: =IF(C70="","",IFERROR(INDEX('Sub-principles'!$E$2:$E$11,MATCH(C70,'Sub-principles'!$A$2:$A$11,0)),"")) | G70: =IF(OR(D70="",F70=""),"",D70/5*F70)
F71: =IF(C71="","",IFERROR(INDEX('Sub-principles'!$E$2:$E$11,MATCH(C71,'Sub-principles'!$A$2:$A$11,0)),"")) | G71: =IF(OR(D71="",F71=""),"",D71/5*F71)
F72: =IF(C72="","",IFERROR(INDEX('Sub-principles'!$E$2:$E$11,MATCH(C72,'Sub-principles'!$A$2:$A$11,0)),"")) | G72: =IF(OR(D72="",F72=""),"",D72/5*F72)
F73: =IF(C73="","",IFERROR(INDEX('Sub-principles'!$E$2:$E$11,MATCH(C73,'Sub-principles'!$A$2:$A$11,0)),"")) | G73: =IF(OR(D73="",F73=""),"",D73/5*F73)
... F1000: =IF(C1000="","",IFERROR(INDEX('Sub-principles'!$E$2:$E$11,MATCH(C1000,'Sub-principles'!$A$2:$A$11,0)),"")) | G1000: =IF(OR(D1000="",F1000=""),"",D1000/5*F1000)

Sheet SDG matrix
A1: Department mapping: sub-principles against the 17 SDGs
A2: Sub-principle | B2: Name | C2: 1 | D2: 2 | E2: 3 | F2: 4 | G2: 5 | H2: 6 | I2: 7 | J2: 8 | K2: 9 | L2: 10 | M2: 11 | N2: 12 | O2: 13 | P2: 14 | Q2: 15 | R2: 16 | S2: 17
A3: PP1.1 | B3: Design & material innovation | C3: =IF(COUNTIFS(tl_sub,$A3,tl_sdg,C$2,tl_align,"Primary")>0,"P",IF(COUNTIFS(tl_sub,$A3,tl_sdg,C$2)>0,"S","")) | D3: =IF(COUNTIFS(tl_sub,$A3,tl_sdg,D$2,tl_align,"Primary")>0,"P",IF(COUNTIFS(tl_sub,$A3,tl_sdg,D$2)>0,"S","")) | E3: =IF(COUNTIFS(tl_sub,$A3,tl_sdg,E$2,tl_align,"Primary")>0,"P",IF(COUNTIFS(tl_sub,$A3,tl_sdg,E$2)>0,"S","")) | F3: =IF(COUNTIFS(tl_sub,$A3,tl_sdg,F$2,tl_align,"Primary")>0,"P",IF(COUNTIFS(tl_sub,$A3,tl_sdg,F$2)>0,"S","")) | G3: =IF(COUNTIFS(tl_sub,$A3,tl_sdg,G$2,tl_align,"Primary")>0,"P",IF(COUNTIFS(tl_sub,$A3,tl_sdg,G$2)>0,"S","")) | H3: =IF(COUNTIFS(tl_sub,$A3,tl_sdg,H$2,tl_align,"Primary")>0,"P",IF(COUNTIFS(tl_sub,$A3,tl_sdg,H$2)>0,"S","")) | I3: =IF(COUNTIFS(tl_sub,$A3,tl_sdg,I$2,tl_align,"Primary")>0,"P",IF(COUNTIFS(tl_sub,$A3,tl_sdg,I$2)>0,"S","")) | J3: =IF(COUNTIFS(tl_sub,$A3,tl_sdg,J$2,tl_align,"Primary")>0,"P",IF(COUNTIFS(tl_sub,$A3,tl_sdg,J$2)>0,"S","")) -> S | ... S3: =IF(COUNTIFS(tl_sub,$A3,tl_sdg,S$2,tl_align,"Primary")>0,"P",IF(COUNTIFS(tl_sub,$A3,tl_sdg,S$2)>0,"S",""))
A4: PP1.2 | B4: ICT innovation | C4: =IF(COUNTIFS(tl_sub,$A4,tl_sdg,C$2,tl_align,"Primary")>0,"P",IF(COUNTIFS(tl_sub,$A4,tl_sdg,C$2)>0,"S","")) | D4: =IF(COUNTIFS(tl_sub,$A4,tl_sdg,D$2,tl_align,"Primary")>0,"P",IF(COUNTIFS(tl_sub,$A4,tl_sdg,D$2)>0,"S","")) | E4: =IF(COUNTIFS(tl_sub,$A4,tl_sdg,E$2,tl_align,"Primary")>0,"P",IF(COUNTIFS(tl_sub,$A4,tl_sdg,E$2)>0,"S","")) | F4: =IF(COUNTIFS(tl_sub,$A4,tl_sdg,F$2,tl_align,"Primary")>0,"P",IF(COUNTIFS(tl_sub,$A4,tl_sdg,F$2)>0,"S","")) | G4: =IF(COUNTIFS(tl_sub,$A4,tl_sdg,G$2,tl_align,"Primary")>0,"P",IF(COUNTIFS(tl_sub,$A4,tl_sdg,G$2)>0,"S","")) | H4: =IF(COUNTIFS(tl_sub,$A4,tl_sdg,H$2,tl_align,"Primary")>0,"P",IF(COUNTIFS(tl_sub,$A4,tl_sdg,H$2)>0,"S","")) | I4: =IF(COUNTIFS(tl_sub,$A4,tl_sdg,I$2,tl_align,"Primary")>0,"P",IF(COUNTIFS(tl_sub,$A4,tl_sdg,I$2)>0,"S","")) | J4: =IF(COUNTIFS(tl_sub,$A4,tl_sdg,J$2,tl_align,"Primary")>0,"P",IF(COUNTIFS(tl_sub,$A4,tl_sdg,J$2)>0,"S","")) -> S | ... S4: =IF(COUNTIFS(tl_sub,$A4,tl_sdg,S$2,tl_align,"Primary")>0,"P",IF(COUNTIFS(tl_sub,$A4,tl_sdg,S$2)>0,"S","")) -> S
A5: PP2.1 | B5: Resilient design & risk | C5: =IF(COUNTIFS(tl_sub,$A5,tl_sdg,C$2,tl_align,"Primary")>0,"P",IF(COUNTIFS(tl_sub,$A5,tl_sdg,C$2)>0,"S","")) | D5: =IF(COUNTIFS(tl_sub,$A5,tl_sdg,D$2,tl_align,"Primary")>0,"P",IF(COUNTIFS(tl_sub,$A5,tl_sdg,D$2)>0,"S","")) | E5: =IF(COUNTIFS(tl_sub,$A5,tl_sdg,E$2,tl_align,"Primary")>0,"P",IF(COUNTIFS(tl_sub,$A5,tl_sdg,E$2)>0,"S","")) | F5: =IF(COUNTIFS(tl_sub,$A5,tl_sdg,F$2,tl_align,"Primary")>0,"P",IF(COUNTIFS(tl_sub,$A5,tl_sdg,F$2)>0,"S","")) | G5: =IF(COUNTIFS(tl_sub,$A5,tl_sdg,G$2,tl_align,"Primary")>0,"P",IF(COUNTIFS(tl_sub,$A5,tl_sdg,G$2)>0,"S","")) | H5: =IF(COUNTIFS(tl_sub,$A5,tl_sdg,H$2,tl_align,"Primary")>0,"P",IF(COUNTIFS(tl_sub,$A5,tl_sdg,H$2)>0,"S","")) -> S | I5: =IF(COUNTIFS(tl_sub,$A5,tl_sdg,I$2,tl_align,"Primary")>0,"P",IF(COUNTIFS(tl_sub,$A5,tl_sdg,I$2)>0,"S","")) -> S | J5: =IF(COUNTIFS(tl_sub,$A5,tl_sdg,J$2,tl_align,"Primary")>0,"P",IF(COUNTIFS(tl_sub,$A5,tl_sdg,J$2)>0,"S","")) | ... S5: =IF(COUNTIFS(tl_sub,$A5,tl_sdg,S$2,tl_align,"Primary")>0,"P",IF(COUNTIFS(tl_sub,$A5,tl_sdg,S$2)>0,"S",""))
A6: PP2.2 | B6: Systemic planning alignment | C6: =IF(COUNTIFS(tl_sub,$A6,tl_sdg,C$2,tl_align,"Primary")>0,"P",IF(COUNTIFS(tl_sub,$A6,tl_sdg,C$2)>0,"S","")) | D6: =IF(COUNTIFS(tl_sub,$A6,tl_sdg,D$2,tl_align,"Primary")>0,"P",IF(COUNTIFS(tl_sub,$A6,tl_sdg,D$2)>0,"S","")) | E6: =IF(COUNTIFS(tl_sub,$A6,tl_sdg,E$2,tl_align,"Primary")>0,"P",IF(COUNTIFS(tl_sub,$A6,tl_sdg,E$2)>0,"S","")) | F6: =IF(COUNTIFS(tl_sub,$A6,tl_sdg,F$2,tl_align,"Primary")>0,"P",IF(COUNTIFS(tl_sub,$A6,tl_sdg,F$2)>0,"S","")) | G6: =IF(COUNTIFS(tl_sub,$A6,tl_sdg,G$2,tl_align,"Primary")>0,"P",IF(COUNTIFS(tl_sub,$A6,tl_sdg,G$2)>0,"S","")) | H6: =IF(COUNTIFS(tl_sub,$A6,tl_sdg,H$2,tl_align,"Primary")>0,"P",IF(COUNTIFS(tl_sub,$A6,tl_sdg,H$2)>0,"S","")) | I6: =IF(COUNTIFS(tl_sub,$A6,tl_sdg,I$2,tl_align,"Primary")>0,"P",IF(COUNTIFS(tl_sub,$A6,tl_sdg,I$2)>0,"S","")) | J6: =IF(COUNTIFS(tl_sub,$A6,tl_sdg,J$2,tl_align,"Primary")>0,"P",IF(COUNTIFS(tl_sub,$A6,tl_sdg,J$2)>0,"S","")) | ... S6: =IF(COUNTIFS(tl_sub,$A6,tl_sdg,S$2,tl_align,"Primary")>0,"P",IF(COUNTIFS(tl_sub,$A6,tl_sdg,S$2)>0,"S","")) -> S
A7: PP2.3 | B7: Localised resources | C7: =IF(COUNTIFS(tl_sub,$A7,tl_sdg,C$2,tl_align,"Primary")>0,"P",IF(COUNTIFS(tl_sub,$A7,tl_sdg,C$2)>0,"S","")) | D7: =IF(COUNTIFS(tl_sub,$A7,tl_sdg,D$2,tl_align,"Primary")>0,"P",IF(COUNTIFS(tl_sub,$A7,tl_sdg,D$2)>0,"S","")) | E7: =IF(COUNTIFS(tl_sub,$A7,tl_sdg,E$2,tl_align,"Primary")>0,"P",IF(COUNTIFS(tl_sub,$A7,tl_sdg,E$2)>0,"S","")) | F7: =IF(COUNTIFS(tl_sub,$A7,tl_sdg,F$2,tl_align,"Primary")>0,"P",IF(COUNTIFS(tl_sub,$A7,tl_sdg,F$2)>0,"S","")) | G7: =IF(COUNTIFS(tl_sub,$A7,tl_sdg,G$2,tl_align,"Primary")>0,"P",IF(COUNTIFS(tl_sub,$A7,tl_sdg,G$2)>0,"S","")) | H7: =IF(COUNTIFS(tl_sub,$A7,tl_sdg,H$2,tl_align,"Primary")>0,"P",IF(COUNTIFS(tl_sub,$A7,tl_sdg,H$2)>0,"S","")) | I7: =IF(COUNTIFS(tl_sub,$A7,tl_sdg,I$2,tl_align,"Primary")>0,"P",IF(COUNTIFS(tl_sub,$A7,tl_sdg,I$2)>0,"S","")) | J7: =IF(COUNTIFS(tl_sub,$A7,tl_sdg,J$2,tl_align,"Primary")>0,"P",IF(COUNTIFS(tl_sub,$A7,tl_sdg,J$2)>0,"S","")) -> S | ... S7: =IF(COUNTIFS(tl_sub,$A7,tl_sdg,S$2,tl_align,"Primary")>0,"P",IF(COUNTIFS(tl_sub,$A7,tl_sdg,S$2)>0,"S",""))
A8: PP3.1 | B8: Spatial-zone geolocation | C8: =IF(COUNTIFS(tl_sub,$A8,tl_sdg,C$2,tl_align,"Primary")>0,"P",IF(COUNTIFS(tl_sub,$A8,tl_sdg,C$2)>0,"S","")) | D8: =IF(COUNTIFS(tl_sub,$A8,tl_sdg,D$2,tl_align,"Primary")>0,"P",IF(COUNTIFS(tl_sub,$A8,tl_sdg,D$2)>0,"S","")) | E8: =IF(COUNTIFS(tl_sub,$A8,tl_sdg,E$2,tl_align,"Primary")>0,"P",IF(COUNTIFS(tl_sub,$A8,tl_sdg,E$2)>0,"S","")) | F8: =IF(COUNTIFS(tl_sub,$A8,tl_sdg,F$2,tl_align,"Primary")>0,"P",IF(COUNTIFS(tl_sub,$A8,tl_sdg,F$2)>0,"S","")) -> S | G8: =IF(COUNTIFS(tl_sub,$A8,tl_sdg,G$2,tl_align,"Primary")>0,"P",IF(COUNTIFS(tl_sub,$A8,tl_sdg,G$2)>0,"S","")) | H8: =IF(COUNTIFS(tl_sub,$A8,tl_sdg,H$2,tl_align,"Primary")>0,"P",IF(COUNTIFS(tl_sub,$A8,tl_sdg,H$2)>0,"S","")) | I8: =IF(COUNTIFS(tl_sub,$A8,tl_sdg,I$2,tl_align,"Primary")>0,"P",IF(COUNTIFS(tl_sub,$A8,tl_sdg,I$2)>0,"S","")) | J8: =IF(COUNTIFS(tl_sub,$A8,tl_sdg,J$2,tl_align,"Primary")>0,"P",IF(COUNTIFS(tl_sub,$A8,tl_sdg,J$2)>0,"S","")) | ... S8: =IF(COUNTIFS(tl_sub,$A8,tl_sdg,S$2,tl_align,"Primary")>0,"P",IF(COUNTIFS(tl_sub,$A8,tl_sdg,S$2)>0,"S",""))
A9: PP3.2 | B9: Public value & spatial justice | C9: =IF(COUNTIFS(tl_sub,$A9,tl_sdg,C$2,tl_align,"Primary")>0,"P",IF(COUNTIFS(tl_sub,$A9,tl_sdg,C$2)>0,"S","")) -> S | D9: =IF(COUNTIFS(tl_sub,$A9,tl_sdg,D$2,tl_align,"Primary")>0,"P",IF(COUNTIFS(tl_sub,$A9,tl_sdg,D$2)>0,"S","")) | E9: =IF(COUNTIFS(tl_sub,$A9,tl_sdg,E$2,tl_align,"Primary")>0,"P",IF(COUNTIFS(tl_sub,$A9,tl_sdg,E$2)>0,"S","")) | F9: =IF(COUNTIFS(tl_sub,$A9,tl_sdg,F$2,tl_align,"Primary")>0,"P",IF(COUNTIFS(tl_sub,$A9,tl_sdg,F$2)>0,"S","")) | G9: =IF(COUNTIFS(tl_sub,$A9,tl_sdg,G$2,tl_align,"Primary")>0,"P",IF(COUNTIFS(tl_sub,$A9,tl_sdg,G$2)>0,"S","")) | H9: =IF(COUNTIFS(tl_sub,$A9,tl_sdg,H$2,tl_align,"Primary")>0,"P",IF(COUNTIFS(tl_sub,$A9,tl_sdg,H$2)>0,"S","")) | I9: =IF(COUNTIFS(tl_sub,$A9,tl_sdg,I$2,tl_align,"Primary")>0,"P",IF(COUNTIFS(tl_sub,$A9,tl_sdg,I$2)>0,"S","")) | J9: =IF(COUNTIFS(tl_sub,$A9,tl_sdg,J$2,tl_align,"Primary")>0,"P",IF(COUNTIFS(tl_sub,$A9,tl_sdg,J$2)>0,"S","")) | ... S9: =IF(COUNTIFS(tl_sub,$A9,tl_sdg,S$2,tl_align,"Primary")>0,"P",IF(COUNTIFS(tl_sub,$A9,tl_sdg,S$2)>0,"S",""))
A10: PP3.3 | B10: Partnerships & localisation | C10: =IF(COUNTIFS(tl_sub,$A10,tl_sdg,C$2,tl_align,"Primary")>0,"P",IF(COUNTIFS(tl_sub,$A10,tl_sdg,C$2)>0,"S","")) | D10: =IF(COUNTIFS(tl_sub,$A10,tl_sdg,D$2,tl_align,"Primary")>0,"P",IF(COUNTIFS(tl_sub,$A10,tl_sdg,D$2)>0,"S","")) | E10: =IF(COUNTIFS(tl_sub,$A10,tl_sdg,E$2,tl_align,"Primary")>0,"P",IF(COUNTIFS(tl_sub,$A10,tl_sdg,E$2)>0,"S","")) | F10: =IF(COUNTIFS(tl_sub,$A10,tl_sdg,F$2,tl_align,"Primary")>0,"P",IF(COUNTIFS(tl_sub,$A10,tl_sdg,F$2)>0,"S","")) | G10: =IF(COUNTIFS(tl_sub,$A10,tl_sdg,G$2,tl_align,"Primary")>0,"P",IF(COUNTIFS(tl_sub,$A10,tl_sdg,G$2)>0,"S","")) | H10: =IF(COUNTIFS(tl_sub,$A10,tl_sdg,H$2,tl_align,"Primary")>0,"P",IF(COUNTIFS(tl_sub,$A10,tl_sdg,H$2)>0,"S","")) | I10: =IF(COUNTIFS(tl_sub,$A10,tl_sdg,I$2,tl_align,"Primary")>0,"P",IF(COUNTIFS(tl_sub,$A10,tl_sdg,I$2)>0,"S","")) | J10: =IF(COUNTIFS(tl_sub,$A10,tl_sdg,J$2,tl_align,"Primary")>0,"P",IF(COUNTIFS(tl_sub,$A10,tl_sdg,J$2)>0,"S","")) -> S | ... S10: =IF(COUNTIFS(tl_sub,$A10,tl_sdg,S$2,tl_align,"Primary")>0,"P",IF(COUNTIFS(tl_sub,$A10,tl_sdg,S$2)>0,"S","")) -> P
A11: PP4.1 | B11: Funding & budget compliance | C11: =IF(COUNTIFS(tl_sub,$A11,tl_sdg,C$2,tl_align,"Primary")>0,"P",IF(COUNTIFS(tl_sub,$A11,tl_sdg,C$2)>0,"S","")) | D11: =IF(COUNTIFS(tl_sub,$A11,tl_sdg,D$2,tl_align,"Primary")>0,"P",IF(COUNTIFS(tl_sub,$A11,tl_sdg,D$2)>0,"S","")) | E11: =IF(COUNTIFS(tl_sub,$A11,tl_sdg,E$2,tl_align,"Primary")>0,"P",IF(COUNTIFS(tl_sub,$A11,tl_sdg,E$2)>0,"S","")) | F11: =IF(COUNTIFS(tl_sub,$A11,tl_sdg,F$2,tl_align,"Primary")>0,"P",IF(COUNTIFS(tl_sub,$A11,tl_sdg,F$2)>0,"S","")) | G11: =IF(COUNTIFS(tl_sub,$A11,tl_sdg,G$2,tl_align,"Primary")>0,"P",IF(COUNTIFS(tl_sub,$A11,tl_sdg,G$2)>0,"S","")) | H11: =IF(COUNTIFS(tl_sub,$A11,tl_sdg,H$2,tl_align,"Primary")>0,"P",IF(COUNTIFS(tl_sub,$A11,tl_sdg,H$2)>0,"S","")) | I11: =IF(COUNTIFS(tl_sub,$A11,tl_sdg,I$2,tl_align,"Primary")>0,"P",IF(COUNTIFS(tl_sub,$A11,tl_sdg,I$2)>0,"S","")) | J11: =IF(COUNTIFS(tl_sub,$A11,tl_sdg,J$2,tl_align,"Primary")>0,"P",IF(COUNTIFS(tl_sub,$A11,tl_sdg,J$2)>0,"S","")) | ... S11: =IF(COUNTIFS(tl_sub,$A11,tl_sdg,S$2,tl_align,"Primary")>0,"P",IF(COUNTIFS(tl_sub,$A11,tl_sdg,S$2)>0,"S","")) -> S
A12: PP4.2 | B12: Socio-economic compliance | C12: =IF(COUNTIFS(tl_sub,$A12,tl_sdg,C$2,tl_align,"Primary")>0,"P",IF(COUNTIFS(tl_sub,$A12,tl_sdg,C$2)>0,"S","")) | D12: =IF(COUNTIFS(tl_sub,$A12,tl_sdg,D$2,tl_align,"Primary")>0,"P",IF(COUNTIFS(tl_sub,$A12,tl_sdg,D$2)>0,"S","")) | E12: =IF(COUNTIFS(tl_sub,$A12,tl_sdg,E$2,tl_align,"Primary")>0,"P",IF(COUNTIFS(tl_sub,$A12,tl_sdg,E$2)>0,"S","")) | F12: =IF(COUNTIFS(tl_sub,$A12,tl_sdg,F$2,tl_align,"Primary")>0,"P",IF(COUNTIFS(tl_sub,$A12,tl_sdg,F$2)>0,"S","")) | G12: =IF(COUNTIFS(tl_sub,$A12,tl_sdg,G$2,tl_align,"Primary")>0,"P",IF(COUNTIFS(tl_sub,$A12,tl_sdg,G$2)>0,"S","")) | H12: =IF(COUNTIFS(tl_sub,$A12,tl_sdg,H$2,tl_align,"Primary")>0,"P",IF(COUNTIFS(tl_sub,$A12,tl_sdg,H$2)>0,"S","")) | I12: =IF(COUNTIFS(tl_sub,$A12,tl_sdg,I$2,tl_align,"Primary")>0,"P",IF(COUNTIFS(tl_sub,$A12,tl_sdg,I$2)>0,"S","")) | J12: =IF(COUNTIFS(tl_sub,$A12,tl_sdg,J$2,tl_align,"Primary")>0,"P",IF(COUNTIFS(tl_sub,$A12,tl_sdg,J$2)>0,"S","")) -> S | ... S12: =IF(COUNTIFS(tl_sub,$A12,tl_sdg,S$2,tl_align,"Primary")>0,"P",IF(COUNTIFS(tl_sub,$A12,tl_sdg,S$2)>0,"S","")) -> S
B13: Sub-principles linked | C13: =COUNTIF(C3:C12,"?*") -> 1 | D13: =COUNTIF(D3:D12,"?*") -> 0 | E13: =COUNTIF(E3:E12,"?*") -> 0 | F13: =COUNTIF(F3:F12,"?*") -> 1 | G13: =COUNTIF(G3:G12,"?*") -> 0 | H13: =COUNTIF(H3:H12,"?*") -> 1 | I13: =COUNTIF(I3:I12,"?*") -> 1 | J13: =COUNTIF(J3:J12,"?*") -> 5 | ... S13: =COUNTIF(S3:S12,"?*") -> 5
A15: P = at least one primary target in that SDG · S = secondary targets only

Sheet SDG goals
A1: SDG | B1: Short name | C1: Goal title | D1: Colour | E1: Target links | F1: Primary links | G1: Sub-principles
A2: 1 | B2: No Poverty | C2: End poverty in all its forms everywhere | D2: #E5243B | E2: =COUNTIF(tl_sdg,A2) -> 1 | F2: =COUNTIFS(tl_sdg,A2,tl_align,"Primary") -> 0 | G2: =COUNTIF('SDG matrix'!C3:C12,"?*") -> 1
A3: 2 | B3: Zero Hunger | C3: End hunger, achieve food security and improved nutrition and promote sustainable agriculture | D3: #DDA63A | E3: =COUNTIF(tl_sdg,A3) -> 0 | F3: =COUNTIFS(tl_sdg,A3,tl_align,"Primary") -> 0 | G3: =COUNTIF('SDG matrix'!D3:D12,"?*") -> 0
A4: 3 | B4: Good Health and Well-being | C4: Ensure healthy lives and promote well-being for all at all ages | D4: #4C9F38 | E4: =COUNTIF(tl_sdg,A4) -> 0 | F4: =COUNTIFS(tl_sdg,A4,tl_align,"Primary") -> 0 | G4: =COUNTIF('SDG matrix'!E3:E12,"?*") -> 0
A5: 4 | B5: Quality Education | C5: Ensure inclusive and equitable quality education and promote lifelong learning opportunities for all | D5: #C5192D | E5: =COUNTIF(tl_sdg,A5) -> 1 | F5: =COUNTIFS(tl_sdg,A5,tl_align,"Primary") -> 0 | G5: =COUNTIF('SDG matrix'!F3:F12,"?*") -> 1
A6: 5 | B6: Gender Equality | C6: Achieve gender equality and empower all women and girls | D6: #FF3A21 | E6: =COUNTIF(tl_sdg,A6) -> 0 | F6: =COUNTIFS(tl_sdg,A6,tl_align,"Primary") -> 0 | G6: =COUNTIF('SDG matrix'!G3:G12,"?*") -> 0
A7: 6 | B7: Clean Water and Sanitation | C7: Ensure availability and sustainable management of water and sanitation for all | D7: #26BDE2 | E7: =COUNTIF(tl_sdg,A7) -> 2 | F7: =COUNTIFS(tl_sdg,A7,tl_align,"Primary") -> 0 | G7: =COUNTIF('SDG matrix'!H3:H12,"?*") -> 1
A8: 7 | B8: Affordable and Clean Energy | C8: Ensure access to affordable, reliable, sustainable and modern energy for all | D8: #FCC30B | E8: =COUNTIF(tl_sdg,A8) -> 2 | F8: =COUNTIFS(tl_sdg,A8,tl_align,"Primary") -> 0 | G8: =COUNTIF('SDG matrix'!I3:I12,"?*") -> 1
A9: 8 | B9: Decent Work and Economic Growth | C9: Promote sustained, inclusive and sustainable economic growth, full and productive employment and decent work for all | D9: #A21942 | E9: =COUNTIF(tl_sdg,A9) -> 6 | F9: =COUNTIFS(tl_sdg,A9,tl_align,"Primary") -> 0 | G9: =COUNTIF('SDG matrix'!J3:J12,"?*") -> 5
A10: 9 | B10: Industry, Innovation and Infrastructure | C10: Build resilient infrastructure, promote inclusive and sustainable industrialization and foster innovation | D10: #FD6925 | E10: =COUNTIF(tl_sdg,A10) -> 10 | F10: =COUNTIFS(tl_sdg,A10,tl_align,"Primary") -> 6 | G10: =COUNTIF('SDG matrix'!K3:K12,"?*") -> 7
A11: 10 | B11: Reduced Inequalities | C11: Reduce inequality within and among countries | D11: #DD1367 | E11: =COUNTIF(tl_sdg,A11) -> 4 | F11: =COUNTIFS(tl_sdg,A11,tl_align,"Primary") -> 1 | G11: =COUNTIF('SDG matrix'!L3:L12,"?*") -> 4
A12: 11 | B12: Sustainable Cities and Communities | C12: Make cities and human settlements inclusive, safe, resilient and sustainable | D12: #FD9D24 | E12: =COUNTIF(tl_sdg,A12) -> 12 | F12: =COUNTIFS(tl_sdg,A12,tl_align,"Primary") -> 7 | G12: =COUNTIF('SDG matrix'!M3:M12,"?*") -> 7
A13: 12 | B13: Responsible Consumption and Production | C13: Ensure sustainable consumption and production patterns | D13: #BF8B2E | E13: =COUNTIF(tl_sdg,A13) -> 5 | F13: =COUNTIFS(tl_sdg,A13,tl_align,"Primary") -> 2 | G13: =COUNTIF('SDG matrix'!N3:N12,"?*") -> 4
A14: 13 | B14: Climate Action | C14: Take urgent action to combat climate change and its impacts | D14: #3F7E44 | E14: =COUNTIF(tl_sdg,A14) -> 4 | F14: =COUNTIFS(tl_sdg,A14,tl_align,"Primary") -> 2 | G14: =COUNTIF('SDG matrix'!O3:O12,"?*") -> 3
A15: 14 | B15: Life Below Water | C15: Conserve and sustainably use the oceans, seas and marine resources for sustainable development | D15: #0A97D9 | E15: =COUNTIF(tl_sdg,A15) -> 0 | F15: =COUNTIFS(tl_sdg,A15,tl_align,"Primary") -> 0 | G15: =COUNTIF('SDG matrix'!P3:P12,"?*") -> 0
A16: 15 | B16: Life on Land | C16: Protect, restore and promote sustainable use of terrestrial ecosystems, sustainably manage forests, combat desertification, and halt and reverse land degradation and halt biodiversity loss | D16: #56C02B | E16: =COUNTIF(tl_sdg,A16) -> 0 | F16: =COUNTIFS(tl_sdg,A16,tl_align,"Primary") -> 0 | G16: =COUNTIF('SDG matrix'!Q3:Q12,"?*") -> 0
A17: 16 | B17: Peace, Justice and Strong Institutions | C17: Promote peaceful and inclusive societies for sustainable development, provide access to justice for all and build effective, accountable and inclusive institutions at all levels | D17: #00689D | E17: =COUNTIF(tl_sdg,A17) -> 8 | F17: =COUNTIFS(tl_sdg,A17,tl_align,"Primary") -> 3 | G17: =COUNTIF('SDG matrix'!R3:R12,"?*") -> 5
A18: 17 | B18: Partnerships for the Goals | C18: Strengthen the means of implementation and revitalize the Global Partnership for Sustainable Development | D18: #19486A | E18: =COUNTIF(tl_sdg,A18) -> 11 | F18: =COUNTIFS(tl_sdg,A18,tl_align,"Primary") -> 2 | G18: =COUNTIF('SDG matrix'!S3:S12,"?*") -> 5
B19: Total | E19: =SUM(E2:E18) -> 66 | F19: =SUM(F2:F18) -> 23

Sheet Coverage summary
A1: SDG coverage summary
A2: Per goal: how many of its targets the Panoptic sub-principles reach. Counts come from 'SDG target coverage'; the amber columns are for the team.
A4: SDG | B4: Goal | C4: Targets | D4: Linked targets | E4: With a primary link | F4: Secondary only | G4: Gaps | H4: Coverage | I4: Outcome-target gaps | J4: Target links | K4: Sub-principles linking | L4: Principles linking | M4: Team priority | N4: Discussion notes
A5: 1 | B5: No Poverty | C5: =COUNTIF(cov_sdg,A5) -> 7 | D5: =COUNTIFS(cov_sdg,A5,cov_status,"<>Gap") -> 1 | E5: =COUNTIFS(cov_sdg,A5,cov_status,"Primary link") -> 0 | F5: =COUNTIFS(cov_sdg,A5,cov_status,"Secondary only") -> 1 | G5: =COUNTIFS(cov_sdg,A5,cov_status,"Gap") -> 6 | H5: =IF(C5=0,0,D5/C5) -> 0.14285714 | I5: =COUNTIFS(cov_sdg,A5,cov_status,"Gap",cov_type,"Outcome") -> 4 | J5: =COUNTIF(tl_sdg,A5) -> 1 | K5: =COUNTIF('SDG matrix'!C3:C12,"?*") -> 1 | L5: =_xlfn.TEXTJOIN(", ",TRUE(),IF(SUMPRODUCT((tl_sdg=$A5)*(tl_principle="PP1"))>0,"PP1",""),IF(SUMPRODUCT((tl_sdg=$A5)*(tl_principle="PP2"))>0,"PP2",""),IF(SUMPRODUCT((tl_sdg=$A5)*(tl_principle="PP3"))>0,"PP3",""),IF(SUMPRODUCT((tl_sdg=$A5)*(tl_principle="PP4"))>0,"PP4","")) -> PP3
A6: 2 | B6: Zero Hunger | C6: =COUNTIF(cov_sdg,A6) -> 8 | D6: =COUNTIFS(cov_sdg,A6,cov_status,"<>Gap") -> 0 | E6: =COUNTIFS(cov_sdg,A6,cov_status,"Primary link") -> 0 | F6: =COUNTIFS(cov_sdg,A6,cov_status,"Secondary only") -> 0 | G6: =COUNTIFS(cov_sdg,A6,cov_status,"Gap") -> 8 | H6: =IF(C6=0,0,D6/C6) -> 0 | I6: =COUNTIFS(cov_sdg,A6,cov_status,"Gap",cov_type,"Outcome") -> 5 | J6: =COUNTIF(tl_sdg,A6) -> 0 | K6: =COUNTIF('SDG matrix'!D3:D12,"?*") -> 0 | L6: =_xlfn.TEXTJOIN(", ",TRUE(),IF(SUMPRODUCT((tl_sdg=$A6)*(tl_principle="PP1"))>0,"PP1",""),IF(SUMPRODUCT((tl_sdg=$A6)*(tl_principle="PP2"))>0,"PP2",""),IF(SUMPRODUCT((tl_sdg=$A6)*(tl_principle="PP3"))>0,"PP3",""),IF(SUMPRODUCT((tl_sdg=$A6)*(tl_principle="PP4"))>0,"PP4",""))
A7: 3 | B7: Good Health and Well-being | C7: =COUNTIF(cov_sdg,A7) -> 13 | D7: =COUNTIFS(cov_sdg,A7,cov_status,"<>Gap") -> 0 | E7: =COUNTIFS(cov_sdg,A7,cov_status,"Primary link") -> 0 | F7: =COUNTIFS(cov_sdg,A7,cov_status,"Secondary only") -> 0 | G7: =COUNTIFS(cov_sdg,A7,cov_status,"Gap") -> 13 | H7: =IF(C7=0,0,D7/C7) -> 0 | I7: =COUNTIFS(cov_sdg,A7,cov_status,"Gap",cov_type,"Outcome") -> 9 | J7: =COUNTIF(tl_sdg,A7) -> 0 | K7: =COUNTIF('SDG matrix'!E3:E12,"?*") -> 0 | L7: =_xlfn.TEXTJOIN(", ",TRUE(),IF(SUMPRODUCT((tl_sdg=$A7)*(tl_principle="PP1"))>0,"PP1",""),IF(SUMPRODUCT((tl_sdg=$A7)*(tl_principle="PP2"))>0,"PP2",""),IF(SUMPRODUCT((tl_sdg=$A7)*(tl_principle="PP3"))>0,"PP3",""),IF(SUMPRODUCT((tl_sdg=$A7)*(tl_principle="PP4"))>0,"PP4",""))
A8: 4 | B8: Quality Education | C8: =COUNTIF(cov_sdg,A8) -> 10 | D8: =COUNTIFS(cov_sdg,A8,cov_status,"<>Gap") -> 1 | E8: =COUNTIFS(cov_sdg,A8,cov_status,"Primary link") -> 0 | F8: =COUNTIFS(cov_sdg,A8,cov_status,"Secondary only") -> 1 | G8: =COUNTIFS(cov_sdg,A8,cov_status,"Gap") -> 9 | H8: =IF(C8=0,0,D8/C8) -> 0.1 | I8: =COUNTIFS(cov_sdg,A8,cov_status,"Gap",cov_type,"Outcome") -> 6 | J8: =COUNTIF(tl_sdg,A8) -> 1 | K8: =COUNTIF('SDG matrix'!F3:F12,"?*") -> 1 | L8: =_xlfn.TEXTJOIN(", ",TRUE(),IF(SUMPRODUCT((tl_sdg=$A8)*(tl_principle="PP1"))>0,"PP1",""),IF(SUMPRODUCT((tl_sdg=$A8)*(tl_principle="PP2"))>0,"PP2",""),IF(SUMPRODUCT((tl_sdg=$A8)*(tl_principle="PP3"))>0,"PP3",""),IF(SUMPRODUCT((tl_sdg=$A8)*(tl_principle="PP4"))>0,"PP4","")) -> PP3
A9: 5 | B9: Gender Equality | C9: =COUNTIF(cov_sdg,A9) -> 9 | D9: =COUNTIFS(cov_sdg,A9,cov_status,"<>Gap") -> 0 | E9: =COUNTIFS(cov_sdg,A9,cov_status,"Primary link") -> 0 | F9: =COUNTIFS(cov_sdg,A9,cov_status,"Secondary only") -> 0 | G9: =COUNTIFS(cov_sdg,A9,cov_status,"Gap") -> 9 | H9: =IF(C9=0,0,D9/C9) -> 0 | I9: =COUNTIFS(cov_sdg,A9,cov_status,"Gap",cov_type,"Outcome") -> 6 | J9: =COUNTIF(tl_sdg,A9) -> 0 | K9: =COUNTIF('SDG matrix'!G3:G12,"?*") -> 0 | L9: =_xlfn.TEXTJOIN(", ",TRUE(),IF(SUMPRODUCT((tl_sdg=$A9)*(tl_principle="PP1"))>0,"PP1",""),IF(SUMPRODUCT((tl_sdg=$A9)*(tl_principle="PP2"))>0,"PP2",""),IF(SUMPRODUCT((tl_sdg=$A9)*(tl_principle="PP3"))>0,"PP3",""),IF(SUMPRODUCT((tl_sdg=$A9)*(tl_principle="PP4"))>0,"PP4",""))
A10: 6 | B10: Clean Water and Sanitation | C10: =COUNTIF(cov_sdg,A10) -> 8 | D10: =COUNTIFS(cov_sdg,A10,cov_status,"<>Gap") -> 2 | E10: =COUNTIFS(cov_sdg,A10,cov_status,"Primary link") -> 0 | F10: =COUNTIFS(cov_sdg,A10,cov_status,"Secondary only") -> 2 | G10: =COUNTIFS(cov_sdg,A10,cov_status,"Gap") -> 6 | H10: =IF(C10=0,0,D10/C10) -> 0.25 | I10: =COUNTIFS(cov_sdg,A10,cov_status,"Gap",cov_type,"Outcome") -> 4 | J10: =COUNTIF(tl_sdg,A10) -> 2 | K10: =COUNTIF('SDG matrix'!H3:H12,"?*") -> 1 | L10: =_xlfn.TEXTJOIN(", ",TRUE(),IF(SUMPRODUCT((tl_sdg=$A10)*(tl_principle="PP1"))>0,"PP1",""),IF(SUMPRODUCT((tl_sdg=$A10)*(tl_principle="PP2"))>0,"PP2",""),IF(SUMPRODUCT((tl_sdg=$A10)*(tl_principle="PP3"))>0,"PP3",""),IF(SUMPRODUCT((tl_sdg=$A10)*(tl_principle="PP4"))>0,"PP4","")) -> PP2
A11: 7 | B11: Affordable and Clean Energy | C11: =COUNTIF(cov_sdg,A11) -> 5 | D11: =COUNTIFS(cov_sdg,A11,cov_status,"<>Gap") -> 2 | E11: =COUNTIFS(cov_sdg,A11,cov_status,"Primary link") -> 0 | F11: =COUNTIFS(cov_sdg,A11,cov_status,"Secondary only") -> 2 | G11: =COUNTIFS(cov_sdg,A11,cov_status,"Gap") -> 3 | H11: =IF(C11=0,0,D11/C11) -> 0.4 | I11: =COUNTIFS(cov_sdg,A11,cov_status,"Gap",cov_type,"Outcome") -> 1 | J11: =COUNTIF(tl_sdg,A11) -> 2 | K11: =COUNTIF('SDG matrix'!I3:I12,"?*") -> 1 | L11: =_xlfn.TEXTJOIN(", ",TRUE(),IF(SUMPRODUCT((tl_sdg=$A11)*(tl_principle="PP1"))>0,"PP1",""),IF(SUMPRODUCT((tl_sdg=$A11)*(tl_principle="PP2"))>0,"PP2",""),IF(SUMPRODUCT((tl_sdg=$A11)*(tl_principle="PP3"))>0,"PP3",""),IF(SUMPRODUCT((tl_sdg=$A11)*(tl_principle="PP4"))>0,"PP4","")) -> PP2
A12: 8 | B12: Decent Work and Economic Growth | C12: =COUNTIF(cov_sdg,A12) -> 12 | D12: =COUNTIFS(cov_sdg,A12,cov_status,"<>Gap") -> 3 | E12: =COUNTIFS(cov_sdg,A12,cov_status,"Primary link") -> 0 | F12: =COUNTIFS(cov_sdg,A12,cov_status,"Secondary only") -> 3 | G12: =COUNTIFS(cov_sdg,A12,cov_status,"Gap") -> 9 | H12: =IF(C12=0,0,D12/C12) -> 0.25 | I12: =COUNTIFS(cov_sdg,A12,cov_status,"Gap",cov_type,"Outcome") -> 7 | J12: =COUNTIF(tl_sdg,A12) -> 6 | K12: =COUNTIF('SDG matrix'!J3:J12,"?*") -> 5 | L12: =_xlfn.TEXTJOIN(", ",TRUE(),IF(SUMPRODUCT((tl_sdg=$A12)*(tl_principle="PP1"))>0,"PP1",""),IF(SUMPRODUCT((tl_sdg=$A12)*(tl_principle="PP2"))>0,"PP2",""),IF(SUMPRODUCT((tl_sdg=$A12)*(tl_principle="PP3"))>0,"PP3",""),IF(SUMPRODUCT((tl_sdg=$A12)*(tl_principle="PP4"))>0,"PP4","")) -> PP1, PP2, PP3, PP4
A13: 9 | B13: Industry, Innovation and Infrastructure | C13: =COUNTIF(cov_sdg,A13) -> 8 | D13: =COUNTIFS(cov_sdg,A13,cov_status,"<>Gap") -> 4 | E13: =COUNTIFS(cov_sdg,A13,cov_status,"Primary link") -> 4 | F13: =COUNTIFS(cov_sdg,A13,cov_status,"Secondary only") -> 0 | G13: =COUNTIFS(cov_sdg,A13,cov_status,"Gap") -> 4 | H13: =IF(C13=0,0,D13/C13) -> 0.5 | I13: =COUNTIFS(cov_sdg,A13,cov_status,"Gap",cov_type,"Outcome") -> 2 | J13: =COUNTIF(tl_sdg,A13) -> 10 | K13: =COUNTIF('SDG matrix'!K3:K12,"?*") -> 7 | L13: =_xlfn.TEXTJOIN(", ",TRUE(),IF(SUMPRODUCT((tl_sdg=$A13)*(tl_principle="PP1"))>0,"PP1",""),IF(SUMPRODUCT((tl_sdg=$A13)*(tl_principle="PP2"))>0,"PP2",""),IF(SUMPRODUCT((tl_sdg=$A13)*(tl_principle="PP3"))>0,"PP3",""),IF(SUMPRODUCT((tl_sdg=$A13)*(tl_principle="PP4"))>0,"PP4","")) -> PP1, PP2, PP3
A14: 10 | B14: Reduced Inequalities | C14: =COUNTIF(cov_sdg,A14) -> 10 | D14: =COUNTIFS(cov_sdg,A14,cov_status,"<>Gap") -> 1 | E14: =COUNTIFS(cov_sdg,A14,cov_status,"Primary link") -> 1 | F14: =COUNTIFS(cov_sdg,A14,cov_status,"Secondary only") -> 0 | G14: =COUNTIFS(cov_sdg,A14,cov_status,"Gap") -> 9 | H14: =IF(C14=0,0,D14/C14) -> 0.1 | I14: =COUNTIFS(cov_sdg,A14,cov_status,"Gap",cov_type,"Outcome") -> 6 | J14: =COUNTIF(tl_sdg,A14) -> 4 | K14: =COUNTIF('SDG matrix'!L3:L12,"?*") -> 4 | L14: =_xlfn.TEXTJOIN(", ",TRUE(),IF(SUMPRODUCT((tl_sdg=$A14)*(tl_principle="PP1"))>0,"PP1",""),IF(SUMPRODUCT((tl_sdg=$A14)*(tl_principle="PP2"))>0,"PP2",""),IF(SUMPRODUCT((tl_sdg=$A14)*(tl_principle="PP3"))>0,"PP3",""),IF(SUMPRODUCT((tl_sdg=$A14)*(tl_principle="PP4"))>0,"PP4","")) -> PP3, PP4
A15: 11 | B15: Sustainable Cities and Communities | C15: =COUNTIF(cov_sdg,A15) -> 10 | D15: =COUNTIFS(cov_sdg,A15,cov_status,"<>Gap") -> 7 | E15: =COUNTIFS(cov_sdg,A15,cov_status,"Primary link") -> 4 | F15: =COUNTIFS(cov_sdg,A15,cov_status,"Secondary only") -> 3 | G15: =COUNTIFS(cov_sdg,A15,cov_status,"Gap") -> 3 | H15: =IF(C15=0,0,D15/C15) -> 0.7 | I15: =COUNTIFS(cov_sdg,A15,cov_status,"Gap",cov_type,"Outcome") -> 2 | J15: =COUNTIF(tl_sdg,A15) -> 12 | K15: =COUNTIF('SDG matrix'!M3:M12,"?*") -> 7 | L15: =_xlfn.TEXTJOIN(", ",TRUE(),IF(SUMPRODUCT((tl_sdg=$A15)*(tl_principle="PP1"))>0,"PP1",""),IF(SUMPRODUCT((tl_sdg=$A15)*(tl_principle="PP2"))>0,"PP2",""),IF(SUMPRODUCT((tl_sdg=$A15)*(tl_principle="PP3"))>0,"PP3",""),IF(SUMPRODUCT((tl_sdg=$A15)*(tl_principle="PP4"))>0,"PP4","")) -> PP1, PP2, PP3, PP4
A16: 12 | B16: Responsible Consumption and Production | C16: =COUNTIF(cov_sdg,A16) -> 11 | D16: =COUNTIFS(cov_sdg,A16,cov_status,"<>Gap") -> 2 | E16: =COUNTIFS(cov_sdg,A16,cov_status,"Primary link") -> 2 | F16: =COUNTIFS(cov_sdg,A16,cov_status,"Secondary only") -> 0 | G16: =COUNTIFS(cov_sdg,A16,cov_status,"Gap") -> 9 | H16: =IF(C16=0,0,D16/C16) -> 0.18181818 | I16: =COUNTIFS(cov_sdg,A16,cov_status,"Gap",cov_type,"Outcome") -> 6 | J16: =COUNTIF(tl_sdg,A16) -> 5 | K16: =COUNTIF('SDG matrix'!N3:N12,"?*") -> 4 | L16: =_xlfn.TEXTJOIN(", ",TRUE(),IF(SUMPRODUCT((tl_sdg=$A16)*(tl_principle="PP1"))>0,"PP1",""),IF(SUMPRODUCT((tl_sdg=$A16)*(tl_principle="PP2"))>0,"PP2",""),IF(SUMPRODUCT((tl_sdg=$A16)*(tl_principle="PP3"))>0,"PP3",""),IF(SUMPRODUCT((tl_sdg=$A16)*(tl_principle="PP4"))>0,"PP4","")) -> PP1, PP2, PP3
A17: 13 | B17: Climate Action | C17: =COUNTIF(cov_sdg,A17) -> 5 | D17: =COUNTIFS(cov_sdg,A17,cov_status,"<>Gap") -> 2 | E17: =COUNTIFS(cov_sdg,A17,cov_status,"Primary link") -> 2 | F17: =COUNTIFS(cov_sdg,A17,cov_status,"Secondary only") -> 0 | G17: =COUNTIFS(cov_sdg,A17,cov_status,"Gap") -> 3 | H17: =IF(C17=0,0,D17/C17) -> 0.4 | I17: =COUNTIFS(cov_sdg,A17,cov_status,"Gap",cov_type,"Outcome") -> 1 | J17: =COUNTIF(tl_sdg,A17) -> 4 | K17: =COUNTIF('SDG matrix'!O3:O12,"?*") -> 3 | L17: =_xlfn.TEXTJOIN(", ",TRUE(),IF(SUMPRODUCT((tl_sdg=$A17)*(tl_principle="PP1"))>0,"PP1",""),IF(SUMPRODUCT((tl_sdg=$A17)*(tl_principle="PP2"))>0,"PP2",""),IF(SUMPRODUCT((tl_sdg=$A17)*(tl_principle="PP3"))>0,"PP3",""),IF(SUMPRODUCT((tl_sdg=$A17)*(tl_principle="PP4"))>0,"PP4","")) -> PP2
A18: 14 | B18: Life Below Water | C18: =COUNTIF(cov_sdg,A18) -> 10 | D18: =COUNTIFS(cov_sdg,A18,cov_status,"<>Gap") -> 0 | E18: =COUNTIFS(cov_sdg,A18,cov_status,"Primary link") -> 0 | F18: =COUNTIFS(cov_sdg,A18,cov_status,"Secondary only") -> 0 | G18: =COUNTIFS(cov_sdg,A18,cov_status,"Gap") -> 10 | H18: =IF(C18=0,0,D18/C18) -> 0 | I18: =COUNTIFS(cov_sdg,A18,cov_status,"Gap",cov_type,"Outcome") -> 7 | J18: =COUNTIF(tl_sdg,A18) -> 0 | K18: =COUNTIF('SDG matrix'!P3:P12,"?*") -> 0 | L18: =_xlfn.TEXTJOIN(", ",TRUE(),IF(SUMPRODUCT((tl_sdg=$A18)*(tl_principle="PP1"))>0,"PP1",""),IF(SUMPRODUCT((tl_sdg=$A18)*(tl_principle="PP2"))>0,"PP2",""),IF(SUMPRODUCT((tl_sdg=$A18)*(tl_principle="PP3"))>0,"PP3",""),IF(SUMPRODUCT((tl_sdg=$A18)*(tl_principle="PP4"))>0,"PP4",""))
A19: 15 | B19: Life on Land | C19: =COUNTIF(cov_sdg,A19) -> 12 | D19: =COUNTIFS(cov_sdg,A19,cov_status,"<>Gap") -> 0 | E19: =COUNTIFS(cov_sdg,A19,cov_status,"Primary link") -> 0 | F19: =COUNTIFS(cov_sdg,A19,cov_status,"Secondary only") -> 0 | G19: =COUNTIFS(cov_sdg,A19,cov_status,"Gap") -> 12 | H19: =IF(C19=0,0,D19/C19) -> 0 | I19: =COUNTIFS(cov_sdg,A19,cov_status,"Gap",cov_type,"Outcome") -> 9 | J19: =COUNTIF(tl_sdg,A19) -> 0 | K19: =COUNTIF('SDG matrix'!Q3:Q12,"?*") -> 0 | L19: =_xlfn.TEXTJOIN(", ",TRUE(),IF(SUMPRODUCT((tl_sdg=$A19)*(tl_principle="PP1"))>0,"PP1",""),IF(SUMPRODUCT((tl_sdg=$A19)*(tl_principle="PP2"))>0,"PP2",""),IF(SUMPRODUCT((tl_sdg=$A19)*(tl_principle="PP3"))>0,"PP3",""),IF(SUMPRODUCT((tl_sdg=$A19)*(tl_principle="PP4"))>0,"PP4",""))
A20: 16 | B20: Peace, Justice and Strong Institutions | C20: =COUNTIF(cov_sdg,A20) -> 12 | D20: =COUNTIFS(cov_sdg,A20,cov_status,"<>Gap") -> 3 | E20: =COUNTIFS(cov_sdg,A20,cov_status,"Primary link") -> 2 | F20: =COUNTIFS(cov_sdg,A20,cov_status,"Secondary only") -> 1 | G20: =COUNTIFS(cov_sdg,A20,cov_status,"Gap") -> 9 | H20: =IF(C20=0,0,D20/C20) -> 0.25 | I20: =COUNTIFS(cov_sdg,A20,cov_status,"Gap",cov_type,"Outcome") -> 7 | J20: =COUNTIF(tl_sdg,A20) -> 8 | K20: =COUNTIF('SDG matrix'!R3:R12,"?*") -> 5 | L20: =_xlfn.TEXTJOIN(", ",TRUE(),IF(SUMPRODUCT((tl_sdg=$A20)*(tl_principle="PP1"))>0,"PP1",""),IF(SUMPRODUCT((tl_sdg=$A20)*(tl_principle="PP2"))>0,"PP2",""),IF(SUMPRODUCT((tl_sdg=$A20)*(tl_principle="PP3"))>0,"PP3",""),IF(SUMPRODUCT((tl_sdg=$A20)*(tl_principle="PP4"))>0,"PP4","")) -> PP1, PP3, PP4
A21: 17 | B21: Partnerships for the Goals | C21: =COUNTIF(cov_sdg,A21) -> 19 | D21: =COUNTIFS(cov_sdg,A21,cov_status,"<>Gap") -> 7 | E21: =COUNTIFS(cov_sdg,A21,cov_status,"Primary link") -> 2 | F21: =COUNTIFS(cov_sdg,A21,cov_status,"Secondary only") -> 5 | G21: =COUNTIFS(cov_sdg,A21,cov_status,"Gap") -> 12 | H21: =IF(C21=0,0,D21/C21) -> 0.36842105 | I21: =COUNTIFS(cov_sdg,A21,cov_status,"Gap",cov_type,"Outcome") -> 12 | J21: =COUNTIF(tl_sdg,A21) -> 11 | K21: =COUNTIF('SDG matrix'!S3:S12,"?*") -> 5 | L21: =_xlfn.TEXTJOIN(", ",TRUE(),IF(SUMPRODUCT((tl_sdg=$A21)*(tl_principle="PP1"))>0,"PP1",""),IF(SUMPRODUCT((tl_sdg=$A21)*(tl_principle="PP2"))>0,"PP2",""),IF(SUMPRODUCT((tl_sdg=$A21)*(tl_principle="PP3"))>0,"PP3",""),IF(SUMPRODUCT((tl_sdg=$A21)*(tl_principle="PP4"))>0,"PP4","")) -> PP1, PP2, PP3, PP4
B22: All SDGs | C22: =SUM(C5:C21) -> 169 | D22: =SUM(D5:D21) -> 35 | E22: =SUM(E5:E21) -> 17 | F22: =SUM(F5:F21) -> 18 | G22: =SUM(G5:G21) -> 134 | H22: =IF(C22=0,0,D22/C22) -> 0.20710059 | I22: =SUM(I5:I21) -> 94 | J22: =SUM(J5:J21) -> 66
B23: Goals with no link at all | D23: =COUNTIF(D5:D21,0) -> 5

Sheet SDG target coverage
A1: SDG target coverage: which Panoptic principles reach each SDG target
A2: All 169 targets. P = primary link, S = secondary link, from 'Target links' (formulas, so edits there flow through). Coverage: Primary link / Secondary only / Gap. The amber columns are for the team's gap discussion.
H3: PP1 Innovation | J3: PP2 Resilience | M3: PP3 Stakeholder value | P3: PP4 Governance | U3: For the team discussion
A4: SDG | B4: Goal | C4: Target | D4: Type | E4: Target short name | F4: Target text (UNSD) | G4: Indicators | H4: PP1.1 | I4: PP1.2 | J4: PP2.1 | K4: PP2.2 | L4: PP2.3 | M4: PP3.1 | N4: PP3.2 | O4: PP3.3 | P4: PP4.1 | Q4: PP4.2 | R4: Principles linked | S4: Target links | T4: Coverage | U4: Relevance to the department | V4: Proposed sub-principle | W4: Proposed alignment | X4: Decision | Y4: Notes and owner
A5: 1 | B5: No Poverty | C5: 1.1 | D5: Outcome | F5: By 2030, eradicate extreme poverty for all people everywhere, currently measured as people living on less than $1.25 a day | G5: 1 | H5: =IF(SUMPRODUCT((tl_target=$C5)*(tl_sub=H$4)*(tl_align="Primary"))>0,"P",IF(SUMPRODUCT((tl_target=$C5)*(tl_sub=H$4))>0,"S","")) | I5: =IF(SUMPRODUCT((tl_target=$C5)*(tl_sub=I$4)*(tl_align="Primary"))>0,"P",IF(SUMPRODUCT((tl_target=$C5)*(tl_sub=I$4))>0,"S","")) | J5: =IF(SUMPRODUCT((tl_target=$C5)*(tl_sub=J$4)*(tl_align="Primary"))>0,"P",IF(SUMPRODUCT((tl_target=$C5)*(tl_sub=J$4))>0,"S","")) | K5: =IF(SUMPRODUCT((tl_target=$C5)*(tl_sub=K$4)*(tl_align="Primary"))>0,"P",IF(SUMPRODUCT((tl_target=$C5)*(tl_sub=K$4))>0,"S","")) | L5: =IF(SUMPRODUCT((tl_target=$C5)*(tl_sub=L$4)*(tl_align="Primary"))>0,"P",IF(SUMPRODUCT((tl_target=$C5)*(tl_sub=L$4))>0,"S","")) | M5: =IF(SUMPRODUCT((tl_target=$C5)*(tl_sub=M$4)*(tl_align="Primary"))>0,"P",IF(SUMPRODUCT((tl_target=$C5)*(tl_sub=M$4))>0,"S","")) | N5: =IF(SUMPRODUCT((tl_target=$C5)*(tl_sub=N$4)*(tl_align="Primary"))>0,"P",IF(SUMPRODUCT((tl_target=$C5)*(tl_sub=N$4))>0,"S","")) | O5: =IF(SUMPRODUCT((tl_target=$C5)*(tl_sub=O$4)*(tl_align="Primary"))>0,"P",IF(SUMPRODUCT((tl_target=$C5)*(tl_sub=O$4))>0,"S","")) | ... Q5: =IF(SUMPRODUCT((tl_target=$C5)*(tl_sub=Q$4)*(tl_align="Primary"))>0,"P",IF(SUMPRODUCT((tl_target=$C5)*(tl_sub=Q$4))>0,"S","")) | R5: =_xlfn.TEXTJOIN(", ",TRUE(),IF(SUMPRODUCT((tl_target=$C5)*(tl_principle="PP1"))>0,"PP1",""),IF(SUMPRODUCT((tl_target=$C5)*(tl_principle="PP2"))>0,"PP2",""),IF(SUMPRODUCT((tl_target=$C5)*(tl_principle="PP3"))>0,"PP3",""),IF(SUMPRODUCT((tl_target=$C5)*(tl_principle="PP4"))>0,"PP4","")) | S5: =SUMPRODUCT(--(tl_target=$C5)) -> 0 | T5: =IF(SUMPRODUCT((tl_target=$C5)*(tl_align="Primary"))>0,"Primary link",IF(S5>0,"Secondary only","Gap")) -> Gap
A6: 1 | B6: No Poverty | C6: 1.2 | D6: Outcome | F6: By 2030, reduce at least by half the proportion of men, women and children of all ages living in poverty in all its dimensions according to national definitions | G6: 2 | H6: =IF(SUMPRODUCT((tl_target=$C6)*(tl_sub=H$4)*(tl_align="Primary"))>0,"P",IF(SUMPRODUCT((tl_target=$C6)*(tl_sub=H$4))>0,"S","")) | I6: =IF(SUMPRODUCT((tl_target=$C6)*(tl_sub=I$4)*(tl_align="Primary"))>0,"P",IF(SUMPRODUCT((tl_target=$C6)*(tl_sub=I$4))>0,"S","")) | J6: =IF(SUMPRODUCT((tl_target=$C6)*(tl_sub=J$4)*(tl_align="Primary"))>0,"P",IF(SUMPRODUCT((tl_target=$C6)*(tl_sub=J$4))>0,"S","")) | K6: =IF(SUMPRODUCT((tl_target=$C6)*(tl_sub=K$4)*(tl_align="Primary"))>0,"P",IF(SUMPRODUCT((tl_target=$C6)*(tl_sub=K$4))>0,"S","")) | L6: =IF(SUMPRODUCT((tl_target=$C6)*(tl_sub=L$4)*(tl_align="Primary"))>0,"P",IF(SUMPRODUCT((tl_target=$C6)*(tl_sub=L$4))>0,"S","")) | M6: =IF(SUMPRODUCT((tl_target=$C6)*(tl_sub=M$4)*(tl_align="Primary"))>0,"P",IF(SUMPRODUCT((tl_target=$C6)*(tl_sub=M$4))>0,"S","")) | N6: =IF(SUMPRODUCT((tl_target=$C6)*(tl_sub=N$4)*(tl_align="Primary"))>0,"P",IF(SUMPRODUCT((tl_target=$C6)*(tl_sub=N$4))>0,"S","")) | O6: =IF(SUMPRODUCT((tl_target=$C6)*(tl_sub=O$4)*(tl_align="Primary"))>0,"P",IF(SUMPRODUCT((tl_target=$C6)*(tl_sub=O$4))>0,"S","")) | ... Q6: =IF(SUMPRODUCT((tl_target=$C6)*(tl_sub=Q$4)*(tl_align="Primary"))>0,"P",IF(SUMPRODUCT((tl_target=$C6)*(tl_sub=Q$4))>0,"S","")) | R6: =_xlfn.TEXTJOIN(", ",TRUE(),IF(SUMPRODUCT((tl_target=$C6)*(tl_principle="PP1"))>0,"PP1",""),IF(SUMPRODUCT((tl_target=$C6)*(tl_principle="PP2"))>0,"PP2",""),IF(SUMPRODUCT((tl_target=$C6)*(tl_principle="PP3"))>0,"PP3",""),IF(SUMPRODUCT((tl_target=$C6)*(tl_principle="PP4"))>0,"PP4","")) | S6: =SUMPRODUCT(--(tl_target=$C6)) -> 0 | T6: =IF(SUMPRODUCT((tl_target=$C6)*(tl_align="Primary"))>0,"Primary link",IF(S6>0,"Secondary only","Gap")) -> Gap
A7: 1 | B7: No Poverty | C7: 1.3 | D7: Outcome | F7: Implement nationally appropriate social protection systems and measures for all, including floors, and by 2030 achieve substantial coverage of the poor and the vulnerable | G7: 1 | H7: =IF(SUMPRODUCT((tl_target=$C7)*(tl_sub=H$4)*(tl_align="Primary"))>0,"P",IF(SUMPRODUCT((tl_target=$C7)*(tl_sub=H$4))>0,"S","")) | I7: =IF(SUMPRODUCT((tl_target=$C7)*(tl_sub=I$4)*(tl_align="Primary"))>0,"P",IF(SUMPRODUCT((tl_target=$C7)*(tl_sub=I$4))>0,"S","")) | J7: =IF(SUMPRODUCT((tl_target=$C7)*(tl_sub=J$4)*(tl_align="Primary"))>0,"P",IF(SUMPRODUCT((tl_target=$C7)*(tl_sub=J$4))>0,"S","")) | K7: =IF(SUMPRODUCT((tl_target=$C7)*(tl_sub=K$4)*(tl_align="Primary"))>0,"P",IF(SUMPRODUCT((tl_target=$C7)*(tl_sub=K$4))>0,"S","")) | L7: =IF(SUMPRODUCT((tl_target=$C7)*(tl_sub=L$4)*(tl_align="Primary"))>0,"P",IF(SUMPRODUCT((tl_target=$C7)*(tl_sub=L$4))>0,"S","")) | M7: =IF(SUMPRODUCT((tl_target=$C7)*(tl_sub=M$4)*(tl_align="Primary"))>0,"P",IF(SUMPRODUCT((tl_target=$C7)*(tl_sub=M$4))>0,"S","")) | N7: =IF(SUMPRODUCT((tl_target=$C7)*(tl_sub=N$4)*(tl_align="Primary"))>0,"P",IF(SUMPRODUCT((tl_target=$C7)*(tl_sub=N$4))>0,"S","")) | O7: =IF(SUMPRODUCT((tl_target=$C7)*(tl_sub=O$4)*(tl_align="Primary"))>0,"P",IF(SUMPRODUCT((tl_target=$C7)*(tl_sub=O$4))>0,"S","")) | ... Q7: =IF(SUMPRODUCT((tl_target=$C7)*(tl_sub=Q$4)*(tl_align="Primary"))>0,"P",IF(SUMPRODUCT((tl_target=$C7)*(tl_sub=Q$4))>0,"S","")) | R7: =_xlfn.TEXTJOIN(", ",TRUE(),IF(SUMPRODUCT((tl_target=$C7)*(tl_principle="PP1"))>0,"PP1",""),IF(SUMPRODUCT((tl_target=$C7)*(tl_principle="PP2"))>0,"PP2",""),IF(SUMPRODUCT((tl_target=$C7)*(tl_principle="PP3"))>0,"PP3",""),IF(SUMPRODUCT((tl_target=$C7)*(tl_principle="PP4"))>0,"PP4","")) | S7: =SUMPRODUCT(--(tl_target=$C7)) -> 0 | T7: =IF(SUMPRODUCT((tl_target=$C7)*(tl_align="Primary"))>0,"Primary link",IF(S7>0,"Secondary only","Gap")) -> Gap
A8: 1 | B8: No Poverty | C8: 1.4 | D8: Outcome | E8: Equal access to basic services and resources | F8: By 2030, ensure that all men and women, in particular the poor and the vulnerable, have equal rights to economic resources, as well as access to basic services, ownership and control over land and other forms of property, inheritance, natural resources, appropriate new technology and financial services, including microfinance | G8: 2 | H8: =IF(SUMPRODUCT((tl_target=$C8)*(tl_sub=H$4)*(tl_align="Primary"))>0,"P",IF(SUMPRODUCT((tl_target=$C8)*(tl_sub=H$4))>0,"S","")) | I8: =IF(SUMPRODUCT((tl_target=$C8)*(tl_sub=I$4)*(tl_align="Primary"))>0,"P",IF(SUMPRODUCT((tl_target=$C8)*(tl_sub=I$4))>0,"S","")) | J8: =IF(SUMPRODUCT((tl_target=$C8)*(tl_sub=J$4)*(tl_align="Primary"))>0,"P",IF(SUMPRODUCT((tl_target=$C8)*(tl_sub=J$4))>0,"S","")) | K8: =IF(SUMPRODUCT((tl_target=$C8)*(tl_sub=K$4)*(tl_align="Primary"))>0,"P",IF(SUMPRODUCT((tl_target=$C8)*(tl_sub=K$4))>0,"S","")) | L8: =IF(SUMPRODUCT((tl_target=$C8)*(tl_sub=L$4)*(tl_align="Primary"))>0,"P",IF(SUMPRODUCT((tl_target=$C8)*(tl_sub=L$4))>0,"S","")) | M8: =IF(SUMPRODUCT((tl_target=$C8)*(tl_sub=M$4)*(tl_align="Primary"))>0,"P",IF(SUMPRODUCT((tl_target=$C8)*(tl_sub=M$4))>0,"S","")) | N8: =IF(SUMPRODUCT((tl_target=$C8)*(tl_sub=N$4)*(tl_align="Primary"))>0,"P",IF(SUMPRODUCT((tl_target=$C8)*(tl_sub=N$4))>0,"S","")) -> S | O8: =IF(SUMPRODUCT((tl_target=$C8)*(tl_sub=O$4)*(tl_align="Primary"))>0,"P",IF(SUMPRODUCT((tl_target=$C8)*(tl_sub=O$4))>0,"S","")) | ... Q8: =IF(SUMPRODUCT((tl_target=$C8)*(tl_sub=Q$4)*(tl_align="Primary"))>0,"P",IF(SUMPRODUCT((tl_target=$C8)*(tl_sub=Q$4))>0,"S","")) | R8: =_xlfn.TEXTJOIN(", ",TRUE(),IF(SUMPRODUCT((tl_target=$C8)*(tl_principle="PP1"))>0,"PP1",""),IF(SUMPRODUCT((tl_target=$C8)*(tl_principle="PP2"))>0,"PP2",""),IF(SUMPRODUCT((tl_target=$C8)*(tl_principle="PP3"))>0,"PP3",""),IF(SUMPRODUCT((tl_target=$C8)*(tl_principle="PP4"))>0,"PP4","")) -> PP3 | S8: =SUMPRODUCT(--(tl_target=$C8)) -> 1 | T8: =IF(SUMPRODUCT((tl_target=$C8)*(tl_align="Primary"))>0,"Primary link",IF(S8>0,"Secondary only","Gap")) -> Secondary only
A9: 1 | B9: No Poverty | C9: 1.5 | D9: Outcome | F9: By 2030, build the resilience of the poor and those in vulnerable situations and reduce their exposure and vulnerability to climate-related extreme events and other economic, social and environmental shocks and disasters | G9: 4 | H9: =IF(SUMPRODUCT((tl_target=$C9)*(tl_sub=H$4)*(tl_align="Primary"))>0,"P",IF(SUMPRODUCT((tl_target=$C9)*(tl_sub=H$4))>0,"S","")) | I9: =IF(SUMPRODUCT((tl_target=$C9)*(tl_sub=I$4)*(tl_align="Primary"))>0,"P",IF(SUMPRODUCT((tl_target=$C9)*(tl_sub=I$4))>0,"S","")) | J9: =IF(SUMPRODUCT((tl_target=$C9)*(tl_sub=J$4)*(tl_align="Primary"))>0,"P",IF(SUMPRODUCT((tl_target=$C9)*(tl_sub=J$4))>0,"S","")) | K9: =IF(SUMPRODUCT((tl_target=$C9)*(tl_sub=K$4)*(tl_align="Primary"))>0,"P",IF(SUMPRODUCT((tl_target=$C9)*(tl_sub=K$4))>0,"S","")) | L9: =IF(SUMPRODUCT((tl_target=$C9)*(tl_sub=L$4)*(tl_align="Primary"))>0,"P",IF(SUMPRODUCT((tl_target=$C9)*(tl_sub=L$4))>0,"S","")) | M9: =IF(SUMPRODUCT((tl_target=$C9)*(tl_sub=M$4)*(tl_align="Primary"))>0,"P",IF(SUMPRODUCT((tl_target=$C9)*(tl_sub=M$4))>0,"S","")) | N9: =IF(SUMPRODUCT((tl_target=$C9)*(tl_sub=N$4)*(tl_align="Primary"))>0,"P",IF(SUMPRODUCT((tl_target=$C9)*(tl_sub=N$4))>0,"S","")) | O9: =IF(SUMPRODUCT((tl_target=$C9)*(tl_sub=O$4)*(tl_align="Primary"))>0,"P",IF(SUMPRODUCT((tl_target=$C9)*(tl_sub=O$4))>0,"S","")) | ... Q9: =IF(SUMPRODUCT((tl_target=$C9)*(tl_sub=Q$4)*(tl_align="Primary"))>0,"P",IF(SUMPRODUCT((tl_target=$C9)*(tl_sub=Q$4))>0,"S","")) | R9: =_xlfn.TEXTJOIN(", ",TRUE(),IF(SUMPRODUCT((tl_target=$C9)*(tl_principle="PP1"))>0,"PP1",""),IF(SUMPRODUCT((tl_target=$C9)*(tl_principle="PP2"))>0,"PP2",""),IF(SUMPRODUCT((tl_target=$C9)*(tl_principle="PP3"))>0,"PP3",""),IF(SUMPRODUCT((tl_target=$C9)*(tl_principle="PP4"))>0,"PP4","")) | S9: =SUMPRODUCT(--(tl_target=$C9)) -> 0 | T9: =IF(SUMPRODUCT((tl_target=$C9)*(tl_align="Primary"))>0,"Primary link",IF(S9>0,"Secondary only","Gap")) -> Gap
A10: 1 | B10: No Poverty | C10: 1.a | D10: Means of implementation | F10: Ensure significant mobilization of resources from a variety of sources, including through enhanced development cooperation, in order to provide adequate and predictable means for developing countries, in particular least developed countries, to implement programmes and policies to end poverty in all its dimensions | G10: 2 | H10: =IF(SUMPRODUCT((tl_target=$C10)*(tl_sub=H$4)*(tl_align="Primary"))>0,"P",IF(SUMPRODUCT((tl_target=$C10)*(tl_sub=H$4))>0,"S","")) | I10: =IF(SUMPRODUCT((tl_target=$C10)*(tl_sub=I$4)*(tl_align="Primary"))>0,"P",IF(SUMPRODUCT((tl_target=$C10)*(tl_sub=I$4))>0,"S","")) | J10: =IF(SUMPRODUCT((tl_target=$C10)*(tl_sub=J$4)*(tl_align="Primary"))>0,"P",IF(SUMPRODUCT((tl_target=$C10)*(tl_sub=J$4))>0,"S","")) | K10: =IF(SUMPRODUCT((tl_target=$C10)*(tl_sub=K$4)*(tl_align="Primary"))>0,"P",IF(SUMPRODUCT((tl_target=$C10)*(tl_sub=K$4))>0,"S","")) | L10: =IF(SUMPRODUCT((tl_target=$C10)*(tl_sub=L$4)*(tl_align="Primary"))>0,"P",IF(SUMPRODUCT((tl_target=$C10)*(tl_sub=L$4))>0,"S","")) | M10: =IF(SUMPRODUCT((tl_target=$C10)*(tl_sub=M$4)*(tl_align="Primary"))>0,"P",IF(SUMPRODUCT((tl_target=$C10)*(tl_sub=M$4))>0,"S","")) | N10: =IF(SUMPRODUCT((tl_target=$C10)*(tl_sub=N$4)*(tl_align="Primary"))>0,"P",IF(SUMPRODUCT((tl_target=$C10)*(tl_sub=N$4))>0,"S","")) | O10: =IF(SUMPRODUCT((tl_target=$C10)*(tl_sub=O$4)*(tl_align="Primary"))>0,"P",IF(SUMPRODUCT((tl_target=$C10)*(tl_sub=O$4))>0,"S","")) | ... Q10: =IF(SUMPRODUCT((tl_target=$C10)*(tl_sub=Q$4)*(tl_align="Primary"))>0,"P",IF(SUMPRODUCT((tl_target=$C10)*(tl_sub=Q$4))>0,"S","")) | R10: =_xlfn.TEXTJOIN(", ",TRUE(),IF(SUMPRODUCT((tl_target=$C10)*(tl_principle="PP1"))>0,"PP1",""),IF(SUMPRODUCT((tl_target=$C10)*(tl_principle="PP2"))>0,"PP2",""),IF(SUMPRODUCT((tl_target=$C10)*(tl_principle="PP3"))>0,"PP3",""),IF(SUMPRODUCT((tl_target=$C10)*(tl_principle="PP4"))>0,"PP4","")) | S10: =SUMPRODUCT(--(tl_target=$C10)) -> 0 | T10: =IF(SUMPRODUCT((tl_target=$C10)*(tl_align="Primary"))>0,"Primary link",IF(S10>0,"Secondary only","Gap")) -> Gap
A11: 1 | B11: No Poverty | C11: 1.b | D11: Means of implementation | F11: Create sound policy frameworks at the national, regional and international levels, based on pro-poor and gender-sensitive development strategies, to support accelerated investment in poverty eradication actions | G11: 1 | H11: =IF(SUMPRODUCT((tl_target=$C11)*(tl_sub=H$4)*(tl_align="Primary"))>0,"P",IF(SUMPRODUCT((tl_target=$C11)*(tl_sub=H$4))>0,"S","")) | I11: =IF(SUMPRODUCT((tl_target=$C11)*(tl_sub=I$4)*(tl_align="Primary"))>0,"P",IF(SUMPRODUCT((tl_target=$C11)*(tl_sub=I$4))>0,"S","")) | J11: =IF(SUMPRODUCT((tl_target=$C11)*(tl_sub=J$4)*(tl_align="Primary"))>0,"P",IF(SUMPRODUCT((tl_target=$C11)*(tl_sub=J$4))>0,"S","")) | K11: =IF(SUMPRODUCT((tl_target=$C11)*(tl_sub=K$4)*(tl_align="Primary"))>0,"P",IF(SUMPRODUCT((tl_target=$C11)*(tl_sub=K$4))>0,"S","")) | L11: =IF(SUMPRODUCT((tl_target=$C11)*(tl_sub=L$4)*(tl_align="Primary"))>0,"P",IF(SUMPRODUCT((tl_target=$C11)*(tl_sub=L$4))>0,"S","")) | M11: =IF(SUMPRODUCT((tl_target=$C11)*(tl_sub=M$4)*(tl_align="Primary"))>0,"P",IF(SUMPRODUCT((tl_target=$C11)*(tl_sub=M$4))>0,"S","")) | N11: =IF(SUMPRODUCT((tl_target=$C11)*(tl_sub=N$4)*(tl_align="Primary"))>0,"P",IF(SUMPRODUCT((tl_target=$C11)*(tl_sub=N$4))>0,"S","")) | O11: =IF(SUMPRODUCT((tl_target=$C11)*(tl_sub=O$4)*(tl_align="Primary"))>0,"P",IF(SUMPRODUCT((tl_target=$C11)*(tl_sub=O$4))>0,"S","")) | ... Q11: =IF(SUMPRODUCT((tl_target=$C11)*(tl_sub=Q$4)*(tl_align="Primary"))>0,"P",IF(SUMPRODUCT((tl_target=$C11)*(tl_sub=Q$4))>0,"S","")) | R11: =_xlfn.TEXTJOIN(", ",TRUE(),IF(SUMPRODUCT((tl_target=$C11)*(tl_principle="PP1"))>0,"PP1",""),IF(SUMPRODUCT((tl_target=$C11)*(tl_principle="PP2"))>0,"PP2",""),IF(SUMPRODUCT((tl_target=$C11)*(tl_principle="PP3"))>0,"PP3",""),IF(SUMPRODUCT((tl_target=$C11)*(tl_principle="PP4"))>0,"PP4","")) | S11: =SUMPRODUCT(--(tl_target=$C11)) -> 0 | T11: =IF(SUMPRODUCT((tl_target=$C11)*(tl_align="Primary"))>0,"Primary link",IF(S11>0,"Secondary only","Gap")) -> Gap
A12: 2 | B12: Zero Hunger | C12: 2.1 | D12: Outcome | F12: By 2030, end hunger and ensure access by all people, in particular the poor and people in vulnerable situations, including infants, to safe, nutritious and sufficient food all year round | G12: 2 | H12: =IF(SUMPRODUCT((tl_target=$C12)*(tl_sub=H$4)*(tl_align="Primary"))>0,"P",IF(SUMPRODUCT((tl_target=$C12)*(tl_sub=H$4))>0,"S","")) | I12: =IF(SUMPRODUCT((tl_target=$C12)*(tl_sub=I$4)*(tl_align="Primary"))>0,"P",IF(SUMPRODUCT((tl_target=$C12)*(tl_sub=I$4))>0,"S","")) | J12: =IF(SUMPRODUCT((tl_target=$C12)*(tl_sub=J$4)*(tl_align="Primary"))>0,"P",IF(SUMPRODUCT((tl_target=$C12)*(tl_sub=J$4))>0,"S","")) | K12: =IF(SUMPRODUCT((tl_target=$C12)*(tl_sub=K$4)*(tl_align="Primary"))>0,"P",IF(SUMPRODUCT((tl_target=$C12)*(tl_sub=K$4))>0,"S","")) | L12: =IF(SUMPRODUCT((tl_target=$C12)*(tl_sub=L$4)*(tl_align="Primary"))>0,"P",IF(SUMPRODUCT((tl_target=$C12)*(tl_sub=L$4))>0,"S","")) | M12: =IF(SUMPRODUCT((tl_target=$C12)*(tl_sub=M$4)*(tl_align="Primary"))>0,"P",IF(SUMPRODUCT((tl_target=$C12)*(tl_sub=M$4))>0,"S","")) | N12: =IF(SUMPRODUCT((tl_target=$C12)*(tl_sub=N$4)*(tl_align="Primary"))>0,"P",IF(SUMPRODUCT((tl_target=$C12)*(tl_sub=N$4))>0,"S","")) | O12: =IF(SUMPRODUCT((tl_target=$C12)*(tl_sub=O$4)*(tl_align="Primary"))>0,"P",IF(SUMPRODUCT((tl_target=$C12)*(tl_sub=O$4))>0,"S","")) | ... Q12: =IF(SUMPRODUCT((tl_target=$C12)*(tl_sub=Q$4)*(tl_align="Primary"))>0,"P",IF(SUMPRODUCT((tl_target=$C12)*(tl_sub=Q$4))>0,"S","")) | R12: =_xlfn.TEXTJOIN(", ",TRUE(),IF(SUMPRODUCT((tl_target=$C12)*(tl_principle="PP1"))>0,"PP1",""),IF(SUMPRODUCT((tl_target=$C12)*(tl_principle="PP2"))>0,"PP2",""),IF(SUMPRODUCT((tl_target=$C12)*(tl_principle="PP3"))>0,"PP3",""),IF(SUMPRODUCT((tl_target=$C12)*(tl_principle="PP4"))>0,"PP4","")) | S12: =SUMPRODUCT(--(tl_target=$C12)) -> 0 | T12: =IF(SUMPRODUCT((tl_target=$C12)*(tl_align="Primary"))>0,"Primary link",IF(S12>0,"Secondary only","Gap")) -> Gap
A13: 2 | B13: Zero Hunger | C13: 2.2 | D13: Outcome | F13: By 2030, end all forms of malnutrition, including achieving, by 2025, the internationally agreed targets on stunting and wasting in children under 5 years of age, and address the nutritional needs of adolescent girls, pregnant and lactating women and older persons | G13: 4 | H13: =IF(SUMPRODUCT((tl_target=$C13)*(tl_sub=H$4)*(tl_align="Primary"))>0,"P",IF(SUMPRODUCT((tl_target=$C13)*(tl_sub=H$4))>0,"S","")) | I13: =IF(SUMPRODUCT((tl_target=$C13)*(tl_sub=I$4)*(tl_align="Primary"))>0,"P",IF(SUMPRODUCT((tl_target=$C13)*(tl_sub=I$4))>0,"S","")) | J13: =IF(SUMPRODUCT((tl_target=$C13)*(tl_sub=J$4)*(tl_align="Primary"))>0,"P",IF(SUMPRODUCT((tl_target=$C13)*(tl_sub=J$4))>0,"S","")) | K13: =IF(SUMPRODUCT((tl_target=$C13)*(tl_sub=K$4)*(tl_align="Primary"))>0,"P",IF(SUMPRODUCT((tl_target=$C13)*(tl_sub=K$4))>0,"S","")) | L13: =IF(SUMPRODUCT((tl_target=$C13)*(tl_sub=L$4)*(tl_align="Primary"))>0,"P",IF(SUMPRODUCT((tl_target=$C13)*(tl_sub=L$4))>0,"S","")) | M13: =IF(SUMPRODUCT((tl_target=$C13)*(tl_sub=M$4)*(tl_align="Primary"))>0,"P",IF(SUMPRODUCT((tl_target=$C13)*(tl_sub=M$4))>0,"S","")) | N13: =IF(SUMPRODUCT((tl_target=$C13)*(tl_sub=N$4)*(tl_align="Primary"))>0,"P",IF(SUMPRODUCT((tl_target=$C13)*(tl_sub=N$4))>0,"S","")) | O13: =IF(SUMPRODUCT((tl_target=$C13)*(tl_sub=O$4)*(tl_align="Primary"))>0,"P",IF(SUMPRODUCT((tl_target=$C13)*(tl_sub=O$4))>0,"S","")) | ... Q13: =IF(SUMPRODUCT((tl_target=$C13)*(tl_sub=Q$4)*(tl_align="Primary"))>0,"P",IF(SUMPRODUCT((tl_target=$C13)*(tl_sub=Q$4))>0,"S","")) | R13: =_xlfn.TEXTJOIN(", ",TRUE(),IF(SUMPRODUCT((tl_target=$C13)*(tl_principle="PP1"))>0,"PP1",""),IF(SUMPRODUCT((tl_target=$C13)*(tl_principle="PP2"))>0,"PP2",""),IF(SUMPRODUCT((tl_target=$C13)*(tl_principle="PP3"))>0,"PP3",""),IF(SUMPRODUCT((tl_target=$C13)*(tl_principle="PP4"))>0,"PP4","")) | S13: =SUMPRODUCT(--(tl_target=$C13)) -> 0 | T13: =IF(SUMPRODUCT((tl_target=$C13)*(tl_align="Primary"))>0,"Primary link",IF(S13>0,"Secondary only","Gap")) -> Gap
A14: 2 | B14: Zero Hunger | C14: 2.3 | D14: Outcome | F14: By 2030, double the agricultural productivity and incomes of small-scale food producers, in particular women, indigenous peoples, family farmers, pastoralists and fishers, including through secure and equal access to land, other productive resources and inputs, knowledge, financial services, markets and opportunities for value addition and non-farm employment | G14: 2 | H14: =IF(SUMPRODUCT((tl_target=$C14)*(tl_sub=H$4)*(tl_align="Primary"))>0,"P",IF(SUMPRODUCT((tl_target=$C14)*(tl_sub=H$4))>0,"S","")) | I14: =IF(SUMPRODUCT((tl_target=$C14)*(tl_sub=I$4)*(tl_align="Primary"))>0,"P",IF(SUMPRODUCT((tl_target=$C14)*(tl_sub=I$4))>0,"S","")) | J14: =IF(SUMPRODUCT((tl_target=$C14)*(tl_sub=J$4)*(tl_align="Primary"))>0,"P",IF(SUMPRODUCT((tl_target=$C14)*(tl_sub=J$4))>0,"S","")) | K14: =IF(SUMPRODUCT((tl_target=$C14)*(tl_sub=K$4)*(tl_align="Primary"))>0,"P",IF(SUMPRODUCT((tl_target=$C14)*(tl_sub=K$4))>0,"S","")) | L14: =IF(SUMPRODUCT((tl_target=$C14)*(tl_sub=L$4)*(tl_align="Primary"))>0,"P",IF(SUMPRODUCT((tl_target=$C14)*(tl_sub=L$4))>0,"S","")) | M14: =IF(SUMPRODUCT((tl_target=$C14)*(tl_sub=M$4)*(tl_align="Primary"))>0,"P",IF(SUMPRODUCT((tl_target=$C14)*(tl_sub=M$4))>0,"S","")) | N14: =IF(SUMPRODUCT((tl_target=$C14)*(tl_sub=N$4)*(tl_align="Primary"))>0,"P",IF(SUMPRODUCT((tl_target=$C14)*(tl_sub=N$4))>0,"S","")) | O14: =IF(SUMPRODUCT((tl_target=$C14)*(tl_sub=O$4)*(tl_align="Primary"))>0,"P",IF(SUMPRODUCT((tl_target=$C14)*(tl_sub=O$4))>0,"S","")) | ... Q14: =IF(SUMPRODUCT((tl_target=$C14)*(tl_sub=Q$4)*(tl_align="Primary"))>0,"P",IF(SUMPRODUCT((tl_target=$C14)*(tl_sub=Q$4))>0,"S","")) | R14: =_xlfn.TEXTJOIN(", ",TRUE(),IF(SUMPRODUCT((tl_target=$C14)*(tl_principle="PP1"))>0,"PP1",""),IF(SUMPRODUCT((tl_target=$C14)*(tl_principle="PP2"))>0,"PP2",""),IF(SUMPRODUCT((tl_target=$C14)*(tl_principle="PP3"))>0,"PP3",""),IF(SUMPRODUCT((tl_target=$C14)*(tl_principle="PP4"))>0,"PP4","")) | S14: =SUMPRODUCT(--(tl_target=$C14)) -> 0 | T14: =IF(SUMPRODUCT((tl_target=$C14)*(tl_align="Primary"))>0,"Primary link",IF(S14>0,"Secondary only","Gap")) -> Gap
A15: 2 | B15: Zero Hunger | C15: 2.4 | D15: Outcome | F15: By 2030, ensure sustainable food production systems and implement resilient agricultural practices that increase productivity and production, that help maintain ecosystems, that strengthen capacity for adaptation to climate change, extreme weather, drought, flooding and other disasters and that progressively improve land and soil quality | G15: 1 | H15: =IF(SUMPRODUCT((tl_target=$C15)*(tl_sub=H$4)*(tl_align="Primary"))>0,"P",IF(SUMPRODUCT((tl_target=$C15)*(tl_sub=H$4))>0,"S","")) | I15: =IF(SUMPRODUCT((tl_target=$C15)*(tl_sub=I$4)*(tl_align="Primary"))>0,"P",IF(SUMPRODUCT((tl_target=$C15)*(tl_sub=I$4))>0,"S","")) | J15: =IF(SUMPRODUCT((tl_target=$C15)*(tl_sub=J$4)*(tl_align="Primary"))>0,"P",IF(SUMPRODUCT((tl_target=$C15)*(tl_sub=J$4))>0,"S","")) | K15: =IF(SUMPRODUCT((tl_target=$C15)*(tl_sub=K$4)*(tl_align="Primary"))>0,"P",IF(SUMPRODUCT((tl_target=$C15)*(tl_sub=K$4))>0,"S","")) | L15: =IF(SUMPRODUCT((tl_target=$C15)*(tl_sub=L$4)*(tl_align="Primary"))>0,"P",IF(SUMPRODUCT((tl_target=$C15)*(tl_sub=L$4))>0,"S","")) | M15: =IF(SUMPRODUCT((tl_target=$C15)*(tl_sub=M$4)*(tl_align="Primary"))>0,"P",IF(SUMPRODUCT((tl_target=$C15)*(tl_sub=M$4))>0,"S","")) | N15: =IF(SUMPRODUCT((tl_target=$C15)*(tl_sub=N$4)*(tl_align="Primary"))>0,"P",IF(SUMPRODUCT((tl_target=$C15)*(tl_sub=N$4))>0,"S","")) | O15: =IF(SUMPRODUCT((tl_target=$C15)*(tl_sub=O$4)*(tl_align="Primary"))>0,"P",IF(SUMPRODUCT((tl_target=$C15)*(tl_sub=O$4))>0,"S","")) | ... Q15: =IF(SUMPRODUCT((tl_target=$C15)*(tl_sub=Q$4)*(tl_align="Primary"))>0,"P",IF(SUMPRODUCT((tl_target=$C15)*(tl_sub=Q$4))>0,"S","")) | R15: =_xlfn.TEXTJOIN(", ",TRUE(),IF(SUMPRODUCT((tl_target=$C15)*(tl_principle="PP1"))>0,"PP1",""),IF(SUMPRODUCT((tl_target=$C15)*(tl_principle="PP2"))>0,"PP2",""),IF(SUMPRODUCT((tl_target=$C15)*(tl_principle="PP3"))>0,"PP3",""),IF(SUMPRODUCT((tl_target=$C15)*(tl_principle="PP4"))>0,"PP4","")) | S15: =SUMPRODUCT(--(tl_target=$C15)) -> 0 | T15: =IF(SUMPRODUCT((tl_target=$C15)*(tl_align="Primary"))>0,"Primary link",IF(S15>0,"Secondary only","Gap")) -> Gap
A16: 2 | B16: Zero Hunger | C16: 2.5 | D16: Outcome | F16: By 2020, maintain the genetic diversity of seeds, cultivated plants and farmed and domesticated animals and their related wild species, including through soundly managed and diversified seed and plant banks at the national, regional and international levels, and promote access to and fair and equitable sharing of benefits arising from the utilization of genetic resources and associated traditional knowledge, as internationally agreed | G16: 2 | H16: =IF(SUMPRODUCT((tl_target=$C16)*(tl_sub=H$4)*(tl_align="Primary"))>0,"P",IF(SUMPRODUCT((tl_target=$C16)*(tl_sub=H$4))>0,"S","")) | I16: =IF(SUMPRODUCT((tl_target=$C16)*(tl_sub=I$4)*(tl_align="Primary"))>0,"P",IF(SUMPRODUCT((tl_target=$C16)*(tl_sub=I$4))>0,"S","")) | J16: =IF(SUMPRODUCT((tl_target=$C16)*(tl_sub=J$4)*(tl_align="Primary"))>0,"P",IF(SUMPRODUCT((tl_target=$C16)*(tl_sub=J$4))>0,"S","")) | K16: =IF(SUMPRODUCT((tl_target=$C16)*(tl_sub=K$4)*(tl_align="Primary"))>0,"P",IF(SUMPRODUCT((tl_target=$C16)*(tl_sub=K$4))>0,"S","")) | L16: =IF(SUMPRODUCT((tl_target=$C16)*(tl_sub=L$4)*(tl_align="Primary"))>0,"P",IF(SUMPRODUCT((tl_target=$C16)*(tl_sub=L$4))>0,"S","")) | M16: =IF(SUMPRODUCT((tl_target=$C16)*(tl_sub=M$4)*(tl_align="Primary"))>0,"P",IF(SUMPRODUCT((tl_target=$C16)*(tl_sub=M$4))>0,"S","")) | N16: =IF(SUMPRODUCT((tl_target=$C16)*(tl_sub=N$4)*(tl_align="Primary"))>0,"P",IF(SUMPRODUCT((tl_target=$C16)*(tl_sub=N$4))>0,"S","")) | O16: =IF(SUMPRODUCT((tl_target=$C16)*(tl_sub=O$4)*(tl_align="Primary"))>0,"P",IF(SUMPRODUCT((tl_target=$C16)*(tl_sub=O$4))>0,"S","")) | ... Q16: =IF(SUMPRODUCT((tl_target=$C16)*(tl_sub=Q$4)*(tl_align="Primary"))>0,"P",IF(SUMPRODUCT((tl_target=$C16)*(tl_sub=Q$4))>0,"S","")) | R16: =_xlfn.TEXTJOIN(", ",TRUE(),IF(SUMPRODUCT((tl_target=$C16)*(tl_principle="PP1"))>0,"PP1",""),IF(SUMPRODUCT((tl_target=$C16)*(tl_principle="PP2"))>0,"PP2",""),IF(SUMPRODUCT((tl_target=$C16)*(tl_principle="PP3"))>0,"PP3",""),IF(SUMPRODUCT((tl_target=$C16)*(tl_principle="PP4"))>0,"PP4","")) | S16: =SUMPRODUCT(--(tl_target=$C16)) -> 0 | T16: =IF(SUMPRODUCT((tl_target=$C16)*(tl_align="Primary"))>0,"Primary link",IF(S16>0,"Secondary only","Gap")) -> Gap
A17: 2 | B17: Zero Hunger | C17: 2.a | D17: Means of implementation | F17: Increase investment, including through enhanced international cooperation, in rural infrastructure, agricultural research and extension services, technology development and plant and livestock gene banks in order to enhance agricultural productive capacity in developing countries, in particular least developed countries | G17: 2 | H17: =IF(SUMPRODUCT((tl_target=$C17)*(tl_sub=H$4)*(tl_align="Primary"))>0,"P",IF(SUMPRODUCT((tl_target=$C17)*(tl_sub=H$4))>0,"S","")) | I17: =IF(SUMPRODUCT((tl_target=$C17)*(tl_sub=I$4)*(tl_align="Primary"))>0,"P",IF(SUMPRODUCT((tl_target=$C17)*(tl_sub=I$4))>0,"S","")) | J17: =IF(SUMPRODUCT((tl_target=$C17)*(tl_sub=J$4)*(tl_align="Primary"))>0,"P",IF(SUMPRODUCT((tl_target=$C17)*(tl_sub=J$4))>0,"S","")) | K17: =IF(SUMPRODUCT((tl_target=$C17)*(tl_sub=K$4)*(tl_align="Primary"))>0,"P",IF(SUMPRODUCT((tl_target=$C17)*(tl_sub=K$4))>0,"S","")) | L17: =IF(SUMPRODUCT((tl_target=$C17)*(tl_sub=L$4)*(tl_align="Primary"))>0,"P",IF(SUMPRODUCT((tl_target=$C17)*(tl_sub=L$4))>0,"S","")) | M17: =IF(SUMPRODUCT((tl_target=$C17)*(tl_sub=M$4)*(tl_align="Primary"))>0,"P",IF(SUMPRODUCT((tl_target=$C17)*(tl_sub=M$4))>0,"S","")) | N17: =IF(SUMPRODUCT((tl_target=$C17)*(tl_sub=N$4)*(tl_align="Primary"))>0,"P",IF(SUMPRODUCT((tl_target=$C17)*(tl_sub=N$4))>0,"S","")) | O17: =IF(SUMPRODUCT((tl_target=$C17)*(tl_sub=O$4)*(tl_align="Primary"))>0,"P",IF(SUMPRODUCT((tl_target=$C17)*(tl_sub=O$4))>0,"S","")) | ... Q17: =IF(SUMPRODUCT((tl_target=$C17)*(tl_sub=Q$4)*(tl_align="Primary"))>0,"P",IF(SUMPRODUCT((tl_target=$C17)*(tl_sub=Q$4))>0,"S","")) | R17: =_xlfn.TEXTJOIN(", ",TRUE(),IF(SUMPRODUCT((tl_target=$C17)*(tl_principle="PP1"))>0,"PP1",""),IF(SUMPRODUCT((tl_target=$C17)*(tl_principle="PP2"))>0,"PP2",""),IF(SUMPRODUCT((tl_target=$C17)*(tl_principle="PP3"))>0,"PP3",""),IF(SUMPRODUCT((tl_target=$C17)*(tl_principle="PP4"))>0,"PP4","")) | S17: =SUMPRODUCT(--(tl_target=$C17)) -> 0 | T17: =IF(SUMPRODUCT((tl_target=$C17)*(tl_align="Primary"))>0,"Primary link",IF(S17>0,"Secondary only","Gap")) -> Gap
A18: 2 | B18: Zero Hunger | C18: 2.b | D18: Means of implementation | F18: Correct and prevent trade restrictions and distortions in world agricultural markets, including through the parallel elimination of all forms of agricultural export subsidies and all export measures with equivalent effect, in accordance with the mandate of the Doha Development Round | G18: 1 | H18: =IF(SUMPRODUCT((tl_target=$C18)*(tl_sub=H$4)*(tl_align="Primary"))>0,"P",IF(SUMPRODUCT((tl_target=$C18)*(tl_sub=H$4))>0,"S","")) | I18: =IF(SUMPRODUCT((tl_target=$C18)*(tl_sub=I$4)*(tl_align="Primary"))>0,"P",IF(SUMPRODUCT((tl_target=$C18)*(tl_sub=I$4))>0,"S","")) | J18: =IF(SUMPRODUCT((tl_target=$C18)*(tl_sub=J$4)*(tl_align="Primary"))>0,"P",IF(SUMPRODUCT((tl_target=$C18)*(tl_sub=J$4))>0,"S","")) | K18: =IF(SUMPRODUCT((tl_target=$C18)*(tl_sub=K$4)*(tl_align="Primary"))>0,"P",IF(SUMPRODUCT((tl_target=$C18)*(tl_sub=K$4))>0,"S","")) | L18: =IF(SUMPRODUCT((tl_target=$C18)*(tl_sub=L$4)*(tl_align="Primary"))>0,"P",IF(SUMPRODUCT((tl_target=$C18)*(tl_sub=L$4))>0,"S","")) | M18: =IF(SUMPRODUCT((tl_target=$C18)*(tl_sub=M$4)*(tl_align="Primary"))>0,"P",IF(SUMPRODUCT((tl_target=$C18)*(tl_sub=M$4))>0,"S","")) | N18: =IF(SUMPRODUCT((tl_target=$C18)*(tl_sub=N$4)*(tl_align="Primary"))>0,"P",IF(SUMPRODUCT((tl_target=$C18)*(tl_sub=N$4))>0,"S","")) | O18: =IF(SUMPRODUCT((tl_target=$C18)*(tl_sub=O$4)*(tl_align="Primary"))>0,"P",IF(SUMPRODUCT((tl_target=$C18)*(tl_sub=O$4))>0,"S","")) | ... Q18: =IF(SUMPRODUCT((tl_target=$C18)*(tl_sub=Q$4)*(tl_align="Primary"))>0,"P",IF(SUMPRODUCT((tl_target=$C18)*(tl_sub=Q$4))>0,"S","")) | R18: =_xlfn.TEXTJOIN(", ",TRUE(),IF(SUMPRODUCT((tl_target=$C18)*(tl_principle="PP1"))>0,"PP1",""),IF(SUMPRODUCT((tl_target=$C18)*(tl_principle="PP2"))>0,"PP2",""),IF(SUMPRODUCT((tl_target=$C18)*(tl_principle="PP3"))>0,"PP3",""),IF(SUMPRODUCT((tl_target=$C18)*(tl_principle="PP4"))>0,"PP4","")) | S18: =SUMPRODUCT(--(tl_target=$C18)) -> 0 | T18: =IF(SUMPRODUCT((tl_target=$C18)*(tl_align="Primary"))>0,"Primary link",IF(S18>0,"Secondary only","Gap")) -> Gap
A19: 2 | B19: Zero Hunger | C19: 2.c | D19: Means of implementation | F19: Adopt measures to ensure the proper functioning of food commodity markets and their derivatives and facilitate timely access to market information, including on food reserves, in order to help limit extreme food price volatility | G19: 1 | H19: =IF(SUMPRODUCT((tl_target=$C19)*(tl_sub=H$4)*(tl_align="Primary"))>0,"P",IF(SUMPRODUCT((tl_target=$C19)*(tl_sub=H$4))>0,"S","")) | I19: =IF(SUMPRODUCT((tl_target=$C19)*(tl_sub=I$4)*(tl_align="Primary"))>0,"P",IF(SUMPRODUCT((tl_target=$C19)*(tl_sub=I$4))>0,"S","")) | J19: =IF(SUMPRODUCT((tl_target=$C19)*(tl_sub=J$4)*(tl_align="Primary"))>0,"P",IF(SUMPRODUCT((tl_target=$C19)*(tl_sub=J$4))>0,"S","")) | K19: =IF(SUMPRODUCT((tl_target=$C19)*(tl_sub=K$4)*(tl_align="Primary"))>0,"P",IF(SUMPRODUCT((tl_target=$C19)*(tl_sub=K$4))>0,"S","")) | L19: =IF(SUMPRODUCT((tl_target=$C19)*(tl_sub=L$4)*(tl_align="Primary"))>0,"P",IF(SUMPRODUCT((tl_target=$C19)*(tl_sub=L$4))>0,"S","")) | M19: =IF(SUMPRODUCT((tl_target=$C19)*(tl_sub=M$4)*(tl_align="Primary"))>0,"P",IF(SUMPRODUCT((tl_target=$C19)*(tl_sub=M$4))>0,"S","")) | N19: =IF(SUMPRODUCT((tl_target=$C19)*(tl_sub=N$4)*(tl_align="Primary"))>0,"P",IF(SUMPRODUCT((tl_target=$C19)*(tl_sub=N$4))>0,"S","")) | O19: =IF(SUMPRODUCT((tl_target=$C19)*(tl_sub=O$4)*(tl_align="Primary"))>0,"P",IF(SUMPRODUCT((tl_target=$C19)*(tl_sub=O$4))>0,"S","")) | ... Q19: =IF(SUMPRODUCT((tl_target=$C19)*(tl_sub=Q$4)*(tl_align="Primary"))>0,"P",IF(SUMPRODUCT((tl_target=$C19)*(tl_sub=Q$4))>0,"S","")) | R19: =_xlfn.TEXTJOIN(", ",TRUE(),IF(SUMPRODUCT((tl_target=$C19)*(tl_principle="PP1"))>0,"PP1",""),IF(SUMPRODUCT((tl_target=$C19)*(tl_principle="PP2"))>0,"PP2",""),IF(SUMPRODUCT((tl_target=$C19)*(tl_principle="PP3"))>0,"PP3",""),IF(SUMPRODUCT((tl_target=$C19)*(tl_principle="PP4"))>0,"PP4","")) | S19: =SUMPRODUCT(--(tl_target=$C19)) -> 0 | T19: =IF(SUMPRODUCT((tl_target=$C19)*(tl_align="Primary"))>0,"Primary link",IF(S19>0,"Secondary only","Gap")) -> Gap
A20: 3 | B20: Good Health and Well-being | C20: 3.1 | D20: Outcome | F20: By 2030, reduce the global maternal mortality ratio to less than 70 per 100,000 live births | G20: 2 | H20: =IF(SUMPRODUCT((tl_target=$C20)*(tl_sub=H$4)*(tl_align="Primary"))>0,"P",IF(SUMPRODUCT((tl_target=$C20)*(tl_sub=H$4))>0,"S","")) | I20: =IF(SUMPRODUCT((tl_target=$C20)*(tl_sub=I$4)*(tl_align="Primary"))>0,"P",IF(SUMPRODUCT((tl_target=$C20)*(tl_sub=I$4))>0,"S","")) | J20: =IF(SUMPRODUCT((tl_target=$C20)*(tl_sub=J$4)*(tl_align="Primary"))>0,"P",IF(SUMPRODUCT((tl_target=$C20)*(tl_sub=J$4))>0,"S","")) | K20: =IF(SUMPRODUCT((tl_target=$C20)*(tl_sub=K$4)*(tl_align="Primary"))>0,"P",IF(SUMPRODUCT((tl_target=$C20)*(tl_sub=K$4))>0,"S","")) | L20: =IF(SUMPRODUCT((tl_target=$C20)*(tl_sub=L$4)*(tl_align="Primary"))>0,"P",IF(SUMPRODUCT((tl_target=$C20)*(tl_sub=L$4))>0,"S","")) | M20: =IF(SUMPRODUCT((tl_target=$C20)*(tl_sub=M$4)*(tl_align="Primary"))>0,"P",IF(SUMPRODUCT((tl_target=$C20)*(tl_sub=M$4))>0,"S","")) | N20: =IF(SUMPRODUCT((tl_target=$C20)*(tl_sub=N$4)*(tl_align="Primary"))>0,"P",IF(SUMPRODUCT((tl_target=$C20)*(tl_sub=N$4))>0,"S","")) | O20: =IF(SUMPRODUCT((tl_target=$C20)*(tl_sub=O$4)*(tl_align="Primary"))>0,"P",IF(SUMPRODUCT((tl_target=$C20)*(tl_sub=O$4))>0,"S","")) | ... Q20: =IF(SUMPRODUCT((tl_target=$C20)*(tl_sub=Q$4)*(tl_align="Primary"))>0,"P",IF(SUMPRODUCT((tl_target=$C20)*(tl_sub=Q$4))>0,"S","")) | R20: =_xlfn.TEXTJOIN(", ",TRUE(),IF(SUMPRODUCT((tl_target=$C20)*(tl_principle="PP1"))>0,"PP1",""),IF(SUMPRODUCT((tl_target=$C20)*(tl_principle="PP2"))>0,"PP2",""),IF(SUMPRODUCT((tl_target=$C20)*(tl_principle="PP3"))>0,"PP3",""),IF(SUMPRODUCT((tl_target=$C20)*(tl_principle="PP4"))>0,"PP4","")) | S20: =SUMPRODUCT(--(tl_target=$C20)) -> 0 | T20: =IF(SUMPRODUCT((tl_target=$C20)*(tl_align="Primary"))>0,"Primary link",IF(S20>0,"Secondary only","Gap")) -> Gap
... A35: 4 | B35: Quality Education | C35: 4.3 | D35: Outcome | F35: By 2030, ensure equal access for all women and men to affordable and quality technical, vocational and tertiary education, including university | G35: 1 | H35: =IF(SUMPRODUCT((tl_target=$C35)*(tl_sub=H$4)*(tl_align="Primary"))>0,"P",IF(SUMPRODUCT((tl_target=$C35)*(tl_sub=H$4))>0,"S","")) | I35: =IF(SUMPRODUCT((tl_target=$C35)*(tl_sub=I$4)*(tl_align="Primary"))>0,"P",IF(SUMPRODUCT((tl_target=$C35)*(tl_sub=I$4))>0,"S","")) | J35: =IF(SUMPRODUCT((tl_target=$C35)*(tl_sub=J$4)*(tl_align="Primary"))>0,"P",IF(SUMPRODUCT((tl_target=$C35)*(tl_sub=J$4))>0,"S","")) | K35: =IF(SUMPRODUCT((tl_target=$C35)*(tl_sub=K$4)*(tl_align="Primary"))>0,"P",IF(SUMPRODUCT((tl_target=$C35)*(tl_sub=K$4))>0,"S","")) | L35: =IF(SUMPRODUCT((tl_target=$C35)*(tl_sub=L$4)*(tl_align="Primary"))>0,"P",IF(SUMPRODUCT((tl_target=$C35)*(tl_sub=L$4))>0,"S","")) | M35: =IF(SUMPRODUCT((tl_target=$C35)*(tl_sub=M$4)*(tl_align="Primary"))>0,"P",IF(SUMPRODUCT((tl_target=$C35)*(tl_sub=M$4))>0,"S","")) | N35: =IF(SUMPRODUCT((tl_target=$C35)*(tl_sub=N$4)*(tl_align="Primary"))>0,"P",IF(SUMPRODUCT((tl_target=$C35)*(tl_sub=N$4))>0,"S","")) | O35: =IF(SUMPRODUCT((tl_target=$C35)*(tl_sub=O$4)*(tl_align="Primary"))>0,"P",IF(SUMPRODUCT((tl_target=$C35)*(tl_sub=O$4))>0,"S","")) | ... Q35: =IF(SUMPRODUCT((tl_target=$C35)*(tl_sub=Q$4)*(tl_align="Primary"))>0,"P",IF(SUMPRODUCT((tl_target=$C35)*(tl_sub=Q$4))>0,"S","")) | R35: =_xlfn.TEXTJOIN(", ",TRUE(),IF(SUMPRODUCT((tl_target=$C35)*(tl_principle="PP1"))>0,"PP1",""),IF(SUMPRODUCT((tl_target=$C35)*(tl_principle="PP2"))>0,"PP2",""),IF(SUMPRODUCT((tl_target=$C35)*(tl_principle="PP3"))>0,"PP3",""),IF(SUMPRODUCT((tl_target=$C35)*(tl_principle="PP4"))>0,"PP4","")) | S35: =SUMPRODUCT(--(tl_target=$C35)) -> 0 | T35: =IF(SUMPRODUCT((tl_target=$C35)*(tl_align="Primary"))>0,"Primary link",IF(S35>0,"Secondary only","Gap")) -> Gap
A36: 4 | B36: Quality Education | C36: 4.4 | D36: Outcome | E36: Relevant skills for work | F36: By 2030, substantially increase the number of youth and adults who have relevant skills, including technical and vocational skills, for employment, decent jobs and entrepreneurship | G36: 1 | H36: =IF(SUMPRODUCT((tl_target=$C36)*(tl_sub=H$4)*(tl_align="Primary"))>0,"P",IF(SUMPRODUCT((tl_target=$C36)*(tl_sub=H$4))>0,"S","")) | I36: =IF(SUMPRODUCT((tl_target=$C36)*(tl_sub=I$4)*(tl_align="Primary"))>0,"P",IF(SUMPRODUCT((tl_target=$C36)*(tl_sub=I$4))>0,"S","")) | J36: =IF(SUMPRODUCT((tl_target=$C36)*(tl_sub=J$4)*(tl_align="Primary"))>0,"P",IF(SUMPRODUCT((tl_target=$C36)*(tl_sub=J$4))>0,"S","")) | K36: =IF(SUMPRODUCT((tl_target=$C36)*(tl_sub=K$4)*(tl_align="Primary"))>0,"P",IF(SUMPRODUCT((tl_target=$C36)*(tl_sub=K$4))>0,"S","")) | L36: =IF(SUMPRODUCT((tl_target=$C36)*(tl_sub=L$4)*(tl_align="Primary"))>0,"P",IF(SUMPRODUCT((tl_target=$C36)*(tl_sub=L$4))>0,"S","")) | M36: =IF(SUMPRODUCT((tl_target=$C36)*(tl_sub=M$4)*(tl_align="Primary"))>0,"P",IF(SUMPRODUCT((tl_target=$C36)*(tl_sub=M$4))>0,"S","")) -> S | N36: =IF(SUMPRODUCT((tl_target=$C36)*(tl_sub=N$4)*(tl_align="Primary"))>0,"P",IF(SUMPRODUCT((tl_target=$C36)*(tl_sub=N$4))>0,"S","")) | O36: =IF(SUMPRODUCT((tl_target=$C36)*(tl_sub=O$4)*(tl_align="Primary"))>0,"P",IF(SUMPRODUCT((tl_target=$C36)*(tl_sub=O$4))>0,"S","")) | ... Q36: =IF(SUMPRODUCT((tl_target=$C36)*(tl_sub=Q$4)*(tl_align="Primary"))>0,"P",IF(SUMPRODUCT((tl_target=$C36)*(tl_sub=Q$4))>0,"S","")) | R36: =_xlfn.TEXTJOIN(", ",TRUE(),IF(SUMPRODUCT((tl_target=$C36)*(tl_principle="PP1"))>0,"PP1",""),IF(SUMPRODUCT((tl_target=$C36)*(tl_principle="PP2"))>0,"PP2",""),IF(SUMPRODUCT((tl_target=$C36)*(tl_principle="PP3"))>0,"PP3",""),IF(SUMPRODUCT((tl_target=$C36)*(tl_principle="PP4"))>0,"PP4","")) -> PP3 | S36: =SUMPRODUCT(--(tl_target=$C36)) -> 1 | T36: =IF(SUMPRODUCT((tl_target=$C36)*(tl_align="Primary"))>0,"Primary link",IF(S36>0,"Secondary only","Gap")) -> Secondary only
A37: 4 | B37: Quality Education | C37: 4.5 | D37: Outcome | F37: By 2030, eliminate gender disparities in education and ensure equal access to all levels of education and vocational training for the vulnerable, including persons with disabilities, indigenous peoples and children in vulnerable situations | G37: 1 | H37: =IF(SUMPRODUCT((tl_target=$C37)*(tl_sub=H$4)*(tl_align="Primary"))>0,"P",IF(SUMPRODUCT((tl_target=$C37)*(tl_sub=H$4))>0,"S","")) | I37: =IF(SUMPRODUCT((tl_target=$C37)*(tl_sub=I$4)*(tl_align="Primary"))>0,"P",IF(SUMPRODUCT((tl_target=$C37)*(tl_sub=I$4))>0,"S","")) | J37: =IF(SUMPRODUCT((tl_target=$C37)*(tl_sub=J$4)*(tl_align="Primary"))>0,"P",IF(SUMPRODUCT((tl_target=$C37)*(tl_sub=J$4))>0,"S","")) | K37: =IF(SUMPRODUCT((tl_target=$C37)*(tl_sub=K$4)*(tl_align="Primary"))>0,"P",IF(SUMPRODUCT((tl_target=$C37)*(tl_sub=K$4))>0,"S","")) | L37: =IF(SUMPRODUCT((tl_target=$C37)*(tl_sub=L$4)*(tl_align="Primary"))>0,"P",IF(SUMPRODUCT((tl_target=$C37)*(tl_sub=L$4))>0,"S","")) | M37: =IF(SUMPRODUCT((tl_target=$C37)*(tl_sub=M$4)*(tl_align="Primary"))>0,"P",IF(SUMPRODUCT((tl_target=$C37)*(tl_sub=M$4))>0,"S","")) | N37: =IF(SUMPRODUCT((tl_target=$C37)*(tl_sub=N$4)*(tl_align="Primary"))>0,"P",IF(SUMPRODUCT((tl_target=$C37)*(tl_sub=N$4))>0,"S","")) | O37: =IF(SUMPRODUCT((tl_target=$C37)*(tl_sub=O$4)*(tl_align="Primary"))>0,"P",IF(SUMPRODUCT((tl_target=$C37)*(tl_sub=O$4))>0,"S","")) | ... Q37: =IF(SUMPRODUCT((tl_target=$C37)*(tl_sub=Q$4)*(tl_align="Primary"))>0,"P",IF(SUMPRODUCT((tl_target=$C37)*(tl_sub=Q$4))>0,"S","")) | R37: =_xlfn.TEXTJOIN(", ",TRUE(),IF(SUMPRODUCT((tl_target=$C37)*(tl_principle="PP1"))>0,"PP1",""),IF(SUMPRODUCT((tl_target=$C37)*(tl_principle="PP2"))>0,"PP2",""),IF(SUMPRODUCT((tl_target=$C37)*(tl_principle="PP3"))>0,"PP3",""),IF(SUMPRODUCT((tl_target=$C37)*(tl_principle="PP4"))>0,"PP4","")) | S37: =SUMPRODUCT(--(tl_target=$C37)) -> 0 | T37: =IF(SUMPRODUCT((tl_target=$C37)*(tl_align="Primary"))>0,"Primary link",IF(S37>0,"Secondary only","Gap")) -> Gap
A38: 4 | B38: Quality Education | C38: 4.6 | D38: Outcome | F38: By 2030, ensure that all youth and a substantial proportion of adults, both men and women, achieve literacy and numeracy | G38: 1 | H38: =IF(SUMPRODUCT((tl_target=$C38)*(tl_sub=H$4)*(tl_align="Primary"))>0,"P",IF(SUMPRODUCT((tl_target=$C38)*(tl_sub=H$4))>0,"S","")) | I38: =IF(SUMPRODUCT((tl_target=$C38)*(tl_sub=I$4)*(tl_align="Primary"))>0,"P",IF(SUMPRODUCT((tl_target=$C38)*(tl_sub=I$4))>0,"S","")) | J38: =IF(SUMPRODUCT((tl_target=$C38)*(tl_sub=J$4)*(tl_align="Primary"))>0,"P",IF(SUMPRODUCT((tl_target=$C38)*(tl_sub=J$4))>0,"S","")) | K38: =IF(SUMPRODUCT((tl_target=$C38)*(tl_sub=K$4)*(tl_align="Primary"))>0,"P",IF(SUMPRODUCT((tl_target=$C38)*(tl_sub=K$4))>0,"S","")) | L38: =IF(SUMPRODUCT((tl_target=$C38)*(tl_sub=L$4)*(tl_align="Primary"))>0,"P",IF(SUMPRODUCT((tl_target=$C38)*(tl_sub=L$4))>0,"S","")) | M38: =IF(SUMPRODUCT((tl_target=$C38)*(tl_sub=M$4)*(tl_align="Primary"))>0,"P",IF(SUMPRODUCT((tl_target=$C38)*(tl_sub=M$4))>0,"S","")) | N38: =IF(SUMPRODUCT((tl_target=$C38)*(tl_sub=N$4)*(tl_align="Primary"))>0,"P",IF(SUMPRODUCT((tl_target=$C38)*(tl_sub=N$4))>0,"S","")) | O38: =IF(SUMPRODUCT((tl_target=$C38)*(tl_sub=O$4)*(tl_align="Primary"))>0,"P",IF(SUMPRODUCT((tl_target=$C38)*(tl_sub=O$4))>0,"S","")) | ... Q38: =IF(SUMPRODUCT((tl_target=$C38)*(tl_sub=Q$4)*(tl_align="Primary"))>0,"P",IF(SUMPRODUCT((tl_target=$C38)*(tl_sub=Q$4))>0,"S","")) | R38: =_xlfn.TEXTJOIN(", ",TRUE(),IF(SUMPRODUCT((tl_target=$C38)*(tl_principle="PP1"))>0,"PP1",""),IF(SUMPRODUCT((tl_target=$C38)*(tl_principle="PP2"))>0,"PP2",""),IF(SUMPRODUCT((tl_target=$C38)*(tl_principle="PP3"))>0,"PP3",""),IF(SUMPRODUCT((tl_target=$C38)*(tl_principle="PP4"))>0,"PP4","")) | S38: =SUMPRODUCT(--(tl_target=$C38)) -> 0 | T38: =IF(SUMPRODUCT((tl_target=$C38)*(tl_align="Primary"))>0,"Primary link",IF(S38>0,"Secondary only","Gap")) -> Gap
A39: 4 | B39: Quality Education | C39: 4.7 | D39: Outcome | F39: By 2030, ensure that all learners acquire the knowledge and skills needed to promote sustainable development, including, among others, through education for sustainable development and sustainable lifestyles, human rights, gender equality, promotion of a culture of peace and non-violence, global citizenship and appreciation of cultural diversity and of culture's contribution to sustainable development | G39: 1 | H39: =IF(SUMPRODUCT((tl_target=$C39)*(tl_sub=H$4)*(tl_align="Primary"))>0,"P",IF(SUMPRODUCT((tl_target=$C39)*(tl_sub=H$4))>0,"S","")) | I39: =IF(SUMPRODUCT((tl_target=$C39)*(tl_sub=I$4)*(tl_align="Primary"))>0,"P",IF(SUMPRODUCT((tl_target=$C39)*(tl_sub=I$4))>0,"S","")) | J39: =IF(SUMPRODUCT((tl_target=$C39)*(tl_sub=J$4)*(tl_align="Primary"))>0,"P",IF(SUMPRODUCT((tl_target=$C39)*(tl_sub=J$4))>0,"S","")) | K39: =IF(SUMPRODUCT((tl_target=$C39)*(tl_sub=K$4)*(tl_align="Primary"))>0,"P",IF(SUMPRODUCT((tl_target=$C39)*(tl_sub=K$4))>0,"S","")) | L39: =IF(SUMPRODUCT((tl_target=$C39)*(tl_sub=L$4)*(tl_align="Primary"))>0,"P",IF(SUMPRODUCT((tl_target=$C39)*(tl_sub=L$4))>0,"S","")) | M39: =IF(SUMPRODUCT((tl_target=$C39)*(tl_sub=M$4)*(tl_align="Primary"))>0,"P",IF(SUMPRODUCT((tl_target=$C39)*(tl_sub=M$4))>0,"S","")) | N39: =IF(SUMPRODUCT((tl_target=$C39)*(tl_sub=N$4)*(tl_align="Primary"))>0,"P",IF(SUMPRODUCT((tl_target=$C39)*(tl_sub=N$4))>0,"S","")) | O39: =IF(SUMPRODUCT((tl_target=$C39)*(tl_sub=O$4)*(tl_align="Primary"))>0,"P",IF(SUMPRODUCT((tl_target=$C39)*(tl_sub=O$4))>0,"S","")) | ... Q39: =IF(SUMPRODUCT((tl_target=$C39)*(tl_sub=Q$4)*(tl_align="Primary"))>0,"P",IF(SUMPRODUCT((tl_target=$C39)*(tl_sub=Q$4))>0,"S","")) | R39: =_xlfn.TEXTJOIN(", ",TRUE(),IF(SUMPRODUCT((tl_target=$C39)*(tl_principle="PP1"))>0,"PP1",""),IF(SUMPRODUCT((tl_target=$C39)*(tl_principle="PP2"))>0,"PP2",""),IF(SUMPRODUCT((tl_target=$C39)*(tl_principle="PP3"))>0,"PP3",""),IF(SUMPRODUCT((tl_target=$C39)*(tl_principle="PP4"))>0,"PP4","")) | S39: =SUMPRODUCT(--(tl_target=$C39)) -> 0 | T39: =IF(SUMPRODUCT((tl_target=$C39)*(tl_align="Primary"))>0,"Primary link",IF(S39>0,"Secondary only","Gap")) -> Gap
A40: 4 | B40: Quality Education | C40: 4.a | D40: Means of implementation | F40: Build and upgrade education facilities that are child, disability and gender sensitive and provide safe, non-violent, inclusive and effective learning environments for all | G40: 1 | H40: =IF(SUMPRODUCT((tl_target=$C40)*(tl_sub=H$4)*(tl_align="Primary"))>0,"P",IF(SUMPRODUCT((tl_target=$C40)*(tl_sub=H$4))>0,"S","")) | I40: =IF(SUMPRODUCT((tl_target=$C40)*(tl_sub=I$4)*(tl_align="Primary"))>0,"P",IF(SUMPRODUCT((tl_target=$C40)*(tl_sub=I$4))>0,"S","")) | J40: =IF(SUMPRODUCT((tl_target=$C40)*(tl_sub=J$4)*(tl_align="Primary"))>0,"P",IF(SUMPRODUCT((tl_target=$C40)*(tl_sub=J$4))>0,"S","")) | K40: =IF(SUMPRODUCT((tl_target=$C40)*(tl_sub=K$4)*(tl_align="Primary"))>0,"P",IF(SUMPRODUCT((tl_target=$C40)*(tl_sub=K$4))>0,"S","")) | L40: =IF(SUMPRODUCT((tl_target=$C40)*(tl_sub=L$4)*(tl_align="Primary"))>0,"P",IF(SUMPRODUCT((tl_target=$C40)*(tl_sub=L$4))>0,"S","")) | M40: =IF(SUMPRODUCT((tl_target=$C40)*(tl_sub=M$4)*(tl_align="Primary"))>0,"P",IF(SUMPRODUCT((tl_target=$C40)*(tl_sub=M$4))>0,"S","")) | N40: =IF(SUMPRODUCT((tl_target=$C40)*(tl_sub=N$4)*(tl_align="Primary"))>0,"P",IF(SUMPRODUCT((tl_target=$C40)*(tl_sub=N$4))>0,"S","")) | O40: =IF(SUMPRODUCT((tl_target=$C40)*(tl_sub=O$4)*(tl_align="Primary"))>0,"P",IF(SUMPRODUCT((tl_target=$C40)*(tl_sub=O$4))>0,"S","")) | ... Q40: =IF(SUMPRODUCT((tl_target=$C40)*(tl_sub=Q$4)*(tl_align="Primary"))>0,"P",IF(SUMPRODUCT((tl_target=$C40)*(tl_sub=Q$4))>0,"S","")) | R40: =_xlfn.TEXTJOIN(", ",TRUE(),IF(SUMPRODUCT((tl_target=$C40)*(tl_principle="PP1"))>0,"PP1",""),IF(SUMPRODUCT((tl_target=$C40)*(tl_principle="PP2"))>0,"PP2",""),IF(SUMPRODUCT((tl_target=$C40)*(tl_principle="PP3"))>0,"PP3",""),IF(SUMPRODUCT((tl_target=$C40)*(tl_principle="PP4"))>0,"PP4","")) | S40: =SUMPRODUCT(--(tl_target=$C40)) -> 0 | T40: =IF(SUMPRODUCT((tl_target=$C40)*(tl_align="Primary"))>0,"Primary link",IF(S40>0,"Secondary only","Gap")) -> Gap
A41: 4 | B41: Quality Education | C41: 4.b | D41: Means of implementation | F41: By 2020, substantially expand globally the number of scholarships available to developing countries, in particular least developed countries, small island developing States and African countries, for enrolment in higher education, including vocational training and information and communications technology, technical, engineering and scientific programmes, in developed countries and other developing countries | G41: 1 | H41: =IF(SUMPRODUCT((tl_target=$C41)*(tl_sub=H$4)*(tl_align="Primary"))>0,"P",IF(SUMPRODUCT((tl_target=$C41)*(tl_sub=H$4))>0,"S","")) | I41: =IF(SUMPRODUCT((tl_target=$C41)*(tl_sub=I$4)*(tl_align="Primary"))>0,"P",IF(SUMPRODUCT((tl_target=$C41)*(tl_sub=I$4))>0,"S","")) | J41: =IF(SUMPRODUCT((tl_target=$C41)*(tl_sub=J$4)*(tl_align="Primary"))>0,"P",IF(SUMPRODUCT((tl_target=$C41)*(tl_sub=J$4))>0,"S","")) | K41: =IF(SUMPRODUCT((tl_target=$C41)*(tl_sub=K$4)*(tl_align="Primary"))>0,"P",IF(SUMPRODUCT((tl_target=$C41)*(tl_sub=K$4))>0,"S","")) | L41: =IF(SUMPRODUCT((tl_target=$C41)*(tl_sub=L$4)*(tl_align="Primary"))>0,"P",IF(SUMPRODUCT((tl_target=$C41)*(tl_sub=L$4))>0,"S","")) | M41: =IF(SUMPRODUCT((tl_target=$C41)*(tl_sub=M$4)*(tl_align="Primary"))>0,"P",IF(SUMPRODUCT((tl_target=$C41)*(tl_sub=M$4))>0,"S","")) | N41: =IF(SUMPRODUCT((tl_target=$C41)*(tl_sub=N$4)*(tl_align="Primary"))>0,"P",IF(SUMPRODUCT((tl_target=$C41)*(tl_sub=N$4))>0,"S","")) | O41: =IF(SUMPRODUCT((tl_target=$C41)*(tl_sub=O$4)*(tl_align="Primary"))>0,"P",IF(SUMPRODUCT((tl_target=$C41)*(tl_sub=O$4))>0,"S","")) | ... Q41: =IF(SUMPRODUCT((tl_target=$C41)*(tl_sub=Q$4)*(tl_align="Primary"))>0,"P",IF(SUMPRODUCT((tl_target=$C41)*(tl_sub=Q$4))>0,"S","")) | R41: =_xlfn.TEXTJOIN(", ",TRUE(),IF(SUMPRODUCT((tl_target=$C41)*(tl_principle="PP1"))>0,"PP1",""),IF(SUMPRODUCT((tl_target=$C41)*(tl_principle="PP2"))>0,"PP2",""),IF(SUMPRODUCT((tl_target=$C41)*(tl_principle="PP3"))>0,"PP3",""),IF(SUMPRODUCT((tl_target=$C41)*(tl_principle="PP4"))>0,"PP4","")) | S41: =SUMPRODUCT(--(tl_target=$C41)) -> 0 | T41: =IF(SUMPRODUCT((tl_target=$C41)*(tl_align="Primary"))>0,"Primary link",IF(S41>0,"Secondary only","Gap")) -> Gap
A42: 4 | B42: Quality Education | C42: 4.c | D42: Means of implementation | F42: By 2030, substantially increase the supply of qualified teachers, including through international cooperation for teacher training in developing countries, especially least developed countries and small island developing States | G42: 1 | H42: =IF(SUMPRODUCT((tl_target=$C42)*(tl_sub=H$4)*(tl_align="Primary"))>0,"P",IF(SUMPRODUCT((tl_target=$C42)*(tl_sub=H$4))>0,"S","")) | I42: =IF(SUMPRODUCT((tl_target=$C42)*(tl_sub=I$4)*(tl_align="Primary"))>0,"P",IF(SUMPRODUCT((tl_target=$C42)*(tl_sub=I$4))>0,"S","")) | J42: =IF(SUMPRODUCT((tl_target=$C42)*(tl_sub=J$4)*(tl_align="Primary"))>0,"P",IF(SUMPRODUCT((tl_target=$C42)*(tl_sub=J$4))>0,"S","")) | K42: =IF(SUMPRODUCT((tl_target=$C42)*(tl_sub=K$4)*(tl_align="Primary"))>0,"P",IF(SUMPRODUCT((tl_target=$C42)*(tl_sub=K$4))>0,"S","")) | L42: =IF(SUMPRODUCT((tl_target=$C42)*(tl_sub=L$4)*(tl_align="Primary"))>0,"P",IF(SUMPRODUCT((tl_target=$C42)*(tl_sub=L$4))>0,"S","")) | M42: =IF(SUMPRODUCT((tl_target=$C42)*(tl_sub=M$4)*(tl_align="Primary"))>0,"P",IF(SUMPRODUCT((tl_target=$C42)*(tl_sub=M$4))>0,"S","")) | N42: =IF(SUMPRODUCT((tl_target=$C42)*(tl_sub=N$4)*(tl_align="Primary"))>0,"P",IF(SUMPRODUCT((tl_target=$C42)*(tl_sub=N$4))>0,"S","")) | O42: =IF(SUMPRODUCT((tl_target=$C42)*(tl_sub=O$4)*(tl_align="Primary"))>0,"P",IF(SUMPRODUCT((tl_target=$C42)*(tl_sub=O$4))>0,"S","")) | ... Q42: =IF(SUMPRODUCT((tl_target=$C42)*(tl_sub=Q$4)*(tl_align="Primary"))>0,"P",IF(SUMPRODUCT((tl_target=$C42)*(tl_sub=Q$4))>0,"S","")) | R42: =_xlfn.TEXTJOIN(", ",TRUE(),IF(SUMPRODUCT((tl_target=$C42)*(tl_principle="PP1"))>0,"PP1",""),IF(SUMPRODUCT((tl_target=$C42)*(tl_principle="PP2"))>0,"PP2",""),IF(SUMPRODUCT((tl_target=$C42)*(tl_principle="PP3"))>0,"PP3",""),IF(SUMPRODUCT((tl_target=$C42)*(tl_principle="PP4"))>0,"PP4","")) | S42: =SUMPRODUCT(--(tl_target=$C42)) -> 0 | T42: =IF(SUMPRODUCT((tl_target=$C42)*(tl_align="Primary"))>0,"Primary link",IF(S42>0,"Secondary only","Gap")) -> Gap
A43: 5 | B43: Gender Equality | C43: 5.1 | D43: Outcome | F43: End all forms of discrimination against all women and girls everywhere | G43: 1 | H43: =IF(SUMPRODUCT((tl_target=$C43)*(tl_sub=H$4)*(tl_align="Primary"))>0,"P",IF(SUMPRODUCT((tl_target=$C43)*(tl_sub=H$4))>0,"S","")) | I43: =IF(SUMPRODUCT((tl_target=$C43)*(tl_sub=I$4)*(tl_align="Primary"))>0,"P",IF(SUMPRODUCT((tl_target=$C43)*(tl_sub=I$4))>0,"S","")) | J43: =IF(SUMPRODUCT((tl_target=$C43)*(tl_sub=J$4)*(tl_align="Primary"))>0,"P",IF(SUMPRODUCT((tl_target=$C43)*(tl_sub=J$4))>0,"S","")) | K43: =IF(SUMPRODUCT((tl_target=$C43)*(tl_sub=K$4)*(tl_align="Primary"))>0,"P",IF(SUMPRODUCT((tl_target=$C43)*(tl_sub=K$4))>0,"S","")) | L43: =IF(SUMPRODUCT((tl_target=$C43)*(tl_sub=L$4)*(tl_align="Primary"))>0,"P",IF(SUMPRODUCT((tl_target=$C43)*(tl_sub=L$4))>0,"S","")) | M43: =IF(SUMPRODUCT((tl_target=$C43)*(tl_sub=M$4)*(tl_align="Primary"))>0,"P",IF(SUMPRODUCT((tl_target=$C43)*(tl_sub=M$4))>0,"S","")) | N43: =IF(SUMPRODUCT((tl_target=$C43)*(tl_sub=N$4)*(tl_align="Primary"))>0,"P",IF(SUMPRODUCT((tl_target=$C43)*(tl_sub=N$4))>0,"S","")) | O43: =IF(SUMPRODUCT((tl_target=$C43)*(tl_sub=O$4)*(tl_align="Primary"))>0,"P",IF(SUMPRODUCT((tl_target=$C43)*(tl_sub=O$4))>0,"S","")) | ... Q43: =IF(SUMPRODUCT((tl_target=$C43)*(tl_sub=Q$4)*(tl_align="Primary"))>0,"P",IF(SUMPRODUCT((tl_target=$C43)*(tl_sub=Q$4))>0,"S","")) | R43: =_xlfn.TEXTJOIN(", ",TRUE(),IF(SUMPRODUCT((tl_target=$C43)*(tl_principle="PP1"))>0,"PP1",""),IF(SUMPRODUCT((tl_target=$C43)*(tl_principle="PP2"))>0,"PP2",""),IF(SUMPRODUCT((tl_target=$C43)*(tl_principle="PP3"))>0,"PP3",""),IF(SUMPRODUCT((tl_target=$C43)*(tl_principle="PP4"))>0,"PP4","")) | S43: =SUMPRODUCT(--(tl_target=$C43)) -> 0 | T43: =IF(SUMPRODUCT((tl_target=$C43)*(tl_align="Primary"))>0,"Primary link",IF(S43>0,"Secondary only","Gap")) -> Gap
A44: 5 | B44: Gender Equality | C44: 5.2 | D44: Outcome | F44: Eliminate all forms of violence against all women and girls in the public and private spheres, including trafficking and sexual and other types of exploitation | G44: 2 | H44: =IF(SUMPRODUCT((tl_target=$C44)*(tl_sub=H$4)*(tl_align="Primary"))>0,"P",IF(SUMPRODUCT((tl_target=$C44)*(tl_sub=H$4))>0,"S","")) | I44: =IF(SUMPRODUCT((tl_target=$C44)*(tl_sub=I$4)*(tl_align="Primary"))>0,"P",IF(SUMPRODUCT((tl_target=$C44)*(tl_sub=I$4))>0,"S","")) | J44: =IF(SUMPRODUCT((tl_target=$C44)*(tl_sub=J$4)*(tl_align="Primary"))>0,"P",IF(SUMPRODUCT((tl_target=$C44)*(tl_sub=J$4))>0,"S","")) | K44: =IF(SUMPRODUCT((tl_target=$C44)*(tl_sub=K$4)*(tl_align="Primary"))>0,"P",IF(SUMPRODUCT((tl_target=$C44)*(tl_sub=K$4))>0,"S","")) | L44: =IF(SUMPRODUCT((tl_target=$C44)*(tl_sub=L$4)*(tl_align="Primary"))>0,"P",IF(SUMPRODUCT((tl_target=$C44)*(tl_sub=L$4))>0,"S","")) | M44: =IF(SUMPRODUCT((tl_target=$C44)*(tl_sub=M$4)*(tl_align="Primary"))>0,"P",IF(SUMPRODUCT((tl_target=$C44)*(tl_sub=M$4))>0,"S","")) | N44: =IF(SUMPRODUCT((tl_target=$C44)*(tl_sub=N$4)*(tl_align="Primary"))>0,"P",IF(SUMPRODUCT((tl_target=$C44)*(tl_sub=N$4))>0,"S","")) | O44: =IF(SUMPRODUCT((tl_target=$C44)*(tl_sub=O$4)*(tl_align="Primary"))>0,"P",IF(SUMPRODUCT((tl_target=$C44)*(tl_sub=O$4))>0,"S","")) | ... Q44: =IF(SUMPRODUCT((tl_target=$C44)*(tl_sub=Q$4)*(tl_align="Primary"))>0,"P",IF(SUMPRODUCT((tl_target=$C44)*(tl_sub=Q$4))>0,"S","")) | R44: =_xlfn.TEXTJOIN(", ",TRUE(),IF(SUMPRODUCT((tl_target=$C44)*(tl_principle="PP1"))>0,"PP1",""),IF(SUMPRODUCT((tl_target=$C44)*(tl_principle="PP2"))>0,"PP2",""),IF(SUMPRODUCT((tl_target=$C44)*(tl_principle="PP3"))>0,"PP3",""),IF(SUMPRODUCT((tl_target=$C44)*(tl_principle="PP4"))>0,"PP4","")) | S44: =SUMPRODUCT(--(tl_target=$C44)) -> 0 | T44: =IF(SUMPRODUCT((tl_target=$C44)*(tl_align="Primary"))>0,"Primary link",IF(S44>0,"Secondary only","Gap")) -> Gap
A45: 5 | B45: Gender Equality | C45: 5.3 | D45: Outcome | F45: Eliminate all harmful practices, such as child, early and forced marriage and female genital mutilation | G45: 2 | H45: =IF(SUMPRODUCT((tl_target=$C45)*(tl_sub=H$4)*(tl_align="Primary"))>0,"P",IF(SUMPRODUCT((tl_target=$C45)*(tl_sub=H$4))>0,"S","")) | I45: =IF(SUMPRODUCT((tl_target=$C45)*(tl_sub=I$4)*(tl_align="Primary"))>0,"P",IF(SUMPRODUCT((tl_target=$C45)*(tl_sub=I$4))>0,"S","")) | J45: =IF(SUMPRODUCT((tl_target=$C45)*(tl_sub=J$4)*(tl_align="Primary"))>0,"P",IF(SUMPRODUCT((tl_target=$C45)*(tl_sub=J$4))>0,"S","")) | K45: =IF(SUMPRODUCT((tl_target=$C45)*(tl_sub=K$4)*(tl_align="Primary"))>0,"P",IF(SUMPRODUCT((tl_target=$C45)*(tl_sub=K$4))>0,"S","")) | L45: =IF(SUMPRODUCT((tl_target=$C45)*(tl_sub=L$4)*(tl_align="Primary"))>0,"P",IF(SUMPRODUCT((tl_target=$C45)*(tl_sub=L$4))>0,"S","")) | M45: =IF(SUMPRODUCT((tl_target=$C45)*(tl_sub=M$4)*(tl_align="Primary"))>0,"P",IF(SUMPRODUCT((tl_target=$C45)*(tl_sub=M$4))>0,"S","")) | N45: =IF(SUMPRODUCT((tl_target=$C45)*(tl_sub=N$4)*(tl_align="Primary"))>0,"P",IF(SUMPRODUCT((tl_target=$C45)*(tl_sub=N$4))>0,"S","")) | O45: =IF(SUMPRODUCT((tl_target=$C45)*(tl_sub=O$4)*(tl_align="Primary"))>0,"P",IF(SUMPRODUCT((tl_target=$C45)*(tl_sub=O$4))>0,"S","")) | ... Q45: =IF(SUMPRODUCT((tl_target=$C45)*(tl_sub=Q$4)*(tl_align="Primary"))>0,"P",IF(SUMPRODUCT((tl_target=$C45)*(tl_sub=Q$4))>0,"S","")) | R45: =_xlfn.TEXTJOIN(", ",TRUE(),IF(SUMPRODUCT((tl_target=$C45)*(tl_principle="PP1"))>0,"PP1",""),IF(SUMPRODUCT((tl_target=$C45)*(tl_principle="PP2"))>0,"PP2",""),IF(SUMPRODUCT((tl_target=$C45)*(tl_principle="PP3"))>0,"PP3",""),IF(SUMPRODUCT((tl_target=$C45)*(tl_principle="PP4"))>0,"PP4","")) | S45: =SUMPRODUCT(--(tl_target=$C45)) -> 0 | T45: =IF(SUMPRODUCT((tl_target=$C45)*(tl_align="Primary"))>0,"Primary link",IF(S45>0,"Secondary only","Gap")) -> Gap
A46: 5 | B46: Gender Equality | C46: 5.4 | D46: Outcome | F46: Recognize and value unpaid care and domestic work through the provision of public services, infrastructure and social protection policies and the promotion of shared responsibility within the household and the family as nationally appropriate | G46: 1 | H46: =IF(SUMPRODUCT((tl_target=$C46)*(tl_sub=H$4)*(tl_align="Primary"))>0,"P",IF(SUMPRODUCT((tl_target=$C46)*(tl_sub=H$4))>0,"S","")) | I46: =IF(SUMPRODUCT((tl_target=$C46)*(tl_sub=I$4)*(tl_align="Primary"))>0,"P",IF(SUMPRODUCT((tl_target=$C46)*(tl_sub=I$4))>0,"S","")) | J46: =IF(SUMPRODUCT((tl_target=$C46)*(tl_sub=J$4)*(tl_align="Primary"))>0,"P",IF(SUMPRODUCT((tl_target=$C46)*(tl_sub=J$4))>0,"S","")) | K46: =IF(SUMPRODUCT((tl_target=$C46)*(tl_sub=K$4)*(tl_align="Primary"))>0,"P",IF(SUMPRODUCT((tl_target=$C46)*(tl_sub=K$4))>0,"S","")) | L46: =IF(SUMPRODUCT((tl_target=$C46)*(tl_sub=L$4)*(tl_align="Primary"))>0,"P",IF(SUMPRODUCT((tl_target=$C46)*(tl_sub=L$4))>0,"S","")) | M46: =IF(SUMPRODUCT((tl_target=$C46)*(tl_sub=M$4)*(tl_align="Primary"))>0,"P",IF(SUMPRODUCT((tl_target=$C46)*(tl_sub=M$4))>0,"S","")) | N46: =IF(SUMPRODUCT((tl_target=$C46)*(tl_sub=N$4)*(tl_align="Primary"))>0,"P",IF(SUMPRODUCT((tl_target=$C46)*(tl_sub=N$4))>0,"S","")) | O46: =IF(SUMPRODUCT((tl_target=$C46)*(tl_sub=O$4)*(tl_align="Primary"))>0,"P",IF(SUMPRODUCT((tl_target=$C46)*(tl_sub=O$4))>0,"S","")) | ... Q46: =IF(SUMPRODUCT((tl_target=$C46)*(tl_sub=Q$4)*(tl_align="Primary"))>0,"P",IF(SUMPRODUCT((tl_target=$C46)*(tl_sub=Q$4))>0,"S","")) | R46: =_xlfn.TEXTJOIN(", ",TRUE(),IF(SUMPRODUCT((tl_target=$C46)*(tl_principle="PP1"))>0,"PP1",""),IF(SUMPRODUCT((tl_target=$C46)*(tl_principle="PP2"))>0,"PP2",""),IF(SUMPRODUCT((tl_target=$C46)*(tl_principle="PP3"))>0,"PP3",""),IF(SUMPRODUCT((tl_target=$C46)*(tl_principle="PP4"))>0,"PP4","")) | S46: =SUMPRODUCT(--(tl_target=$C46)) -> 0 | T46: =IF(SUMPRODUCT((tl_target=$C46)*(tl_align="Primary"))>0,"Primary link",IF(S46>0,"Secondary only","Gap")) -> Gap
A47: 5 | B47: Gender Equality | C47: 5.5 | D47: Outcome | F47: Ensure women's full and effective participation and equal opportunities for leadership at all levels of decision-making in political, economic and public life | G47: 2 | H47: =IF(SUMPRODUCT((tl_target=$C47)*(tl_sub=H$4)*(tl_align="Primary"))>0,"P",IF(SUMPRODUCT((tl_target=$C47)*(tl_sub=H$4))>0,"S","")) | I47: =IF(SUMPRODUCT((tl_target=$C47)*(tl_sub=I$4)*(tl_align="Primary"))>0,"P",IF(SUMPRODUCT((tl_target=$C47)*(tl_sub=I$4))>0,"S","")) | J47: =IF(SUMPRODUCT((tl_target=$C47)*(tl_sub=J$4)*(tl_align="Primary"))>0,"P",IF(SUMPRODUCT((tl_target=$C47)*(tl_sub=J$4))>0,"S","")) | K47: =IF(SUMPRODUCT((tl_target=$C47)*(tl_sub=K$4)*(tl_align="Primary"))>0,"P",IF(SUMPRODUCT((tl_target=$C47)*(tl_sub=K$4))>0,"S","")) | L47: =IF(SUMPRODUCT((tl_target=$C47)*(tl_sub=L$4)*(tl_align="Primary"))>0,"P",IF(SUMPRODUCT((tl_target=$C47)*(tl_sub=L$4))>0,"S","")) | M47: =IF(SUMPRODUCT((tl_target=$C47)*(tl_sub=M$4)*(tl_align="Primary"))>0,"P",IF(SUMPRODUCT((tl_target=$C47)*(tl_sub=M$4))>0,"S","")) | N47: =IF(SUMPRODUCT((tl_target=$C47)*(tl_sub=N$4)*(tl_align="Primary"))>0,"P",IF(SUMPRODUCT((tl_target=$C47)*(tl_sub=N$4))>0,"S","")) | O47: =IF(SUMPRODUCT((tl_target=$C47)*(tl_sub=O$4)*(tl_align="Primary"))>0,"P",IF(SUMPRODUCT((tl_target=$C47)*(tl_sub=O$4))>0,"S","")) | ... Q47: =IF(SUMPRODUCT((tl_target=$C47)*(tl_sub=Q$4)*(tl_align="Primary"))>0,"P",IF(SUMPRODUCT((tl_target=$C47)*(tl_sub=Q$4))>0,"S","")) | R47: =_xlfn.TEXTJOIN(", ",TRUE(),IF(SUMPRODUCT((tl_target=$C47)*(tl_principle="PP1"))>0,"PP1",""),IF(SUMPRODUCT((tl_target=$C47)*(tl_principle="PP2"))>0,"PP2",""),IF(SUMPRODUCT((tl_target=$C47)*(tl_principle="PP3"))>0,"PP3",""),IF(SUMPRODUCT((tl_target=$C47)*(tl_principle="PP4"))>0,"PP4","")) | S47: =SUMPRODUCT(--(tl_target=$C47)) -> 0 | T47: =IF(SUMPRODUCT((tl_target=$C47)*(tl_align="Primary"))>0,"Primary link",IF(S47>0,"Secondary only","Gap")) -> Gap
A48: 5 | B48: Gender Equality | C48: 5.6 | D48: Outcome | F48: Ensure universal access to sexual and reproductive health and reproductive rights as agreed in accordance with the Programme of Action of the International Conference on Population and Development and the Beijing Platform for Action and the outcome documents of their review conferences | G48: 2 | H48: =IF(SUMPRODUCT((tl_target=$C48)*(tl_sub=H$4)*(tl_align="Primary"))>0,"P",IF(SUMPRODUCT((tl_target=$C48)*(tl_sub=H$4))>0,"S","")) | I48: =IF(SUMPRODUCT((tl_target=$C48)*(tl_sub=I$4)*(tl_align="Primary"))>0,"P",IF(SUMPRODUCT((tl_target=$C48)*(tl_sub=I$4))>0,"S","")) | J48: =IF(SUMPRODUCT((tl_target=$C48)*(tl_sub=J$4)*(tl_align="Primary"))>0,"P",IF(SUMPRODUCT((tl_target=$C48)*(tl_sub=J$4))>0,"S","")) | K48: =IF(SUMPRODUCT((tl_target=$C48)*(tl_sub=K$4)*(tl_align="Primary"))>0,"P",IF(SUMPRODUCT((tl_target=$C48)*(tl_sub=K$4))>0,"S","")) | L48: =IF(SUMPRODUCT((tl_target=$C48)*(tl_sub=L$4)*(tl_align="Primary"))>0,"P",IF(SUMPRODUCT((tl_target=$C48)*(tl_sub=L$4))>0,"S","")) | M48: =IF(SUMPRODUCT((tl_target=$C48)*(tl_sub=M$4)*(tl_align="Primary"))>0,"P",IF(SUMPRODUCT((tl_target=$C48)*(tl_sub=M$4))>0,"S","")) | N48: =IF(SUMPRODUCT((tl_target=$C48)*(tl_sub=N$4)*(tl_align="Primary"))>0,"P",IF(SUMPRODUCT((tl_target=$C48)*(tl_sub=N$4))>0,"S","")) | O48: =IF(SUMPRODUCT((tl_target=$C48)*(tl_sub=O$4)*(tl_align="Primary"))>0,"P",IF(SUMPRODUCT((tl_target=$C48)*(tl_sub=O$4))>0,"S","")) | ... Q48: =IF(SUMPRODUCT((tl_target=$C48)*(tl_sub=Q$4)*(tl_align="Primary"))>0,"P",IF(SUMPRODUCT((tl_target=$C48)*(tl_sub=Q$4))>0,"S","")) | R48: =_xlfn.TEXTJOIN(", ",TRUE(),IF(SUMPRODUCT((tl_target=$C48)*(tl_principle="PP1"))>0,"PP1",""),IF(SUMPRODUCT((tl_target=$C48)*(tl_principle="PP2"))>0,"PP2",""),IF(SUMPRODUCT((tl_target=$C48)*(tl_principle="PP3"))>0,"PP3",""),IF(SUMPRODUCT((tl_target=$C48)*(tl_principle="PP4"))>0,"PP4","")) | S48: =SUMPRODUCT(--(tl_target=$C48)) -> 0 | T48: =IF(SUMPRODUCT((tl_target=$C48)*(tl_align="Primary"))>0,"Primary link",IF(S48>0,"Secondary only","Gap")) -> Gap
... A54: 6 | B54: Clean Water and Sanitation | C54: 6.3 | D54: Outcome | F54: By 2030, improve water quality by reducing pollution, eliminating dumping and minimizing release of hazardous chemicals and materials, halving the proportion of untreated wastewater and substantially increasing recycling and safe reuse globally | G54: 2 | H54: =IF(SUMPRODUCT((tl_target=$C54)*(tl_sub=H$4)*(tl_align="Primary"))>0,"P",IF(SUMPRODUCT((tl_target=$C54)*(tl_sub=H$4))>0,"S","")) | I54: =IF(SUMPRODUCT((tl_target=$C54)*(tl_sub=I$4)*(tl_align="Primary"))>0,"P",IF(SUMPRODUCT((tl_target=$C54)*(tl_sub=I$4))>0,"S","")) | J54: =IF(SUMPRODUCT((tl_target=$C54)*(tl_sub=J$4)*(tl_align="Primary"))>0,"P",IF(SUMPRODUCT((tl_target=$C54)*(tl_sub=J$4))>0,"S","")) | K54: =IF(SUMPRODUCT((tl_target=$C54)*(tl_sub=K$4)*(tl_align="Primary"))>0,"P",IF(SUMPRODUCT((tl_target=$C54)*(tl_sub=K$4))>0,"S","")) | L54: =IF(SUMPRODUCT((tl_target=$C54)*(tl_sub=L$4)*(tl_align="Primary"))>0,"P",IF(SUMPRODUCT((tl_target=$C54)*(tl_sub=L$4))>0,"S","")) | M54: =IF(SUMPRODUCT((tl_target=$C54)*(tl_sub=M$4)*(tl_align="Primary"))>0,"P",IF(SUMPRODUCT((tl_target=$C54)*(tl_sub=M$4))>0,"S","")) | N54: =IF(SUMPRODUCT((tl_target=$C54)*(tl_sub=N$4)*(tl_align="Primary"))>0,"P",IF(SUMPRODUCT((tl_target=$C54)*(tl_sub=N$4))>0,"S","")) | O54: =IF(SUMPRODUCT((tl_target=$C54)*(tl_sub=O$4)*(tl_align="Primary"))>0,"P",IF(SUMPRODUCT((tl_target=$C54)*(tl_sub=O$4))>0,"S","")) | ... Q54: =IF(SUMPRODUCT((tl_target=$C54)*(tl_sub=Q$4)*(tl_align="Primary"))>0,"P",IF(SUMPRODUCT((tl_target=$C54)*(tl_sub=Q$4))>0,"S","")) | R54: =_xlfn.TEXTJOIN(", ",TRUE(),IF(SUMPRODUCT((tl_target=$C54)*(tl_principle="PP1"))>0,"PP1",""),IF(SUMPRODUCT((tl_target=$C54)*(tl_principle="PP2"))>0,"PP2",""),IF(SUMPRODUCT((tl_target=$C54)*(tl_principle="PP3"))>0,"PP3",""),IF(SUMPRODUCT((tl_target=$C54)*(tl_principle="PP4"))>0,"PP4","")) | S54: =SUMPRODUCT(--(tl_target=$C54)) -> 0 | T54: =IF(SUMPRODUCT((tl_target=$C54)*(tl_align="Primary"))>0,"Primary link",IF(S54>0,"Secondary only","Gap")) -> Gap
